Workbook

Sheet Scorecard
B2: Jonas Fitness
B4: # | C4: Portfolio | D4: Contact | E4: Company | F4: Initiative | G4: Last Qtr Status | H4: Status | I4: Strategic Value Level | J4: Business Problem Solved | K4: Ratio Impacted | L4: KPI Metric | M4: Financial Target | N4: Financial Actual | O4: Strategic Value Pts | P4: Status Weight | Q4: Progress Value | R4: Total Score
B5: 1 | C5: =IF(F5="","","PYXiS") -> PYXiS | D5: =IF(F5="","",'P1'!$C$17) -> James.Peltier@jonasfitness.com | E5: =IF(F5="","",B$2) -> Jonas Fitness | F5: =IF('P1'!$F$3="","",'P1'!$F$3) -> Claude Code Internal to all developers | G5: =IF(F5="","",'P1'!$AO$5) -> Pilot | H5: =IF(F5="","",'P1'!$AO$4) -> Live | I5: =IF(F5="","",'P1'!$F$8) -> Internal Process | J5: =IF(F5="","",'P1'!$F$5) -> Increase efficiency by 30% among customer deliverables | K5: =IF(F5="","",'P1'!$AC$7) -> R&D | L5: =IF(F5="","",'P1'!$G$13) -> Employee AI Tool Adoption Rate | M5: ='P1'!$BE$35*1000 -> 0 | N5: ='P1'!$E$51*1000 -> 0 | O5: ='P1'!$AV$3 -> 50 | P5: ='P1'!$AV$4 -> 1 | Q5: ='P1'!$AV$5 -> 1.2 | R5: =O5*P5*Q5 -> 60
B6: 2 | C6: =IF(F6="","","PYXiS") -> PYXiS | D6: =IF(F6="","",'P2'!$C$17) -> James.Peltier@jonasfitness.com | E6: =IF(F6="","",B$2) -> Jonas Fitness | F6: =IF('P2'!$F$3="","",'P2'!$F$3) -> Sales Team Enterprise ChatGPT | G6: =IF(F6="","",'P2'!$AO$5) -> Pilot | H6: =IF(F6="","",'P2'!$AO$4) -> Live | I6: =IF(F6="","",'P2'!$F$8) -> Simple Tool | J6: =IF(F6="","",'P2'!$F$5) -> Reduce time needed to review contracts, complete RFP requests and conduct payment pricing reviews/comparisions. | K6: =IF(F6="","",'P2'!$AC$7) -> S&M | L6: =IF(F6="","",'P2'!$G$13) -> Employee AI Tool Adoption Rate | M6: ='P2'!$BE$35*1000 -> 0 | N6: ='P2'!$E$51*1000 -> 0 | O6: ='P2'!$AV$3 -> 10 | P6: ='P2'!$AV$4 -> 1 | Q6: ='P2'!$AV$5 -> 1.2 | R6: =O6*P6*Q6 -> 12
B7: 3 | C7: =IF(F7="","","PYXiS") -> PYXiS | D7: =IF(F7="","",'P3'!$C$17) -> Kim.forster@jonasfitness.com | E7: =IF(F7="","",B$2) -> Jonas Fitness | F7: =IF('P3'!$F$3="","",'P3'!$F$3) -> Operations/Maintenance Enterprise ChatGPT | G7: =IF(F7="","",'P3'!$AO$5) -> Pilot | H7: =IF(F7="","",'P3'!$AO$4) -> Live | I7: =IF(F7="","",'P3'!$F$8) -> Simple Tool | J7: =IF(F7="","",'P3'!$F$5) -> Use ChatGPT to create training documents, emails, templates creation, and assist with billing and payment reconcilation projects. | K7: =IF(F7="","",'P3'!$AC$7) -> Maintenance | L7: =IF(F7="","",'P3'!$G$13) -> Successful Adaptation to New Use Cases | M7: ='P3'!$BE$35*1000 -> 0 | N7: ='P3'!$E$51*1000 -> 0 | O7: ='P3'!$AV$3 -> 10 | P7: ='P3'!$AV$4 -> 1 | Q7: ='P3'!$AV$5 -> 1.2 | R7: =O7*P7*Q7 -> 12
B8: 4 | C8: =IF(F8="","","PYXiS") -> PYXiS | D8: =IF(F8="","",'P4'!$C$17) -> James.Peltier@jonasfitness.com | E8: =IF(F8="","",B$2) -> Jonas Fitness | F8: =IF('P4'!$F$3="","",'P4'!$F$3) -> IRIS Chat Bot | G8: =IF(F8="","",'P4'!$AO$5) -> Pilot | H8: =IF(F8="","",'P4'!$AO$4) -> Pilot | I8: =IF(F8="","",'P4'!$F$8) -> Customer Feature - New | J8: =IF(F8="","",'P4'!$F$5) -> Integrated chatbot delivers real-time, in-product guidance for client “how-to” inquiries, improving user self-service and decreasing call center demand. | K8: =IF(F8="","",'P4'!$AC$7) -> Maintenance | L8: =IF(F8="","",'P4'!$G$13) -> Audit Frequency and Results | M8: ='P4'!$BE$35*1000 -> 0 | N8: ='P4'!$E$51*1000 -> 0 | O8: ='P4'!$AV$3 -> 200 | P8: ='P4'!$AV$4 -> 0.7 | Q8: ='P4'!$AV$5 -> 1 | R8: =O8*P8*Q8 -> 140
B9: 5 | C9: =IF(F9="","","PYXiS") -> PYXiS | D9: =IF(F8="","",'P4'!$C$17) -> James.Peltier@jonasfitness.com | E9: =IF(F9="","",B$2) -> Jonas Fitness | F9: =IF('P5'!$F$3="","",'P5'!$F$3) -> IRIS 2.0, IRIS with Voice | G9: =IF(F9="","",'P5'!$AO$5) -> Idea | H9: =IF(F9="","",'P5'!$AO$4) -> Dev | I9: =IF(F9="","",'P5'!$F$8) -> Internal Process | J9: =IF(F9="","",'P5'!$F$5) -> Allows the end user to ask IRIS questions using voice vs. typing in a request. | K9: =IF(F9="","",'P5'!$AC$7) -> Maintenance | L9: =IF(F9="","",'P5'!$G$13) -> Audit Frequency and Results | M9: ='P5'!$BE$35*1000 -> 0 | N9: ='P5'!$E$51*1000 -> 0 | O9: ='P5'!$AV$3 -> 50 | P9: ='P5'!$AV$4 -> 0.4 | Q9: ='P5'!$AV$5 -> 1.2 | R9: =O9*P9*Q9 -> 24
B10: 6 | C10: =IF(F10="","","PYXiS") -> PYXiS | D10: =IF(F10="","",'P6'!$C$17) -> James.Peltier@jonasfitness.com | E10: =IF(F10="","",B$2) -> Jonas Fitness | F10: =IF('P6'!$F$3="","",'P6'!$F$3) -> Compete AI Project: Phase I - Front Desk Redesign | G10: =IF(F10="","",'P6'!$AO$5) -> Dev | H10: =IF(F10="","",'P6'!$AO$4) -> Dev | I10: =IF(F10="","",'P6'!$F$8) -> Customer Feature - Existing | J10: =IF(F10="","",'P6'!$F$5) -> Addressing key attrition concern: FD is cubersome, too many clicks to complete functions and not steamlined for FD staff. | K10: =IF(F10="","",'P6'!$AC$7) -> S&M | L10: =IF(F10="","",'P6'!$G$13) -> # of Customers using the AI | M10: ='P6'!$BE$35*1000 -> 0 | N10: ='P6'!$E$51*1000 -> 0 | O10: ='P6'!$AV$3 -> 100 | P10: ='P6'!$AV$4 -> 0.4 | Q10: ='P6'!$AV$5 -> 1 | R10: =O10*P10*Q10 -> 40
B11: 7 | C11: =IF(F11="","","PYXiS") -> PYXiS | D11: =IF(F8="","",'P4'!$C$17) -> James.Peltier@jonasfitness.com | E11: =IF(F11="","",B$2) -> Jonas Fitness | F11: =IF('P7'!$F$3="","",'P7'!$F$3) -> Compete AI Project Phase II: Front Desk Redesign, use of APIs to appear as a web-based product. | G11: =IF(F11="","",'P7'!$AO$5) -> Dev | H11: =IF(F11="","",'P7'!$AO$4) -> Dev | I11: =IF(F11="","",'P7'!$F$8) -> Customer Feature - Existing | J11: =IF(F11="","",'P7'!$F$5) -> Addressing the key reason given for new logo lost deals: Compete is not a true web-based product. Currently requires a thin client to be installed to function. | K11: =IF(F11="","",'P7'!$AC$7) -> S&M | L11: =IF(F11="","",'P7'!$G$13) -> .... Select the primary KPI (Jonas Library) | M11: ='P7'!$BE$35*1000 -> 100000 | N11: ='P7'!$E$51*1000 -> 0 | O11: ='P7'!$AV$3 -> 100 | P11: ='P7'!$AV$4 -> 0.4 | Q11: ='P7'!$AV$5 -> 1 | R11: =O11*P11*Q11 -> 40
B12: 8 | C12: =IF(F12="","","PYXiS") -> PYXiS | D12: =IF(F12="","",'P8'!$C$17) -> James.Peltier@jonasfitness.com | E12: =IF(F12="","",B$2) -> Jonas Fitness | F12: =IF('P8'!$F$3="","",'P8'!$F$3) -> Compete AI Project Phase III: Billing Analytic Tool | G12: =IF(F12="","",'P8'!$AO$5) -> Idea | H12: =IF(F12="","",'P8'!$AO$4) -> Dev | I12: =IF(F12="","",'P8'!$F$8) -> Customer Feature - New | J12: =IF(F12="","",'P8'!$F$5) -> Identify trends in billing data without manual intervention. This tool can be sold to both MBS and Non MBS clients as replacement for current BI reporting solutions. | K12: =IF(F12="","",'P8'!$AC$7) -> S&M | L12: =IF(F12="","",'P8'!$G$13) -> # of Customers using the AI | M12: ='P8'!$BE$35*1000 -> 200000 | N12: ='P8'!$E$51*1000 -> 0 | O12: ='P8'!$AV$3 -> 200 | P12: ='P8'!$AV$4 -> 0.4 | Q12: ='P8'!$AV$5 -> 1.2 | R12: =O12*P12*Q12 -> 96
B13: 9 | C13: =IF(F13="","","PYXiS") -> PYXiS | D13: =IF(F13="","",'P9'!$C$17) -> Kim.Forster@jonasfitness.com | E13: =IF(F13="","",B$2) -> Jonas Fitness | F13: =IF('P9'!$F$3="","",'P9'!$F$3) -> AI Client/Marketing Communication Tool | G13: =IF(F13="","",'P9'!$AO$5) -> Not Def | H13: =IF(F13="","",'P9'!$AO$4) -> Idea | I13: =IF(F13="","",'P9'!$F$8) -> Simple Tool | J13: =IF(F13="","",'P9'!$F$5) -> A tool that will help us automate the process of posting, texting, emailing of information for marketing and or customer update information. | K13: =IF(F13="","",'P9'!$AC$7) -> S&M | L13: =IF(F13="","",'P9'!$G$13) -> Employee AI Tool Adoption Rate | M13: ='P9'!$BE$35*1000 -> 0 | N13: ='P9'!$E$51*1000 -> 0 | O13: ='P9'!$AV$3 -> 10 | P13: ='P9'!$AV$4 -> 0.1 | Q13: ='P9'!$AV$5 -> 1.2 | R13: =O13*P13*Q13 -> 1.2
B14: 10 | C14: =IF(F14="","","PYXiS") -> PYXiS | D14: =IF(F14="","",'P10'!$C$17) -> Sandra.Crutcher@jonasfitness.com | E14: =IF(F14="","",B$2) -> Jonas Fitness | F14: =IF('P10'!$F$3="","",'P10'!$F$3) -> AI Tool for Lead Generation and Qualification | G14: =IF(F14="","",'P10'!$AO$5) -> Not Def | H14: =IF(F14="","",'P10'!$AO$4) -> Idea | I14: =IF(F14="","",'P10'!$F$8) -> Simple Tool | J14: =IF(F14="","",'P10'!$F$5) -> Need a tool that can create leads and qualify them, routing them to our sales team. | K14: =IF(F14="","",'P10'!$AC$7) -> S&M | L14: =IF(F14="","",'P10'!$G$13) -> Data Quality Score (Valid-data ratio) | M14: ='P10'!$BE$35*1000 -> 0 | N14: ='P10'!$E$51*1000 -> 0 | O14: ='P10'!$AV$3 -> 10 | P14: ='P10'!$AV$4 -> 0.1 | Q14: ='P10'!$AV$5 -> 1.2 | R14: =O14*P14*Q14 -> 1.2
L15: TOTAL FINANCIAL | M15: =SUM(M5:M14) -> 300000 | N15: =SUM(N5:N14) -> 0 | O15: TOTAL AI SCORE FOR BU | R15: =SUM(R5:R14) -> 426.4
B16: Complete all sections in yellow
B18: Cells in this color are free form text
B20: Cells in this color are limited to the drop down values provided
B22: This is a sample and can be deleted.
B24: Inout all values in $'000s

Sheet P1
B3: PROJECT | F3: Claude Code Internal to all developers | AG3: Strategic Value | AO3: =F8 -> Internal Process | AV3: =IF(F7="",0,VLOOKUP(F7,Lookups!B4:H8,3)) -> 50 | AZ3: =NOW() -> 45961.476
AG4: Stage Multiplier (today) | AO4: =VLOOKUP(COUNTIF(AR10:AT21,"<="&AZ3),Table3357[],2) -> Live | AV4: =IF(AO4="Not Def",0,VLOOKUP(AO4,Lookups!L4:M8,2)) -> 1 | AZ4: Current Qtr | BC4: =VLOOKUP((YEAR(AZ3)&"-"&MONTH(AZ3)),Lookups!S3:U21,2) -> 2025-Q4
B5: Description (Use Case) | F5: Increase efficiency by 30% among customer deliverables | AG5: Stage Last Quarter | AO5: =VLOOKUP(COUNTIF(AR10:AT21,"<"&VLOOKUP(BC4,Lookups!W3:Y9,2)),Table3357[],2) -> Pilot | AQ5: =IF(AV5=1,"No Change","Progression") -> Progression | AV5: =IF(AO4="Not Def",0,IF(AO5=AO4,1,1.2)) -> 1.2
AG6: PROJECT SCORE | AV6: =AV3*AV4*AV5 -> 60
B7: Category | F7: L3. AI-powered internal business process improvements | Y7: Ratio Impacted | AC7: R&D
B8: Strategic Value Level | F8: =IF(F7="","",VLOOKUP(F7,Lookups!B4:H8,2)) -> Internal Process
B9: Examples | F9: =IF(F7="","",VLOOKUP(F7,Lookups!B4:H8,4)) -> Automated customer support triage, intelligent lead scoring, predictive maintenance, churn analysis, scheduling | AG9: Stage | AJ9: Tasks | AO9: Target | AR9: Completed | AU9: Days to Target | AY9: Notes
AG10: Idea | AJ10: Project Defined | AO10: 45915 | AR10: 45915 | AU10: =IF(AO10=$BK$3,"Missing Target",IF(AR10=$BK$3,IF($AZ$3>AO10,INT($AZ$3-AO10)&" Day(s) Overdue","Incomplete"),IF(AR10>AO10,INT(AR10-AO10)&" Day(s) Late",IF(AR10=AO10,"OK",INT(AO10-AR10)&" Day(s) Ahead")))) -> OK
B11: PROJECT RESOURCES | F11: KEY PERFORMANCE INDICATORS / MEASURES OF SUCCESS | AJ11: Business Case approved | AO11: 45915 | AR11: 45915 | AU11: =IF(AO11=$BK$3,"Missing Target",IF(AR11=$BK$3,IF($AZ$3>AO11,INT($AZ$3-AO11)&" Day(s) Overdue","Incomplete"),IF(AR11>AO11,INT(AR11-AO11)&" Day(s) Late",IF(AR11=AO11,"OK",INT(AO11-AR11)&" Day(s) Ahead")))) -> OK
B12: AI Tools & Services | F12: =IF(F7="","",VLOOKUP(F7,Lookups!B4:H8,5)) -> Employee Satisfaction | O12: =IF(F7="","",VLOOKUP(F7,Lookups!B4:H8,6)) -> Productivity Gains | X12: =IF(F7="","",VLOOKUP(F7,Lookups!B4:H8,7)) -> Cost Savings | AJ12: Resources Allocated | AO12: 45915 | AR12: 45915 | AU12: =IF(AO12=$BK$3,"Missing Target",IF(AR12=$BK$3,IF($AZ$3>AO12,INT($AZ$3-AO12)&" Day(s) Overdue","Incomplete"),IF(AR12>AO12,INT(AR12-AO12)&" Day(s) Late",IF(AR12=AO12,"OK",INT(AO12-AR12)&" Day(s) Ahead")))) -> OK
B13: Claude Code | F13: KPI | G13: Employee AI Tool Adoption Rate | O13: KPI | P13: Throughput | X13: KPI | Y13: .... Select the primary KPI (Jonas Library) | AG13: Develop | AJ13: Technical PoC validated | AO13: 45920 | AR13: 45920 | AU13: =IF(AO13=$BK$3,"Missing Target",IF(AR13=$BK$3,IF($AZ$3>AO13,INT($AZ$3-AO13)&" Day(s) Overdue","Incomplete"),IF(AR13>AO13,INT(AR13-AO13)&" Day(s) Late",IF(AR13=AO13,"OK",INT(AO13-AR13)&" Day(s) Ahead")))) -> OK
F14: How does this Project support this KPI? | O14: How does this Project support this KPI? | X14: How does this Project support this KPI? | AJ14: Dev roadmap documented | AO14: 45920 | AR14: 45920 | AU14: =IF(AO14=$BK$3,"Missing Target",IF(AR14=$BK$3,IF($AZ$3>AO14,INT($AZ$3-AO14)&" Day(s) Overdue","Incomplete"),IF(AR14>AO14,INT(AR14-AO14)&" Day(s) Late",IF(AR14=AO14,"OK",INT(AO14-AR14)&" Day(s) Ahead")))) -> OK
F15: 16 Developers | O15: 30% Increase in Throughput | AJ15: Coding started | AO15: 45920 | AR15: 45920 | AU15: =IF(AO15=$A$1,"Missing Target",IF(AR15=$A$1,IF($AZ$3>AO15,INT($AZ$3-AO15)&" Day(s) Overdue","Incomplete"),IF(AR15>AO15,INT(AR15-AO15)&" Day(s) Late",IF(AR15=AO15,"OK",INT(AO15-AR15)&" Day(s) Ahead")))) -> OK
AG16: Pilot | AJ16: Deployment to beta | AO16: 45930 | AR16: 45930 | AU16: =IF(AO16=$A$1,"Missing Target",IF(AR16=$A$1,IF($AZ$3>AO16,INT($AZ$3-AO16)&" Day(s) Overdue","Incomplete"),IF(AR16>AO16,INT(AR16-AO16)&" Day(s) Late",IF(AR16=AO16,"OK",INT(AO16-AR16)&" Day(s) Ahead")))) -> OK
B17: Contact | C17: James.Peltier@jonasfitness.com | AJ17: Initial metrics/feedback | AO17: 45930 | AR17: 45930 | AU17: =IF(AO17=$A$1,"Missing Target",IF(AR17=$A$1,IF($AZ$3>AO17,INT($AZ$3-AO17)&" Day(s) Overdue","Incomplete"),IF(AR17>AO17,INT(AR17-AO17)&" Day(s) Late",IF(AR17=AO17,"OK",INT(AO17-AR17)&" Day(s) Ahead")))) -> OK
B18: Prod Mgr | C18: Karamvir Dhanoa | F18: How will you measure the KPI? | O18: How will you measure the KPI? | X18: How will you measure the KPI? | AJ18: Feedback affecting code | AO18: 45930 | AR18: 45930 | AU18: =IF(AO18=$A$1,"Missing Target",IF(AR18=$A$1,IF($AZ$3>AO18,INT($AZ$3-AO18)&" Day(s) Overdue","Incomplete"),IF(AR18>AO18,INT(AR18-AO18)&" Day(s) Late",IF(AR18=AO18,"OK",INT(AO18-AR18)&" Day(s) Ahead")))) -> OK
B19: Analyst | C19: Chase Winston | F19: All 16 developers to have Claude Code. | O19: Measuring kanban board KPI's. Would expect a 30% increase in PBI throughput | AG19: Live | AJ19: General release available | AO19: 45931 | AR19: 45931 | AU19: =IF(AO19=$A$1,"Missing Target",IF(AR19=$A$1,IF($AZ$3>AO19,INT($AZ$3-AO19)&" Day(s) Overdue","Incomplete"),IF(AR19>AO19,INT(AR19-AO19)&" Day(s) Late",IF(AR19=AO19,"OK",INT(AO19-AR19)&" Day(s) Ahead")))) -> OK
B20: Tech Lead | C20: Jim Peltier | AJ20: Success metrics tracking | AO20: 45931 | AR20: 45931 | AU20: =IF(AO20=$A$1,"Missing Target",IF(AR20=$A$1,IF($AZ$3>AO20,INT($AZ$3-AO20)&" Day(s) Overdue","Incomplete"),IF(AR20>AO20,INT(AR20-AO20)&" Day(s) Late",IF(AR20=AO20,"OK",INT(AO20-AR20)&" Day(s) Ahead")))) -> OK
B21: Exec | C21: Sandy Crutcher | AJ21: Feedback loop continuing | AO21: 45931 | AR21: 45931 | AU21: =IF(AO21=$A$1,"Missing Target",IF(AR21=$A$1,IF($AZ$3>AO21,INT($AZ$3-AO21)&" Day(s) Overdue","Incomplete"),IF(AR21>AO21,INT(AR21-AO21)&" Day(s) Late",IF(AR21=AO21,"OK",INT(AO21-AR21)&" Day(s) Ahead")))) -> OK
B23: WEEKLY KPI TRACKER | F23: 1 | G23: =F23+1 -> 2 | H23: =G23+1 -> 3 | I23: =H23+1 -> 4 | J23: =I23+1 -> 5 | K23: =J23+1 -> 6 | L23: =K23+1 -> 7 | M23: =L23+1 -> 8 | N23: =M23+1 -> 9 | ... BE23: =BD23+1 -> 52
B24: Week Ending | F24: 45915 | G24: =F24+7 -> 45922 | H24: =G24+7 -> 45929 | I24: =H24+7 -> 45936 | J24: =I24+7 -> 45943 | K24: =J24+7 -> 45950 | L24: =K24+7 -> 45957 | M24: =L24+7 -> 45964 | N24: =M24+7 -> 45971 | ... BE24: =BD24+7 -> 46272
B25: =G13&" TARGET" -> Employee AI Tool Adoption Rate TARGET | F25: 16 | G25: =F25 -> 16 | H25: =G25 -> 16 | I25: =H25 -> 16 | J25: =I25 -> 16 | K25: =J25 -> 16 | L25: =K25 -> 16 | M25: =L25 -> 16 | N25: 60 | O25: 60 | P25: 65 | Q25: 65 | R25: 66 | S25: 67 | T25: 68 | U25: 69 | V25: 70 | W25: 71 | X25: 72 | Y25: 73 | Z25: 74 | AA25: 75 | AB25: 76 | AC25: 77 | AD25: 78 | AE25: 79 | AF25: 80 | AG25: 80 | AH25: 80 | AI25: 80 | AJ25: 80 | AK25: 80 | AL25: 80 | AM25: 80 | AN25: 80 | AO25: 80 | AP25: 80 | AQ25: 80 | AR25: 80 | AS25: 80 | AT25: 80 | AU25: 80 | AV25: 80 | AW25: 80 | AX25: 80 | AY25: 80 | AZ25: 80 | BA25: 80 | BB25: 80 | BC25: 80 | BD25: 80 | BE25: 80
B26: Actual | F26: 1 | G26: 3 | H26: 6 | I26: 16 | J26: 16 | K26: 16 | L26: 16 | M26: 16 | N26: 16 | O26: 0 | P26: 0 | Q26: 0 | R26: 0 | S26: 0 | T26: 0 | U26: 0 | V26: 0 | W26: 0 | X26: 0 | Y26: 0 | Z26: 0 | AA26: 0 | AB26: 0 | AC26: 0 | AD26: 0 | AE26: 0 | AF26: 0 | AG26: 0 | AH26: 0 | AI26: 0 | AJ26: 0 | AK26: 0 | AL26: 0 | AM26: 0 | AN26: 0 | AO26: 0 | AP26: 0 | AQ26: 0 | AR26: 0 | AS26: 0 | AT26: 0 | AU26: 0 | AV26: 0 | AW26: 0 | AX26: 0 | AY26: 0 | AZ26: 0 | BA26: 0 | BB26: 0 | BC26: 0 | BD26: 0 | BE26: 0
B27: Delta | F27: =F26-F25 -> -15 | G27: =G26-G25 -> -13 | H27: =H26-H25 -> -10 | I27: =I26-I25 -> 0 | J27: =J26-J25 -> 0 | K27: =K26-K25 -> 0 | L27: =L26-L25 -> 0 | M27: =M26-M25 -> 0 | ... BE27: =BE26-BE25 -> -80
B28: Notes on this KPI (anything to add this week?)
B30: =P13&" TARGET" -> Throughput TARGET | F30: 30 | G30: =F30 -> 30 | H30: =G30 -> 30 | I30: =H30 -> 30 | J30: =I30 -> 30 | K30: =J30 -> 30 | L30: =K30 -> 30 | M30: =L30 -> 30 | N30: =M30 -> 30 | ... BE30: =BD30 -> 30
B31: Actual | F31: 30 | G31: 30 | H31: 30 | I31: 30 | J31: 30 | K31: 30 | L31: 30 | M31: 0
B32: Delta | F32: =F31-F30 -> 0 | G32: =G31-G30 -> 0 | H32: =H31-H30 -> 0 | I32: =I31-I30 -> 0 | J32: =J31-J30 -> 0 | K32: =K31-K30 -> 0 | L32: =L31-L30 -> 0 | M32: =M31-M30 -> -30 | ... BE32: =BE31-BE30 -> -30
B33: Notes on this KPI (anything to add this week?)
B35: =Y13&" TARGET" -> .... Select the primary KPI (Jonas Library) TARGET | F35: 0 | G35: =F35 -> 0 | H35: =G35 -> 0 | I35: =H35 -> 0 | J35: =I35 -> 0 | K35: =J35 -> 0 | L35: =K35 -> 0 | M35: =L35 -> 0 | N35: =M35 -> 0 | ... BE35: =BD35 -> 0
B36: Actual | F36: 0 | G36: 0 | H36: 0 | I36: 0 | J36: 0 | K36: 0 | L36: 0 | M36: 0
B37: Delta | F37: =F36-F35 -> 0 | G37: =G36-G35 -> 0 | H37: =H36-H35 -> 0 | I37: =I36-I35 -> 0 | J37: =J36-J35 -> 0 | K37: =K36-K35 -> 0 | L37: =L36-L35 -> 0 | M37: =M36-M35 -> 0 | ... BE37: =BE36-BE35 -> 0
B38: Notes on this KPI (anything to add this week?)
B41: Revenue Target | F41: =IF($X$12="Revenue Impact",F35,0) -> 0 | G41: =IF($X$12="Revenue Impact",G35,0) -> 0 | H41: =IF($X$12="Revenue Impact",H35,0) -> 0 | I41: =IF($X$12="Revenue Impact",I35,0) -> 0 | J41: =IF($X$12="Revenue Impact",J35,0) -> 0 | K41: =IF($X$12="Revenue Impact",K35,0) -> 0 | L41: =IF($X$12="Revenue Impact",L35,0) -> 0 | M41: =IF($X$12="Revenue Impact",M35,0) -> 0 | ... BE41: =IF($X$12="Revenue Impact",BE35,0) -> 0
B42: Revenue Actual | F42: =IF($X$12="Revenue Impact",F36,0) -> 0 | G42: =IF($X$12="Revenue Impact",G36,0) -> 0 | H42: =IF($X$12="Revenue Impact",H36,0) -> 0 | I42: =IF($X$12="Revenue Impact",I36,0) -> 0 | J42: =IF($X$12="Revenue Impact",J36,0) -> 0 | K42: =IF($X$12="Revenue Impact",K36,0) -> 0 | L42: =IF($X$12="Revenue Impact",L36,0) -> 0 | M42: =IF($X$12="Revenue Impact",M36,0) -> 0 | ... BE42: =IF($X$12="Revenue Impact",BE36,0) -> 0
B44: Cost Target | F44: =IF($X$12="Cost Savings",F35,0) -> 0 | G44: =IF($X$12="Cost Savings",G35,0) -> 0 | H44: =IF($X$12="Cost Savings",H35,0) -> 0 | I44: =IF($X$12="Cost Savings",I35,0) -> 0 | J44: =IF($X$12="Cost Savings",J35,0) -> 0 | K44: =IF($X$12="Cost Savings",K35,0) -> 0 | L44: =IF($X$12="Cost Savings",L35,0) -> 0 | M44: =IF($X$12="Cost Savings",M35,0) -> 0 | ... BE44: =IF($X$12="Cost Savings",BE35,0) -> 0
B45: Cost Actual | F45: =IF($X$12="Cost Savings",F36,0) -> 0 | G45: =IF($X$12="Cost Savings",G36,0) -> 0 | H45: =IF($X$12="Cost Savings",H36,0) -> 0 | I45: =IF($X$12="Cost Savings",I36,0) -> 0 | J45: =IF($X$12="Cost Savings",J36,0) -> 0 | K45: =IF($X$12="Cost Savings",K36,0) -> 0 | L45: =IF($X$12="Cost Savings",L36,0) -> 0 | M45: =IF($X$12="Cost Savings",M36,0) -> 0 | ... BE45: =IF($X$12="Cost Savings",BE36,0) -> 0
B47: Financial Target | F47: =F41+F44 -> 0 | G47: =G41+G44 -> 0 | H47: =H41+H44 -> 0 | I47: =I41+I44 -> 0 | J47: =J41+J44 -> 0 | K47: =K41+K44 -> 0 | L47: =L41+L44 -> 0 | M47: =M41+M44 -> 0 | ... BE47: =BE41+BE44 -> 0
B48: Financial Actual | F48: =F42+F45 -> 0 | G48: =G42+G45 -> 0 | H48: =H42+H45 -> 0 | I48: =I42+I45 -> 0 | J48: =J42+J45 -> 0 | K48: =K42+K45 -> 0 | L48: =L42+L45 -> 0 | M48: =M42+M45 -> 0 | ... BE48: =BE42+BE45 -> 0
E49: To Date
B50: Current Financial Target | E50: =MAX(F50:BE50) -> 0 | F50: =IF($AZ$3>F24,F47,0) -> 0 | G50: =IF($AZ$3>G24,G47,0) -> 0 | H50: =IF($AZ$3>H24,H47,0) -> 0 | I50: =IF($AZ$3>I24,I47,0) -> 0 | J50: =IF($AZ$3>J24,J47,0) -> 0 | K50: =IF($AZ$3>K24,K47,0) -> 0 | L50: =IF($AZ$3>L24,L47,0) -> 0 | M50: =IF($AZ$3>M24,M47,0) -> 0 | ... BE50: =IF($AZ$3>BE24,BE47,0) -> 0
B51: Current Financial Actual | E51: =MAX(F51:BE51) -> 0 | F51: =IF($AZ$3>F25,F48,0) -> 0 | G51: =IF($AZ$3>G25,G48,0) -> 0 | H51: =IF($AZ$3>H25,H48,0) -> 0 | I51: =IF($AZ$3>I25,I48,0) -> 0 | J51: =IF($AZ$3>J25,J48,0) -> 0 | K51: =IF($AZ$3>K25,K48,0) -> 0 | L51: =IF($AZ$3>L25,L48,0) -> 0 | M51: =IF($AZ$3>M25,M48,0) -> 0 | ... BE51: =IF($AZ$3>BE25,BE48,0) -> 0

Sheet P2
B3: PROJECT | F3: Sales Team Enterprise ChatGPT | AG3: Strategic Value | AO3: =F8 -> Simple Tool | AV3: =IF(F7="",0,VLOOKUP(F7,Lookups!B4:H8,3)) -> 10 | AZ3: =NOW() -> 45961.476
AG4: Stage Multiplier (today) | AO4: =VLOOKUP(COUNTIF(AR10:AT21,"<="&AZ3),Table3357[],2) -> Live | AV4: =IF(AO4="Not Def",0,VLOOKUP(AO4,Lookups!L4:M8,2)) -> 1 | AZ4: Current Qtr | BC4: =VLOOKUP((YEAR(AZ3)&"-"&MONTH(AZ3)),Lookups!S3:U21,2) -> 2025-Q4
B5: Description (Use Case) | F5: Reduce time needed to review contracts, complete RFP requests and conduct payment pricing reviews/comparisions. | AG5: Stage Last Quarter | AO5: =VLOOKUP(COUNTIF(AR10:AT21,"<"&VLOOKUP(BC4,Lookups!W3:Y9,2)),Table3357[],2) -> Pilot | AQ5: =IF(AV5=1,"No Change","Progression") -> Progression | AV5: =IF(AO4="Not Def",0,IF(AO5=AO4,1,1.2)) -> 1.2
AG6: PROJECT SCORE | AV6: =AV3*AV4*AV5 -> 12
B7: Category | F7: L1. Using external AI tools for basic internal productivity | Y7: Ratio Impacted | AC7: S&M
B8: Strategic Value Level | F8: =IF(F7="","",VLOOKUP(F7,Lookups!B4:H8,2)) -> Simple Tool
B9: Examples | F9: =IF(F7="","",VLOOKUP(F7,Lookups!B4:H8,4)) -> ChatGPT for content, Co-Pilot for drafting emails, AI meeting summaries | AG9: Stage | AJ9: Tasks | AO9: Target | AR9: Completed | AU9: Days to Target | AY9: Notes
AG10: Idea | AJ10: Project Defined | AO10: 45870 | AR10: 45870 | AU10: =IF(AO10=$BK$3,"Missing Target",IF(AR10=$BK$3,IF($AZ$3>AO10,INT($AZ$3-AO10)&" Day(s) Overdue","Incomplete"),IF(AR10>AO10,INT(AR10-AO10)&" Day(s) Late",IF(AR10=AO10,"OK",INT(AO10-AR10)&" Day(s) Ahead")))) -> OK
B11: PROJECT RESOURCES | F11: KEY PERFORMANCE INDICATORS / MEASURES OF SUCCESS | AJ11: Business Case approved | AO11: 45870 | AR11: 45870 | AU11: =IF(AO11=$BK$3,"Missing Target",IF(AR11=$BK$3,IF($AZ$3>AO11,INT($AZ$3-AO11)&" Day(s) Overdue","Incomplete"),IF(AR11>AO11,INT(AR11-AO11)&" Day(s) Late",IF(AR11=AO11,"OK",INT(AO11-AR11)&" Day(s) Ahead")))) -> OK
B12: AI Tools & Services | F12: =IF(F7="","",VLOOKUP(F7,Lookups!B4:H8,5)) -> Adoption Rate | O12: =IF(F7="","",VLOOKUP(F7,Lookups!B4:H8,6)) -> Productivity Gains | X12: =IF(F7="","",VLOOKUP(F7,Lookups!B4:H8,7)) -> Cost Savings | AJ12: Resources Allocated | AO12: 45870 | AR12: 45870 | AU12: =IF(AO12=$BK$3,"Missing Target",IF(AR12=$BK$3,IF($AZ$3>AO12,INT($AZ$3-AO12)&" Day(s) Overdue","Incomplete"),IF(AR12>AO12,INT(AR12-AO12)&" Day(s) Late",IF(AR12=AO12,"OK",INT(AO12-AR12)&" Day(s) Ahead")))) -> OK
B13: Enterprise ChatGPT | F13: KPI | G13: Employee AI Tool Adoption Rate | O13: KPI | P13: Employee Productivity Gains | X13: KPI | Y13: .... Select the primary KPI (Jonas Library) | AG13: Develop | AJ13: Technical PoC validated | AO13: 45871 | AR13: 45871 | AU13: =IF(AO13=$BK$3,"Missing Target",IF(AR13=$BK$3,IF($AZ$3>AO13,INT($AZ$3-AO13)&" Day(s) Overdue","Incomplete"),IF(AR13>AO13,INT(AR13-AO13)&" Day(s) Late",IF(AR13=AO13,"OK",INT(AO13-AR13)&" Day(s) Ahead")))) -> OK
F14: How does this Project support this KPI? | O14: How does this Project support this KPI? | X14: How does this Project support this KPI? | AJ14: Dev roadmap documented | AO14: 45872 | AR14: 45872 | AU14: =IF(AO14=$BK$3,"Missing Target",IF(AR14=$BK$3,IF($AZ$3>AO14,INT($AZ$3-AO14)&" Day(s) Overdue","Incomplete"),IF(AR14>AO14,INT(AR14-AO14)&" Day(s) Late",IF(AR14=AO14,"OK",INT(AO14-AR14)&" Day(s) Ahead")))) -> OK
F15: 6 Sales FTE to have access to the tool and be trained on how to use it for administrative functions. | O15: ChatGPT helps improve accuracy and saves considerable time by automating billing statement comparisons, answering contract questions, and drafting RFP documents. | AJ15: Coding started | AO15: 45873 | AR15: 45873 | AU15: =IF(AO15=$A$1,"Missing Target",IF(AR15=$A$1,IF($AZ$3>AO15,INT($AZ$3-AO15)&" Day(s) Overdue","Incomplete"),IF(AR15>AO15,INT(AR15-AO15)&" Day(s) Late",IF(AR15=AO15,"OK",INT(AO15-AR15)&" Day(s) Ahead")))) -> OK
AG16: Pilot | AJ16: Deployment to beta | AO16: 45901 | AR16: 45901 | AU16: =IF(AO16=$A$1,"Missing Target",IF(AR16=$A$1,IF($AZ$3>AO16,INT($AZ$3-AO16)&" Day(s) Overdue","Incomplete"),IF(AR16>AO16,INT(AR16-AO16)&" Day(s) Late",IF(AR16=AO16,"OK",INT(AO16-AR16)&" Day(s) Ahead")))) -> OK
B17: Contact | C17: James.Peltier@jonasfitness.com | AJ17: Initial metrics/feedback | AO17: 45901 | AR17: 45901 | AU17: =IF(AO17=$A$1,"Missing Target",IF(AR17=$A$1,IF($AZ$3>AO17,INT($AZ$3-AO17)&" Day(s) Overdue","Incomplete"),IF(AR17>AO17,INT(AR17-AO17)&" Day(s) Late",IF(AR17=AO17,"OK",INT(AO17-AR17)&" Day(s) Ahead")))) -> OK
B18: Prod Mgr | C18: Karamvir Dhanoa | F18: How will you measure the KPI? | O18: How will you measure the KPI? | X18: How will you measure the KPI? | AJ18: Feedback affecting code | AO18: 45901 | AR18: 45901 | AU18: =IF(AO18=$A$1,"Missing Target",IF(AR18=$A$1,IF($AZ$3>AO18,INT($AZ$3-AO18)&" Day(s) Overdue","Incomplete"),IF(AR18>AO18,INT(AR18-AO18)&" Day(s) Late",IF(AR18=AO18,"OK",INT(AO18-AR18)&" Day(s) Ahead")))) -> OK
B19: Analyst | C19: Chase Winston | F19: Confirm all 6 have access. | O19: Track time for completion of projects with a 20% increase in time goal. | AG19: Live | AJ19: General release available | AO19: 45931 | AR19: 45931 | AU19: =IF(AO19=$A$1,"Missing Target",IF(AR19=$A$1,IF($AZ$3>AO19,INT($AZ$3-AO19)&" Day(s) Overdue","Incomplete"),IF(AR19>AO19,INT(AR19-AO19)&" Day(s) Late",IF(AR19=AO19,"OK",INT(AO19-AR19)&" Day(s) Ahead")))) -> OK
B20: Tech Lead | C20: Jim Peltier | AJ20: Success metrics tracking | AO20: 45962 | AU20: =IF(AO20=$A$1,"Missing Target",IF(AR20=$A$1,IF($AZ$3>AO20,INT($AZ$3-AO20)&" Day(s) Overdue","Incomplete"),IF(AR20>AO20,INT(AR20-AO20)&" Day(s) Late",IF(AR20=AO20,"OK",INT(AO20-AR20)&" Day(s) Ahead")))) -> Incomplete
B21: Exec | C21: Sandy Crutcher | AJ21: Feedback loop continuing | AO21: 45992 | AU21: =IF(AO21=$A$1,"Missing Target",IF(AR21=$A$1,IF($AZ$3>AO21,INT($AZ$3-AO21)&" Day(s) Overdue","Incomplete"),IF(AR21>AO21,INT(AR21-AO21)&" Day(s) Late",IF(AR21=AO21,"OK",INT(AO21-AR21)&" Day(s) Ahead")))) -> Incomplete
B23: WEEKLY KPI TRACKER | F23: 1 | G23: =F23+1 -> 2 | H23: =G23+1 -> 3 | I23: =H23+1 -> 4 | J23: =I23+1 -> 5 | K23: =J23+1 -> 6 | L23: =K23+1 -> 7 | M23: =L23+1 -> 8 | N23: =M23+1 -> 9 | ... BE23: =BD23+1 -> 52
B24: Week Ending | F24: 45871 | G24: =F24+7 -> 45878 | H24: =G24+7 -> 45885 | I24: =H24+7 -> 45892 | J24: =I24+7 -> 45899 | K24: =J24+7 -> 45906 | L24: =K24+7 -> 45913 | M24: =L24+7 -> 45920 | N24: =M24+7 -> 45927 | ... BE24: =BD24+7 -> 46228
B25: =G13&" TARGET" -> Employee AI Tool Adoption Rate TARGET | F25: 6 | G25: 6 | H25: 6 | I25: 6 | J25: 6 | K25: 6 | L25: 6 | M25: 6 | N25: 6 | O25: 6 | P25: 6 | Q25: 6 | R25: 6 | S25: 6 | T25: 6 | U25: 6 | V25: 6 | W25: 6 | X25: 6 | Y25: 6 | Z25: 6 | AA25: 6 | AB25: 6 | AC25: 6 | AD25: 6 | AE25: 6 | AF25: 6 | AG25: 6 | AH25: 6 | AI25: 6 | AJ25: 6 | AK25: 6 | AL25: 6 | AM25: 6 | AN25: 6 | AO25: 6 | AP25: 6 | AQ25: 6 | AR25: 6 | AS25: 6 | AT25: 6 | AU25: 6 | AV25: 6 | AW25: 6 | AX25: 6 | AY25: 6 | AZ25: 6 | BA25: 6 | BB25: 6 | BC25: 6 | BD25: 6 | BE25: 6
B26: Actual | F26: 1 | G26: 1 | H26: 1 | I26: 1 | J26: 1 | K26: 1 | L26: 1 | M26: 1 | N26: 1 | O26: 3 | P26: 3 | Q26: 3 | R26: 4 | S26: 6 | T26: 0 | U26: 0 | V26: 0 | W26: 0 | X26: 0 | Y26: 0 | Z26: 0 | AA26: 0 | AB26: 0 | AC26: 0 | AD26: 0 | AE26: 0 | AF26: 0 | AG26: 0 | AH26: 0 | AI26: 0 | AJ26: 0 | AK26: 0 | AL26: 0 | AM26: 0 | AN26: 0 | AO26: 0 | AP26: 0 | AQ26: 0 | AR26: 0 | AS26: 0 | AT26: 0 | AU26: 0 | AV26: 0 | AW26: 0 | AX26: 0 | AY26: 0 | AZ26: 0 | BA26: 0 | BB26: 0 | BC26: 0 | BD26: 0 | BE26: 0
B27: Delta | F27: =F26-F25 -> -5 | G27: =G26-G25 -> -5 | H27: =H26-H25 -> -5 | I27: =I26-I25 -> -5 | J27: =J26-J25 -> -5 | K27: =K26-K25 -> -5 | L27: =L26-L25 -> -5 | M27: =M26-M25 -> -5 | ... BE27: =BE26-BE25 -> -6
B28: Notes on this KPI (anything to add this week?)
B30: =P13&" TARGET" -> Employee Productivity Gains TARGET | F30: 20 | G30: =F30 -> 20 | H30: =G30 -> 20 | I30: =H30 -> 20 | J30: =I30 -> 20 | K30: =J30 -> 20 | L30: =K30 -> 20 | M30: =L30 -> 20 | N30: =M30 -> 20 | ... BE30: =BD30 -> 20
B31: Actual | F31: 5 | G31: 5 | H31: 5 | I31: 5 | J31: 5 | K31: 5 | L31: 5 | M31: 5 | N31: 5 | O31: 15 | P31: 15 | Q31: 20 | R31: 20 | S31: 0 | T31: 0 | U31: 0 | V31: 0 | W31: 0 | X31: 0 | Y31: 0 | Z31: 0 | AA31: 0 | AB31: 0 | AC31: 0 | AD31: 0 | AE31: 0 | AF31: 0 | AG31: 0 | AH31: 0 | AI31: 0 | AJ31: 0 | AK31: 0 | AL31: 0 | AM31: 0 | AN31: 0 | AO31: 0 | AP31: 0 | AQ31: 0 | AR31: 0 | AS31: 0 | AT31: 0 | AU31: 0 | AV31: 0 | AW31: 0 | AX31: 0 | AY31: 0 | AZ31: 0 | BA31: 0 | BB31: 0 | BC31: 0 | BD31: 0 | BE31: 0
B32: Delta | F32: =F31-F30 -> -15 | G32: =G31-G30 -> -15 | H32: =H31-H30 -> -15 | I32: =I31-I30 -> -15 | J32: =J31-J30 -> -15 | K32: =K31-K30 -> -15 | L32: =L31-L30 -> -15 | M32: =M31-M30 -> -15 | ... BE32: =BE31-BE30 -> -20
B33: Notes on this KPI (anything to add this week?)
B35: =Y13&" TARGET" -> .... Select the primary KPI (Jonas Library) TARGET | F35: 0 | G35: =F35 -> 0 | H35: =G35 -> 0 | I35: =H35 -> 0 | J35: =I35 -> 0 | K35: =J35 -> 0 | L35: =K35 -> 0 | M35: =L35 -> 0 | N35: =M35 -> 0 | ... BE35: =BD35 -> 0
B36: Actual | F36: 0 | G36: 0 | H36: 0 | I36: 0 | J36: 0 | K36: 0 | L36: 0 | M36: 0 | N36: 0 | O36: 0 | P36: 0 | Q36: 0 | R36: 0 | S36: 0 | T36: 0 | U36: 0 | V36: 0 | W36: 0 | X36: 0 | Y36: 0 | Z36: 0 | AA36: 0 | AB36: 0 | AC36: 0 | AD36: 0 | AE36: 0 | AF36: 0 | AG36: 0 | AH36: 0 | AI36: 0 | AJ36: 0 | AK36: 0 | AL36: 0 | AM36: 0 | AN36: 0 | AO36: 0 | AP36: 0 | AQ36: 0 | AR36: 0 | AS36: 0 | AT36: 0 | AU36: 0 | AV36: 0 | AW36: 0 | AX36: 0 | AY36: 0 | AZ36: 0 | BA36: 0 | BB36: 0 | BC36: 0 | BD36: 0 | BE36: 0
B37: Delta | F37: =F36-F35 -> 0 | G37: =G36-G35 -> 0 | H37: =H36-H35 -> 0 | I37: =I36-I35 -> 0 | J37: =J36-J35 -> 0 | K37: =K36-K35 -> 0 | L37: =L36-L35 -> 0 | M37: =M36-M35 -> 0 | ... BE37: =BE36-BE35 -> 0
B38: Notes on this KPI (anything to add this week?)
B41: Revenue Target | F41: =IF($X$12="Revenue Impact",F35,0) -> 0 | G41: =IF($X$12="Revenue Impact",G35,0) -> 0 | H41: =IF($X$12="Revenue Impact",H35,0) -> 0 | I41: =IF($X$12="Revenue Impact",I35,0) -> 0 | J41: =IF($X$12="Revenue Impact",J35,0) -> 0 | K41: =IF($X$12="Revenue Impact",K35,0) -> 0 | L41: =IF($X$12="Revenue Impact",L35,0) -> 0 | M41: =IF($X$12="Revenue Impact",M35,0) -> 0 | ... BE41: =IF($X$12="Revenue Impact",BE35,0) -> 0
B42: Revenue Actual | F42: =IF($X$12="Revenue Impact",F36,0) -> 0 | G42: =IF($X$12="Revenue Impact",G36,0) -> 0 | H42: =IF($X$12="Revenue Impact",H36,0) -> 0 | I42: =IF($X$12="Revenue Impact",I36,0) -> 0 | J42: =IF($X$12="Revenue Impact",J36,0) -> 0 | K42: =IF($X$12="Revenue Impact",K36,0) -> 0 | L42: =IF($X$12="Revenue Impact",L36,0) -> 0 | M42: =IF($X$12="Revenue Impact",M36,0) -> 0 | ... BE42: =IF($X$12="Revenue Impact",BE36,0) -> 0
B44: Cost Target | F44: =IF($X$12="Cost Savings",F35,0) -> 0 | G44: =IF($X$12="Cost Savings",G35,0) -> 0 | H44: =IF($X$12="Cost Savings",H35,0) -> 0 | I44: =IF($X$12="Cost Savings",I35,0) -> 0 | J44: =IF($X$12="Cost Savings",J35,0) -> 0 | K44: =IF($X$12="Cost Savings",K35,0) -> 0 | L44: =IF($X$12="Cost Savings",L35,0) -> 0 | M44: =IF($X$12="Cost Savings",M35,0) -> 0 | ... BE44: =IF($X$12="Cost Savings",BE35,0) -> 0
B45: Cost Actual | F45: =IF($X$12="Cost Savings",F36,0) -> 0 | G45: =IF($X$12="Cost Savings",G36,0) -> 0 | H45: =IF($X$12="Cost Savings",H36,0) -> 0 | I45: =IF($X$12="Cost Savings",I36,0) -> 0 | J45: =IF($X$12="Cost Savings",J36,0) -> 0 | K45: =IF($X$12="Cost Savings",K36,0) -> 0 | L45: =IF($X$12="Cost Savings",L36,0) -> 0 | M45: =IF($X$12="Cost Savings",M36,0) -> 0 | ... BE45: =IF($X$12="Cost Savings",BE36,0) -> 0
B47: Financial Target | F47: =F41+F44 -> 0 | G47: =G41+G44 -> 0 | H47: =H41+H44 -> 0 | I47: =I41+I44 -> 0 | J47: =J41+J44 -> 0 | K47: =K41+K44 -> 0 | L47: =L41+L44 -> 0 | M47: =M41+M44 -> 0 | ... BE47: =BE41+BE44 -> 0
B48: Financial Actual | F48: =F42+F45 -> 0 | G48: =G42+G45 -> 0 | H48: =H42+H45 -> 0 | I48: =I42+I45 -> 0 | J48: =J42+J45 -> 0 | K48: =K42+K45 -> 0 | L48: =L42+L45 -> 0 | M48: =M42+M45 -> 0 | ... BE48: =BE42+BE45 -> 0
E49: To Date
B50: Current Financial Target | E50: =MAX(F50:BE50) -> 0 | F50: =IF($AZ$3>F24,F47,0) -> 0 | G50: =IF($AZ$3>G24,G47,0) -> 0 | H50: =IF($AZ$3>H24,H47,0) -> 0 | I50: =IF($AZ$3>I24,I47,0) -> 0 | J50: =IF($AZ$3>J24,J47,0) -> 0 | K50: =IF($AZ$3>K24,K47,0) -> 0 | L50: =IF($AZ$3>L24,L47,0) -> 0 | M50: =IF($AZ$3>M24,M47,0) -> 0 | ... BE50: =IF($AZ$3>BE24,BE47,0) -> 0
B51: Current Financial Actual | E51: =MAX(F51:BE51) -> 0 | F51: =IF($AZ$3>F25,F48,0) -> 0 | G51: =IF($AZ$3>G25,G48,0) -> 0 | H51: =IF($AZ$3>H25,H48,0) -> 0 | I51: =IF($AZ$3>I25,I48,0) -> 0 | J51: =IF($AZ$3>J25,J48,0) -> 0 | K51: =IF($AZ$3>K25,K48,0) -> 0 | L51: =IF($AZ$3>L25,L48,0) -> 0 | M51: =IF($AZ$3>M25,M48,0) -> 0 | ... BE51: =IF($AZ$3>BE25,BE48,0) -> 0

Sheet P3
B3: PROJECT | F3: Operations/Maintenance Enterprise ChatGPT | AG3: Strategic Value | AO3: =F8 -> Simple Tool | AV3: =IF(F7="",0,VLOOKUP(F7,Lookups!B4:H8,3)) -> 10 | AZ3: =NOW() -> 45961.476
AG4: Stage Multiplier (today) | AO4: =VLOOKUP(COUNTIF(AR10:AT21,"<="&AZ3),Table3357[],2) -> Live | AV4: =IF(AO4="Not Def",0,VLOOKUP(AO4,Lookups!L4:M8,2)) -> 1 | AZ4: Current Qtr | BC4: =VLOOKUP((YEAR(AZ3)&"-"&MONTH(AZ3)),Lookups!S3:U21,2) -> 2025-Q4
B5: Description (Use Case) | F5: Use ChatGPT to create training documents, emails, templates creation, and assist with billing and payment reconcilation projects. | AG5: Stage Last Quarter | AO5: =VLOOKUP(COUNTIF(AR10:AT21,"<"&VLOOKUP(BC4,Lookups!W3:Y9,2)),Table3357[],2) -> Pilot | AQ5: =IF(AV5=1,"No Change","Progression") -> Progression | AV5: =IF(AO4="Not Def",0,IF(AO5=AO4,1,1.2)) -> 1.2
AG6: PROJECT SCORE | AV6: =AV3*AV4*AV5 -> 12
B7: Category | F7: L1. Using external AI tools for basic internal productivity | Y7: Ratio Impacted | AC7: Maintenance
B8: Strategic Value Level | F8: =IF(F7="","",VLOOKUP(F7,Lookups!B4:H8,2)) -> Simple Tool
B9: Examples | F9: =IF(F7="","",VLOOKUP(F7,Lookups!B4:H8,4)) -> ChatGPT for content, Co-Pilot for drafting emails, AI meeting summaries | AG9: Stage | AJ9: Tasks | AO9: Target | AR9: Completed | AU9: Days to Target | AY9: Notes
AG10: Idea | AJ10: Project Defined | AO10: 45870 | AR10: 45870 | AU10: =IF(AO10=$BK$3,"Missing Target",IF(AR10=$BK$3,IF($AZ$3>AO10,INT($AZ$3-AO10)&" Day(s) Overdue","Incomplete"),IF(AR10>AO10,INT(AR10-AO10)&" Day(s) Late",IF(AR10=AO10,"OK",INT(AO10-AR10)&" Day(s) Ahead")))) -> OK
B11: PROJECT RESOURCES | F11: KEY PERFORMANCE INDICATORS / MEASURES OF SUCCESS | AJ11: Business Case approved | AO11: 45870 | AR11: 45870 | AU11: =IF(AO11=$BK$3,"Missing Target",IF(AR11=$BK$3,IF($AZ$3>AO11,INT($AZ$3-AO11)&" Day(s) Overdue","Incomplete"),IF(AR11>AO11,INT(AR11-AO11)&" Day(s) Late",IF(AR11=AO11,"OK",INT(AO11-AR11)&" Day(s) Ahead")))) -> OK
B12: AI Tools & Services | F12: =IF(F7="","",VLOOKUP(F7,Lookups!B4:H8,5)) -> Adoption Rate | O12: =IF(F7="","",VLOOKUP(F7,Lookups!B4:H8,6)) -> Productivity Gains | X12: =IF(F7="","",VLOOKUP(F7,Lookups!B4:H8,7)) -> Cost Savings | AJ12: Resources Allocated | AO12: 45870 | AR12: 45870 | AU12: =IF(AO12=$BK$3,"Missing Target",IF(AR12=$BK$3,IF($AZ$3>AO12,INT($AZ$3-AO12)&" Day(s) Overdue","Incomplete"),IF(AR12>AO12,INT(AR12-AO12)&" Day(s) Late",IF(AR12=AO12,"OK",INT(AO12-AR12)&" Day(s) Ahead")))) -> OK
B13: Enterprise ChatGPT | F13: KPI | G13: Successful Adaptation to New Use Cases | O13: KPI | P13: Error Rate Reduction | X13: KPI | Y13: .... Select the primary KPI (Jonas Library) | AG13: Develop | AJ13: Technical PoC validated | AO13: 45870 | AR13: 45870 | AU13: =IF(AO13=$BK$3,"Missing Target",IF(AR13=$BK$3,IF($AZ$3>AO13,INT($AZ$3-AO13)&" Day(s) Overdue","Incomplete"),IF(AR13>AO13,INT(AR13-AO13)&" Day(s) Late",IF(AR13=AO13,"OK",INT(AO13-AR13)&" Day(s) Ahead")))) -> OK
F14: How does this Project support this KPI? | O14: How does this Project support this KPI? | X14: How does this Project support this KPI? | AJ14: Dev roadmap documented | AO14: 45870 | AR14: 45870 | AU14: =IF(AO14=$BK$3,"Missing Target",IF(AR14=$BK$3,IF($AZ$3>AO14,INT($AZ$3-AO14)&" Day(s) Overdue","Incomplete"),IF(AR14>AO14,INT(AR14-AO14)&" Day(s) Late",IF(AR14=AO14,"OK",INT(AO14-AR14)&" Day(s) Ahead")))) -> OK
F15: Where applicable, give access to Enterprise Chat GPT to teams to help them with day to day functions. | O15: Quickly generates KPI calculations not auto-generated from other tools or that will take time to develop and allows us to report more accurately apples to apples across business units. Reduces manual Excel errors. Allows training team to help compare data or help with billing. | AJ15: Coding started | AO15: 45870 | AR15: 45870 | AU15: =IF(AO15=$A$1,"Missing Target",IF(AR15=$A$1,IF($AZ$3>AO15,INT($AZ$3-AO15)&" Day(s) Overdue","Incomplete"),IF(AR15>AO15,INT(AR15-AO15)&" Day(s) Late",IF(AR15=AO15,"OK",INT(AO15-AR15)&" Day(s) Ahead")))) -> OK
AG16: Pilot | AJ16: Deployment to beta | AO16: 45901 | AR16: 45901 | AU16: =IF(AO16=$A$1,"Missing Target",IF(AR16=$A$1,IF($AZ$3>AO16,INT($AZ$3-AO16)&" Day(s) Overdue","Incomplete"),IF(AR16>AO16,INT(AR16-AO16)&" Day(s) Late",IF(AR16=AO16,"OK",INT(AO16-AR16)&" Day(s) Ahead")))) -> OK
B17: Contact | C17: Kim.forster@jonasfitness.com | AJ17: Initial metrics/feedback | AO17: 45901 | AR17: 45901 | AU17: =IF(AO17=$A$1,"Missing Target",IF(AR17=$A$1,IF($AZ$3>AO17,INT($AZ$3-AO17)&" Day(s) Overdue","Incomplete"),IF(AR17>AO17,INT(AR17-AO17)&" Day(s) Late",IF(AR17=AO17,"OK",INT(AO17-AR17)&" Day(s) Ahead")))) -> OK
B18: Prod Mgr | C18: Karamvir Dhanoa | F18: How will you measure the KPI? | O18: How will you measure the KPI? | X18: How will you measure the KPI? | AJ18: Feedback affecting code | AO18: 45901 | AR18: 45901 | AU18: =IF(AO18=$A$1,"Missing Target",IF(AR18=$A$1,IF($AZ$3>AO18,INT($AZ$3-AO18)&" Day(s) Overdue","Incomplete"),IF(AR18>AO18,INT(AR18-AO18)&" Day(s) Late",IF(AR18=AO18,"OK",INT(AO18-AR18)&" Day(s) Ahead")))) -> OK
B19: Analyst | C19: Chase Winston | F19: First step is to measure use cases and the ability to solve them using AI with a goal of one use case identitifed and solved per month, 3 a quarter or .20 a week. | O19: Tracking case efficiency, turnaround time, and other support metrics that should improve as the use of these tools are better understood. Aim to reduce errors in reconcilation cases by 20%. | AG19: Live | AJ19: General release available | AO19: 45931 | AR19: 45931 | AU19: =IF(AO19=$A$1,"Missing Target",IF(AR19=$A$1,IF($AZ$3>AO19,INT($AZ$3-AO19)&" Day(s) Overdue","Incomplete"),IF(AR19>AO19,INT(AR19-AO19)&" Day(s) Late",IF(AR19=AO19,"OK",INT(AO19-AR19)&" Day(s) Ahead")))) -> OK
B20: Tech Lead | C20: Jim Peltier | AJ20: Success metrics tracking | AO20: 45962 | AU20: =IF(AO20=$A$1,"Missing Target",IF(AR20=$A$1,IF($AZ$3>AO20,INT($AZ$3-AO20)&" Day(s) Overdue","Incomplete"),IF(AR20>AO20,INT(AR20-AO20)&" Day(s) Late",IF(AR20=AO20,"OK",INT(AO20-AR20)&" Day(s) Ahead")))) -> Incomplete
B21: Exec | C21: Sandy Crutcher | AJ21: Feedback loop continuing | AO21: 46022 | AU21: =IF(AO21=$A$1,"Missing Target",IF(AR21=$A$1,IF($AZ$3>AO21,INT($AZ$3-AO21)&" Day(s) Overdue","Incomplete"),IF(AR21>AO21,INT(AR21-AO21)&" Day(s) Late",IF(AR21=AO21,"OK",INT(AO21-AR21)&" Day(s) Ahead")))) -> Incomplete
B23: WEEKLY KPI TRACKER | F23: 1 | G23: =F23+1 -> 2 | H23: =G23+1 -> 3 | I23: =H23+1 -> 4 | J23: =I23+1 -> 5 | K23: =J23+1 -> 6 | L23: =K23+1 -> 7 | M23: =L23+1 -> 8 | N23: =M23+1 -> 9 | ... BE23: =BD23+1 -> 52
B24: Week Ending | F24: 45870 | G24: =F24+7 -> 45877 | H24: =G24+7 -> 45884 | I24: =H24+7 -> 45891 | J24: =I24+7 -> 45898 | K24: =J24+7 -> 45905 | L24: =K24+7 -> 45912 | M24: =L24+7 -> 45919 | N24: =M24+7 -> 45926 | ... BE24: =BD24+7 -> 46227
B25: =G13&" TARGET" -> Successful Adaptation to New Use Cases TARGET | F25: 20 | G25: =F25 -> 20 | H25: =G25 -> 20 | I25: =H25 -> 20 | J25: =I25 -> 20 | K25: =J25 -> 20 | L25: =K25 -> 20 | M25: =L25 -> 20 | N25: =M25 -> 20 | ... BE25: =BD25 -> 20
B26: Actual | F26: 20 | G26: 20 | H26: 20 | I26: 20 | J26: 20 | K26: 20 | L26: 20 | M26: 20 | N26: 20 | O26: 20 | P26: 20 | Q26: 20 | R26: 20 | S26: 20
B27: Delta | F27: =F26-F25 -> 0 | G27: =G26-G25 -> 0 | H27: =H26-H25 -> 0 | I27: =I26-I25 -> 0 | J27: =J26-J25 -> 0 | K27: =K26-K25 -> 0 | L27: =L26-L25 -> 0 | M27: =M26-M25 -> 0 | ... BE27: =BE26-BE25 -> -20
B28: Notes on this KPI (anything to add this week?)
B30: =P13&" TARGET" -> Error Rate Reduction TARGET | F30: 20 | G30: =F30 -> 20 | H30: =G30 -> 20 | I30: =H30 -> 20 | J30: =I30 -> 20 | K30: =J30 -> 20 | L30: =K30 -> 20 | M30: =L30 -> 20 | N30: =M30 -> 20 | ... BE30: =BD30 -> 20
B31: Actual | F31: 10 | G31: 10 | H31: 10 | I31: 10 | J31: 10 | K31: 10 | L31: 10 | M31: 10 | N31: 15 | O31: 15 | P31: 15 | Q31: 15 | R31: 15 | S31: 15
B32: Delta | F32: =F31-F30 -> -10 | G32: =G31-G30 -> -10 | H32: =H31-H30 -> -10 | I32: =I31-I30 -> -10 | J32: =J31-J30 -> -10 | K32: =K31-K30 -> -10 | L32: =L31-L30 -> -10 | M32: =M31-M30 -> -10 | ... BE32: =BE31-BE30 -> -20
B33: Notes on this KPI (anything to add this week?)
B35: =Y13&" TARGET" -> .... Select the primary KPI (Jonas Library) TARGET | F35: 0 | G35: =F35 -> 0 | H35: =G35 -> 0 | I35: =H35 -> 0 | J35: =I35 -> 0 | K35: =J35 -> 0 | L35: =K35 -> 0 | M35: =L35 -> 0 | N35: =M35 -> 0 | ... BE35: =BD35 -> 0
B36: Actual | F36: 0 | G36: 0 | H36: 0 | I36: 0 | J36: 0 | K36: 0 | L36: 0 | M36: 0
B37: Delta | F37: =F36-F35 -> 0 | G37: =G36-G35 -> 0 | H37: =H36-H35 -> 0 | I37: =I36-I35 -> 0 | J37: =J36-J35 -> 0 | K37: =K36-K35 -> 0 | L37: =L36-L35 -> 0 | M37: =M36-M35 -> 0 | ... BE37: =BE36-BE35 -> 0
B38: Notes on this KPI (anything to add this week?)
B41: Revenue Target | F41: =IF($X$12="Revenue Impact",F35,0) -> 0 | G41: =IF($X$12="Revenue Impact",G35,0) -> 0 | H41: =IF($X$12="Revenue Impact",H35,0) -> 0 | I41: =IF($X$12="Revenue Impact",I35,0) -> 0 | J41: =IF($X$12="Revenue Impact",J35,0) -> 0 | K41: =IF($X$12="Revenue Impact",K35,0) -> 0 | L41: =IF($X$12="Revenue Impact",L35,0) -> 0 | M41: =IF($X$12="Revenue Impact",M35,0) -> 0 | ... BE41: =IF($X$12="Revenue Impact",BE35,0) -> 0
B42: Revenue Actual | F42: =IF($X$12="Revenue Impact",F36,0) -> 0 | G42: =IF($X$12="Revenue Impact",G36,0) -> 0 | H42: =IF($X$12="Revenue Impact",H36,0) -> 0 | I42: =IF($X$12="Revenue Impact",I36,0) -> 0 | J42: =IF($X$12="Revenue Impact",J36,0) -> 0 | K42: =IF($X$12="Revenue Impact",K36,0) -> 0 | L42: =IF($X$12="Revenue Impact",L36,0) -> 0 | M42: =IF($X$12="Revenue Impact",M36,0) -> 0 | ... BE42: =IF($X$12="Revenue Impact",BE36,0) -> 0
B44: Cost Target | F44: =IF($X$12="Cost Savings",F35,0) -> 0 | G44: =IF($X$12="Cost Savings",G35,0) -> 0 | H44: =IF($X$12="Cost Savings",H35,0) -> 0 | I44: =IF($X$12="Cost Savings",I35,0) -> 0 | J44: =IF($X$12="Cost Savings",J35,0) -> 0 | K44: =IF($X$12="Cost Savings",K35,0) -> 0 | L44: =IF($X$12="Cost Savings",L35,0) -> 0 | M44: =IF($X$12="Cost Savings",M35,0) -> 0 | ... BE44: =IF($X$12="Cost Savings",BE35,0) -> 0
B45: Cost Actual | F45: =IF($X$12="Cost Savings",F36,0) -> 0 | G45: =IF($X$12="Cost Savings",G36,0) -> 0 | H45: =IF($X$12="Cost Savings",H36,0) -> 0 | I45: =IF($X$12="Cost Savings",I36,0) -> 0 | J45: =IF($X$12="Cost Savings",J36,0) -> 0 | K45: =IF($X$12="Cost Savings",K36,0) -> 0 | L45: =IF($X$12="Cost Savings",L36,0) -> 0 | M45: =IF($X$12="Cost Savings",M36,0) -> 0 | ... BE45: =IF($X$12="Cost Savings",BE36,0) -> 0
B47: Financial Target | F47: =F41+F44 -> 0 | G47: =G41+G44 -> 0 | H47: =H41+H44 -> 0 | I47: =I41+I44 -> 0 | J47: =J41+J44 -> 0 | K47: =K41+K44 -> 0 | L47: =L41+L44 -> 0 | M47: =M41+M44 -> 0 | ... BE47: =BE41+BE44 -> 0
B48: Financial Actual | F48: =F42+F45 -> 0 | G48: =G42+G45 -> 0 | H48: =H42+H45 -> 0 | I48: =I42+I45 -> 0 | J48: =J42+J45 -> 0 | K48: =K42+K45 -> 0 | L48: =L42+L45 -> 0 | M48: =M42+M45 -> 0 | ... BE48: =BE42+BE45 -> 0
E49: To Date
B50: Current Financial Target | E50: =MAX(F50:BE50) -> 0 | F50: =IF($AZ$3>F24,F47,0) -> 0 | G50: =IF($AZ$3>G24,G47,0) -> 0 | H50: =IF($AZ$3>H24,H47,0) -> 0 | I50: =IF($AZ$3>I24,I47,0) -> 0 | J50: =IF($AZ$3>J24,J47,0) -> 0 | K50: =IF($AZ$3>K24,K47,0) -> 0 | L50: =IF($AZ$3>L24,L47,0) -> 0 | M50: =IF($AZ$3>M24,M47,0) -> 0 | ... BE50: =IF($AZ$3>BE24,BE47,0) -> 0
B51: Current Financial Actual | E51: =MAX(F51:BE51) -> 0 | F51: =IF($AZ$3>F25,F48,0) -> 0 | G51: =IF($AZ$3>G25,G48,0) -> 0 | H51: =IF($AZ$3>H25,H48,0) -> 0 | I51: =IF($AZ$3>I25,I48,0) -> 0 | J51: =IF($AZ$3>J25,J48,0) -> 0 | K51: =IF($AZ$3>K25,K48,0) -> 0 | L51: =IF($AZ$3>L25,L48,0) -> 0 | M51: =IF($AZ$3>M25,M48,0) -> 0 | ... BE51: =IF($AZ$3>BE25,BE48,0) -> 0

Sheet P4
B3: PROJECT | F3: IRIS Chat Bot | AG3: Strategic Value | AO3: =F8 -> Customer Feature - New | AV3: =IF(F7="",0,VLOOKUP(F7,Lookups!B4:H8,3)) -> 200 | AZ3: =NOW() -> 45961.476
AG4: Stage Multiplier (today) | AO4: =VLOOKUP(COUNTIF(AR10:AT21,"<="&AZ3),Table3357[],2) -> Pilot | AV4: =IF(AO4="Not Def",0,VLOOKUP(AO4,Lookups!L4:M8,2)) -> 0.7 | AZ4: Current Qtr | BC4: =VLOOKUP((YEAR(AZ3)&"-"&MONTH(AZ3)),Lookups!S3:U21,2) -> 2025-Q4
B5: Description (Use Case) | F5: Integrated chatbot delivers real-time, in-product guidance for client “how-to” inquiries, improving user self-service and decreasing call center demand. | AG5: Stage Last Quarter | AO5: =VLOOKUP(COUNTIF(AR10:AT21,"<"&VLOOKUP(BC4,Lookups!W3:Y9,2)),Table3357[],2) -> Pilot | AQ5: =IF(AV5=1,"No Change","Progression") -> No Change | AV5: =IF(AO4="Not Def",0,IF(AO5=AO4,1,1.2)) -> 1
AG6: PROJECT SCORE | AV6: =AV3*AV4*AV5 -> 140
B7: Category | F7: L5. Entirely new product capabilities powered by AI | Y7: Ratio Impacted | AC7: Maintenance
B8: Strategic Value Level | F8: =IF(F7="","",VLOOKUP(F7,Lookups!B4:H8,2)) -> Customer Feature - New
B9: Examples | F9: =IF(F7="","",VLOOKUP(F7,Lookups!B4:H8,4)) -> Predictive analytics modules, AI-powered workflow automation, intelligent decision support systems | AG9: Stage | AJ9: Tasks | AO9: Target | AR9: Completed | AU9: Days to Target | AY9: Notes
AG10: Idea | AJ10: Project Defined | AO10: 44941 | AR10: 44941 | AU10: =IF(AO10=$BK$3,"Missing Target",IF(AR10=$BK$3,IF($AZ$3>AO10,INT($AZ$3-AO10)&" Day(s) Overdue","Incomplete"),IF(AR10>AO10,INT(AR10-AO10)&" Day(s) Late",IF(AR10=AO10,"OK",INT(AO10-AR10)&" Day(s) Ahead")))) -> OK
B11: PROJECT RESOURCES | F11: KEY PERFORMANCE INDICATORS / MEASURES OF SUCCESS | AJ11: Business Case approved | AO11: 44941 | AR11: 44941 | AU11: =IF(AO11=$BK$3,"Missing Target",IF(AR11=$BK$3,IF($AZ$3>AO11,INT($AZ$3-AO11)&" Day(s) Overdue","Incomplete"),IF(AR11>AO11,INT(AR11-AO11)&" Day(s) Late",IF(AR11=AO11,"OK",INT(AO11-AR11)&" Day(s) Ahead")))) -> OK
B12: AI Tools & Services | F12: =IF(F7="","",VLOOKUP(F7,Lookups!B4:H8,5)) -> Market Differentiation | O12: =IF(F7="","",VLOOKUP(F7,Lookups!B4:H8,6)) -> Competitive Advantage | X12: =IF(F7="","",VLOOKUP(F7,Lookups!B4:H8,7)) -> Revenue Impact | AJ12: Resources Allocated | AO12: 44941 | AR12: 44941 | AU12: =IF(AO12=$BK$3,"Missing Target",IF(AR12=$BK$3,IF($AZ$3>AO12,INT($AZ$3-AO12)&" Day(s) Overdue","Incomplete"),IF(AR12>AO12,INT(AR12-AO12)&" Day(s) Late",IF(AR12=AO12,"OK",INT(AO12-AR12)&" Day(s) Ahead")))) -> OK
B13: AWS | F13: KPI | G13: Audit Frequency and Results | O13: KPI | P13: Consistency Scores | X13: KPI | Y13: .... Select the primary KPI (Jonas Library) | AG13: Develop | AJ13: Technical PoC validated | AO13: 44972 | AR13: 44972 | AU13: =IF(AO13=$BK$3,"Missing Target",IF(AR13=$BK$3,IF($AZ$3>AO13,INT($AZ$3-AO13)&" Day(s) Overdue","Incomplete"),IF(AR13>AO13,INT(AR13-AO13)&" Day(s) Late",IF(AR13=AO13,"OK",INT(AO13-AR13)&" Day(s) Ahead")))) -> OK
F14: How does this Project support this KPI? | O14: How does this Project support this KPI? | X14: How does this Project support this KPI? | AJ14: Dev roadmap documented | AO14: 44972 | AR14: 44972 | AU14: =IF(AO14=$BK$3,"Missing Target",IF(AR14=$BK$3,IF($AZ$3>AO14,INT($AZ$3-AO14)&" Day(s) Overdue","Incomplete"),IF(AR14>AO14,INT(AR14-AO14)&" Day(s) Late",IF(AR14=AO14,"OK",INT(AO14-AR14)&" Day(s) Ahead")))) -> OK
F15: Provides customers with accurate information when asked from within the Compete application. | O15: Provides quick and easy access to customer questions and saves them time by not having to call into the call center for assitance. | AJ15: Coding started | AO15: 44972 | AR15: 44972 | AU15: =IF(AO15=$A$1,"Missing Target",IF(AR15=$A$1,IF($AZ$3>AO15,INT($AZ$3-AO15)&" Day(s) Overdue","Incomplete"),IF(AR15>AO15,INT(AR15-AO15)&" Day(s) Late",IF(AR15=AO15,"OK",INT(AO15-AR15)&" Day(s) Ahead")))) -> OK
AG16: Pilot | AJ16: Deployment to beta | AO16: 45352 | AR16: 45352 | AU16: =IF(AO16=$A$1,"Missing Target",IF(AR16=$A$1,IF($AZ$3>AO16,INT($AZ$3-AO16)&" Day(s) Overdue","Incomplete"),IF(AR16>AO16,INT(AR16-AO16)&" Day(s) Late",IF(AR16=AO16,"OK",INT(AO16-AR16)&" Day(s) Ahead")))) -> OK
B17: Contact | C17: James.Peltier@jonasfitness.com | AJ17: Initial metrics/feedback | AO17: 45627 | AR17: 45627 | AU17: =IF(AO17=$A$1,"Missing Target",IF(AR17=$A$1,IF($AZ$3>AO17,INT($AZ$3-AO17)&" Day(s) Overdue","Incomplete"),IF(AR17>AO17,INT(AR17-AO17)&" Day(s) Late",IF(AR17=AO17,"OK",INT(AO17-AR17)&" Day(s) Ahead")))) -> OK
B18: Prod Mgr | C18: Kari Ewersen | F18: How will you measure the KPI? | O18: How will you measure the KPI? | X18: How will you measure the KPI? | AJ18: Feedback affecting code | AO18: 45627 | AR18: 45627 | AU18: =IF(AO18=$A$1,"Missing Target",IF(AR18=$A$1,IF($AZ$3>AO18,INT($AZ$3-AO18)&" Day(s) Overdue","Incomplete"),IF(AR18>AO18,INT(AR18-AO18)&" Day(s) Late",IF(AR18=AO18,"OK",INT(AO18-AR18)&" Day(s) Ahead")))) -> OK
B19: Analyst | C19: Chase Winston | F19: 80% of correct answers and cases that result from a customer being routed from the chat bot to the call center for additional help. | O19: Comparision of the number of calls routed to support and metrics around the use of the tool, inital goal of 20% routed to support. | AG19: Live | AJ19: General release available | AO19: 46022 | AU19: =IF(AO19=$A$1,"Missing Target",IF(AR19=$A$1,IF($AZ$3>AO19,INT($AZ$3-AO19)&" Day(s) Overdue","Incomplete"),IF(AR19>AO19,INT(AR19-AO19)&" Day(s) Late",IF(AR19=AO19,"OK",INT(AO19-AR19)&" Day(s) Ahead")))) -> Incomplete
B20: Tech Lead | C20: Jim Peltier | AJ20: Success metrics tracking | AO20: 46022 | AU20: =IF(AO20=$A$1,"Missing Target",IF(AR20=$A$1,IF($AZ$3>AO20,INT($AZ$3-AO20)&" Day(s) Overdue","Incomplete"),IF(AR20>AO20,INT(AR20-AO20)&" Day(s) Late",IF(AR20=AO20,"OK",INT(AO20-AR20)&" Day(s) Ahead")))) -> Incomplete
B21: Exec | C21: Sandy Crutcher | AJ21: Feedback loop continuing | AO21: 46022 | AU21: =IF(AO21=$A$1,"Missing Target",IF(AR21=$A$1,IF($AZ$3>AO21,INT($AZ$3-AO21)&" Day(s) Overdue","Incomplete"),IF(AR21>AO21,INT(AR21-AO21)&" Day(s) Late",IF(AR21=AO21,"OK",INT(AO21-AR21)&" Day(s) Ahead")))) -> Incomplete
B23: WEEKLY KPI TRACKER | F23: 1 | G23: =F23+1 -> 2 | H23: =G23+1 -> 3 | I23: =H23+1 -> 4 | J23: =I23+1 -> 5 | K23: =J23+1 -> 6 | L23: =K23+1 -> 7 | M23: =L23+1 -> 8 | N23: =M23+1 -> 9 | ... BE23: =BD23+1 -> 52
B24: Week Ending | F24: 45992 | G24: =F24+7 -> 45999 | H24: =G24+7 -> 46006 | I24: =H24+7 -> 46013 | J24: =I24+7 -> 46020 | K24: =J24+7 -> 46027 | L24: =K24+7 -> 46034 | M24: =L24+7 -> 46041 | N24: =M24+7 -> 46048 | ... BE24: =BD24+7 -> 46349
B25: =G13&" TARGET" -> Audit Frequency and Results TARGET | F25: 80 | G25: 80 | H25: 80 | I25: 80 | J25: 80 | K25: 80 | L25: 80 | M25: 80 | N25: 80 | O25: 80 | P25: 80 | Q25: 80 | R25: 80 | S25: 80 | T25: 80 | U25: 80 | V25: 80 | W25: 80 | X25: 80 | Y25: 80 | Z25: 80 | AA25: 80 | AB25: 80 | AC25: 80 | AD25: 80 | AE25: 80 | AF25: 80 | AG25: 80 | AH25: 80 | AI25: 80 | AJ25: 80 | AK25: 80 | AL25: 80 | AM25: 80 | AN25: 80 | AO25: 80 | AP25: 80 | AQ25: 80 | AR25: 80 | AS25: 80 | AT25: 80 | AU25: 80 | AV25: 80 | AW25: 80 | AX25: 80 | AY25: 80 | AZ25: 80 | BA25: 80 | BB25: 80 | BC25: 80 | BD25: 80 | BE25: 80
B26: Actual | F26: 60 | G26: 60 | H26: 60 | I26: 60 | J26: 60 | K26: 60 | L26: 60 | M26: 60 | N26: 60 | O26: 60 | P26: 60 | Q26: 60 | R26: 60 | S26: 80 | T26: 80 | U26: 80 | V26: 80 | W26: 80 | X26: 80 | Y26: 80 | Z26: 80 | AA26: 80 | AB26: 80 | AC26: 80 | AD26: 80 | AE26: 80 | AF26: 80 | AG26: 80 | AH26: 80 | AI26: 80 | AJ26: 80 | AK26: 80 | AL26: 80 | AM26: 80 | AN26: 80 | AO26: 80 | AP26: 80 | AQ26: 80 | AR26: 80 | AS26: 80 | AT26: 80 | AU26: 80 | AV26: 80 | AW26: 80 | AX26: 80 | AY26: 80 | AZ26: 80 | BA26: 80
B27: Delta | F27: =F26-F25 -> -20 | G27: =G26-G25 -> -20 | H27: =H26-H25 -> -20 | I27: =I26-I25 -> -20 | J27: =J26-J25 -> -20 | K27: =K26-K25 -> -20 | L27: =L26-L25 -> -20 | M27: =M26-M25 -> -20 | ... BE27: =BE26-BE25 -> -80
B28: Notes on this KPI (anything to add this week?)
B30: =P13&" TARGET" -> Consistency Scores TARGET | F30: 20 | G30: =F30 -> 20 | H30: =G30 -> 20 | I30: =H30 -> 20 | J30: =I30 -> 20 | K30: =J30 -> 20 | L30: =K30 -> 20 | M30: =L30 -> 20 | N30: =M30 -> 20 | ... BE30: =BD30 -> 20
B31: Actual | F31: 0 | G31: 0 | H31: 0 | I31: 0 | J31: 0 | K31: 0 | L31: 0 | M31: 0 | N31: 0 | O31: 0 | P31: 0 | Q31: 0 | R31: 0 | S31: 0 | T31: 0 | U31: 0 | V31: 0 | W31: 0 | X31: 0 | Y31: 0 | Z31: 0 | AA31: 0 | AB31: 0 | AC31: 0 | AD31: 0 | AE31: 0 | AF31: 0 | AG31: 0 | AH31: 0 | AI31: 0 | AJ31: 0 | AK31: 0 | AL31: 0 | AM31: 0 | AN31: 0 | AO31: 0 | AP31: 0 | AQ31: 0 | AR31: 0 | AS31: 0 | AT31: 0 | AU31: 0 | AV31: 0 | AW31: 0 | AX31: 0 | AY31: 0 | AZ31: 0 | BA31: 0 | BB31: 0 | BC31: 0 | BD31: 0 | BE31: 0
B32: Delta | F32: =F31-F30 -> -20 | G32: =G31-G30 -> -20 | H32: =H31-H30 -> -20 | I32: =I31-I30 -> -20 | J32: =J31-J30 -> -20 | K32: =K31-K30 -> -20 | L32: =L31-L30 -> -20 | M32: =M31-M30 -> -20 | ... BE32: =BE31-BE30 -> -20
B33: Notes on this KPI (anything to add this week?)
B35: =Y13&" TARGET" -> .... Select the primary KPI (Jonas Library) TARGET | G35: =F35 -> 0 | H35: =G35 -> 0 | I35: =H35 -> 0 | J35: =I35 -> 0 | K35: =J35 -> 0 | L35: =K35 -> 0 | M35: =L35 -> 0 | N35: =M35 -> 0 | ... BE35: =BD35 -> 0
B36: Actual | F36: 0 | G36: 0 | H36: 0 | I36: 0 | J36: 0 | K36: 0 | L36: 0 | M36: 0
B37: Delta | F37: =F36-F35 -> 0 | G37: =G36-G35 -> 0 | H37: =H36-H35 -> 0 | I37: =I36-I35 -> 0 | J37: =J36-J35 -> 0 | K37: =K36-K35 -> 0 | L37: =L36-L35 -> 0 | M37: =M36-M35 -> 0 | ... BE37: =BE36-BE35 -> 0
B38: Notes on this KPI (anything to add this week?)
B41: Revenue Target | F41: =IF($X$12="Revenue Impact",F35,0) -> 0 | G41: =IF($X$12="Revenue Impact",G35,0) -> 0 | H41: =IF($X$12="Revenue Impact",H35,0) -> 0 | I41: =IF($X$12="Revenue Impact",I35,0) -> 0 | J41: =IF($X$12="Revenue Impact",J35,0) -> 0 | K41: =IF($X$12="Revenue Impact",K35,0) -> 0 | L41: =IF($X$12="Revenue Impact",L35,0) -> 0 | M41: =IF($X$12="Revenue Impact",M35,0) -> 0 | ... BE41: =IF($X$12="Revenue Impact",BE35,0) -> 0
B42: Revenue Actual | F42: =IF($X$12="Revenue Impact",F36,0) -> 0 | G42: =IF($X$12="Revenue Impact",G36,0) -> 0 | H42: =IF($X$12="Revenue Impact",H36,0) -> 0 | I42: =IF($X$12="Revenue Impact",I36,0) -> 0 | J42: =IF($X$12="Revenue Impact",J36,0) -> 0 | K42: =IF($X$12="Revenue Impact",K36,0) -> 0 | L42: =IF($X$12="Revenue Impact",L36,0) -> 0 | M42: =IF($X$12="Revenue Impact",M36,0) -> 0 | ... BE42: =IF($X$12="Revenue Impact",BE36,0) -> 0
B44: Cost Target | F44: =IF($X$12="Cost Savings",F35,0) -> 0 | G44: =IF($X$12="Cost Savings",G35,0) -> 0 | H44: =IF($X$12="Cost Savings",H35,0) -> 0 | I44: =IF($X$12="Cost Savings",I35,0) -> 0 | J44: =IF($X$12="Cost Savings",J35,0) -> 0 | K44: =IF($X$12="Cost Savings",K35,0) -> 0 | L44: =IF($X$12="Cost Savings",L35,0) -> 0 | M44: =IF($X$12="Cost Savings",M35,0) -> 0 | ... BE44: =IF($X$12="Cost Savings",BE35,0) -> 0
B45: Cost Actual | F45: =IF($X$12="Cost Savings",F36,0) -> 0 | G45: =IF($X$12="Cost Savings",G36,0) -> 0 | H45: =IF($X$12="Cost Savings",H36,0) -> 0 | I45: =IF($X$12="Cost Savings",I36,0) -> 0 | J45: =IF($X$12="Cost Savings",J36,0) -> 0 | K45: =IF($X$12="Cost Savings",K36,0) -> 0 | L45: =IF($X$12="Cost Savings",L36,0) -> 0 | M45: =IF($X$12="Cost Savings",M36,0) -> 0 | ... BE45: =IF($X$12="Cost Savings",BE36,0) -> 0
B47: Financial Target | F47: =F41+F44 -> 0 | G47: =G41+G44 -> 0 | H47: =H41+H44 -> 0 | I47: =I41+I44 -> 0 | J47: =J41+J44 -> 0 | K47: =K41+K44 -> 0 | L47: =L41+L44 -> 0 | M47: =M41+M44 -> 0 | ... BE47: =BE41+BE44 -> 0
B48: Financial Actual | F48: =F42+F45 -> 0 | G48: =G42+G45 -> 0 | H48: =H42+H45 -> 0 | I48: =I42+I45 -> 0 | J48: =J42+J45 -> 0 | K48: =K42+K45 -> 0 | L48: =L42+L45 -> 0 | M48: =M42+M45 -> 0 | ... BE48: =BE42+BE45 -> 0
E49: To Date
B50: Current Financial Target | E50: =MAX(F50:BE50) -> 0 | F50: =IF($AZ$3>F24,F47,0) -> 0 | G50: =IF($AZ$3>G24,G47,0) -> 0 | H50: =IF($AZ$3>H24,H47,0) -> 0 | I50: =IF($AZ$3>I24,I47,0) -> 0 | J50: =IF($AZ$3>J24,J47,0) -> 0 | K50: =IF($AZ$3>K24,K47,0) -> 0 | L50: =IF($AZ$3>L24,L47,0) -> 0 | M50: =IF($AZ$3>M24,M47,0) -> 0 | ... BE50: =IF($AZ$3>BE24,BE47,0) -> 0
B51: Current Financial Actual | E51: =MAX(F51:BE51) -> 0 | F51: =IF($AZ$3>F25,F48,0) -> 0 | G51: =IF($AZ$3>G25,G48,0) -> 0 | H51: =IF($AZ$3>H25,H48,0) -> 0 | I51: =IF($AZ$3>I25,I48,0) -> 0 | J51: =IF($AZ$3>J25,J48,0) -> 0 | K51: =IF($AZ$3>K25,K48,0) -> 0 | L51: =IF($AZ$3>L25,L48,0) -> 0 | M51: =IF($AZ$3>M25,M48,0) -> 0 | ... BE51: =IF($AZ$3>BE25,BE48,0) -> 0

Sheet P5
B3: PROJECT | F3: IRIS 2.0, IRIS with Voice | AG3: Strategic Value | AO3: =F8 -> Internal Process | AV3: =IF(F7="",0,VLOOKUP(F7,Lookups!B4:H8,3)) -> 50 | AZ3: =NOW() -> 45961.476
AG4: Stage Multiplier (today) | AO4: =VLOOKUP(COUNTIF(AR10:AT21,"<="&AZ3),Table3357[],2) -> Dev | AV4: =IF(AO4="Not Def",0,VLOOKUP(AO4,Lookups!L4:M8,2)) -> 0.4 | AZ4: Current Qtr | BC4: =VLOOKUP((YEAR(AZ3)&"-"&MONTH(AZ3)),Lookups!S3:U21,2) -> 2025-Q4
B5: Description (Use Case) | F5: Allows the end user to ask IRIS questions using voice vs. typing in a request. | AG5: Stage Last Quarter | AO5: =VLOOKUP(COUNTIF(AR10:AT21,"<"&VLOOKUP(BC4,Lookups!W3:Y9,2)),Table3357[],2) -> Idea | AQ5: =IF(AV5=1,"No Change","Progression") -> Progression | AV5: =IF(AO4="Not Def",0,IF(AO5=AO4,1,1.2)) -> 1.2
AG6: PROJECT SCORE | AV6: =AV3*AV4*AV5 -> 24
B7: Category | F7: L3. AI-powered internal business process improvements | Y7: Ratio Impacted | AC7: Maintenance
B8: Strategic Value Level | F8: =IF(F7="","",VLOOKUP(F7,Lookups!B4:H8,2)) -> Internal Process
B9: Examples | F9: =IF(F7="","",VLOOKUP(F7,Lookups!B4:H8,4)) -> Automated customer support triage, intelligent lead scoring, predictive maintenance, churn analysis, scheduling | AG9: Stage | AJ9: Tasks | AO9: Target | AR9: Completed | AU9: Days to Target | AY9: Notes
AG10: Idea | AJ10: Project Defined | AO10: 45870 | AR10: 45870 | AU10: =IF(AO10=$BK$3,"Missing Target",IF(AR10=$BK$3,IF($AZ$3>AO10,INT($AZ$3-AO10)&" Day(s) Overdue","Incomplete"),IF(AR10>AO10,INT(AR10-AO10)&" Day(s) Late",IF(AR10=AO10,"OK",INT(AO10-AR10)&" Day(s) Ahead")))) -> OK
B11: PROJECT RESOURCES | F11: KEY PERFORMANCE INDICATORS / MEASURES OF SUCCESS | AJ11: Business Case approved | AO11: 45870 | AR11: 45870 | AU11: =IF(AO11=$BK$3,"Missing Target",IF(AR11=$BK$3,IF($AZ$3>AO11,INT($AZ$3-AO11)&" Day(s) Overdue","Incomplete"),IF(AR11>AO11,INT(AR11-AO11)&" Day(s) Late",IF(AR11=AO11,"OK",INT(AO11-AR11)&" Day(s) Ahead")))) -> OK
B12: AI Tools & Services | F12: =IF(F7="","",VLOOKUP(F7,Lookups!B4:H8,5)) -> Employee Satisfaction | O12: =IF(F7="","",VLOOKUP(F7,Lookups!B4:H8,6)) -> Productivity Gains | X12: =IF(F7="","",VLOOKUP(F7,Lookups!B4:H8,7)) -> Cost Savings | AJ12: Resources Allocated | AO12: 45901 | AR12: 45901 | AU12: =IF(AO12=$BK$3,"Missing Target",IF(AR12=$BK$3,IF($AZ$3>AO12,INT($AZ$3-AO12)&" Day(s) Overdue","Incomplete"),IF(AR12>AO12,INT(AR12-AO12)&" Day(s) Late",IF(AR12=AO12,"OK",INT(AO12-AR12)&" Day(s) Ahead")))) -> OK
B13: AWS, Chat Bot with voice search ability. | F13: KPI | G13: Audit Frequency and Results | O13: KPI | P13: Customer Satisfaction Scores (CSAT, NPS) | X13: KPI | Y13: .... Select the primary KPI (Jonas Library) | AG13: Develop | AJ13: Technical PoC validated | AO13: 45931 | AR13: 45931 | AU13: =IF(AO13=$BK$3,"Missing Target",IF(AR13=$BK$3,IF($AZ$3>AO13,INT($AZ$3-AO13)&" Day(s) Overdue","Incomplete"),IF(AR13>AO13,INT(AR13-AO13)&" Day(s) Late",IF(AR13=AO13,"OK",INT(AO13-AR13)&" Day(s) Ahead")))) -> OK
F14: How does this Project support this KPI? | O14: How does this Project support this KPI? | X14: How does this Project support this KPI? | AJ14: Dev roadmap documented | AU14: =IF(AO14=$BK$3,"Missing Target",IF(AR14=$BK$3,IF($AZ$3>AO14,INT($AZ$3-AO14)&" Day(s) Overdue","Incomplete"),IF(AR14>AO14,INT(AR14-AO14)&" Day(s) Late",IF(AR14=AO14,"OK",INT(AO14-AR14)&" Day(s) Ahead")))) -> Missing Target
F15: Provides customers with accurate information when asked from within the Compete application. | O15: Provides quick and easy access to customer questions and saves time by not having to call into the call center for assistance. Increases customer satisfaction for more immediate answers and allows less wait time for more in depth questions with an agent. | AJ15: Coding started | AU15: =IF(AO15=$A$1,"Missing Target",IF(AR15=$A$1,IF($AZ$3>AO15,INT($AZ$3-AO15)&" Day(s) Overdue","Incomplete"),IF(AR15>AO15,INT(AR15-AO15)&" Day(s) Late",IF(AR15=AO15,"OK",INT(AO15-AR15)&" Day(s) Ahead")))) -> Missing Target
AG16: Pilot | AJ16: Deployment to beta | AU16: =IF(AO16=$A$1,"Missing Target",IF(AR16=$A$1,IF($AZ$3>AO16,INT($AZ$3-AO16)&" Day(s) Overdue","Incomplete"),IF(AR16>AO16,INT(AR16-AO16)&" Day(s) Late",IF(AR16=AO16,"OK",INT(AO16-AR16)&" Day(s) Ahead")))) -> Missing Target
B17: Contact | C17: James.Peltier@jonasfitness.com | AJ17: Initial metrics/feedback | AU17: =IF(AO17=$A$1,"Missing Target",IF(AR17=$A$1,IF($AZ$3>AO17,INT($AZ$3-AO17)&" Day(s) Overdue","Incomplete"),IF(AR17>AO17,INT(AR17-AO17)&" Day(s) Late",IF(AR17=AO17,"OK",INT(AO17-AR17)&" Day(s) Ahead")))) -> Missing Target
B18: Prod Mgr | C18: Kari Ewersen | F18: How will you measure the KPI? | O18: How will you measure the KPI? | X18: How will you measure the KPI? | AJ18: Feedback affecting code | AU18: =IF(AO18=$A$1,"Missing Target",IF(AR18=$A$1,IF($AZ$3>AO18,INT($AZ$3-AO18)&" Day(s) Overdue","Incomplete"),IF(AR18>AO18,INT(AR18-AO18)&" Day(s) Late",IF(AR18=AO18,"OK",INT(AO18-AR18)&" Day(s) Ahead")))) -> Missing Target
B19: Analyst | C19: Chase Winston | F19: 20% of correct answers and cases that result from a customer being routed from the chat bot to the call center for additional help. | O19: Comparison of the number of calls routed to support and metrics around the use of the tool with 20% reduction in in person support needed. | AG19: Live | AJ19: General release available | AU19: =IF(AO19=$A$1,"Missing Target",IF(AR19=$A$1,IF($AZ$3>AO19,INT($AZ$3-AO19)&" Day(s) Overdue","Incomplete"),IF(AR19>AO19,INT(AR19-AO19)&" Day(s) Late",IF(AR19=AO19,"OK",INT(AO19-AR19)&" Day(s) Ahead")))) -> Missing Target
B20: Tech Lead | C20: Jim Peltier | AJ20: Success metrics tracking | AU20: =IF(AO20=$A$1,"Missing Target",IF(AR20=$A$1,IF($AZ$3>AO20,INT($AZ$3-AO20)&" Day(s) Overdue","Incomplete"),IF(AR20>AO20,INT(AR20-AO20)&" Day(s) Late",IF(AR20=AO20,"OK",INT(AO20-AR20)&" Day(s) Ahead")))) -> Missing Target
B21: Exec | C21: Sandy Crutcher | AJ21: Feedback loop continuing | AU21: =IF(AO21=$A$1,"Missing Target",IF(AR21=$A$1,IF($AZ$3>AO21,INT($AZ$3-AO21)&" Day(s) Overdue","Incomplete"),IF(AR21>AO21,INT(AR21-AO21)&" Day(s) Late",IF(AR21=AO21,"OK",INT(AO21-AR21)&" Day(s) Ahead")))) -> Missing Target
B23: WEEKLY KPI TRACKER | F23: 1 | G23: =F23+1 -> 2 | H23: =G23+1 -> 3 | I23: =H23+1 -> 4 | J23: =I23+1 -> 5 | K23: =J23+1 -> 6 | L23: =K23+1 -> 7 | M23: =L23+1 -> 8 | N23: =M23+1 -> 9 | ... BE23: =BD23+1 -> 52
B24: Week Ending | F24: 46022 | G24: =F24+7 -> 46029 | H24: =G24+7 -> 46036 | I24: =H24+7 -> 46043 | J24: =I24+7 -> 46050 | K24: =J24+7 -> 46057 | L24: =K24+7 -> 46064 | M24: =L24+7 -> 46071 | N24: =M24+7 -> 46078 | ... BE24: =BD24+7 -> 46379
B25: =G13&" TARGET" -> Audit Frequency and Results TARGET | F25: 20 | G25: =F25 -> 20 | H25: =G25 -> 20 | I25: =H25 -> 20 | J25: =I25 -> 20 | K25: =J25 -> 20 | L25: =K25 -> 20 | M25: =L25 -> 20 | N25: =M25 -> 20 | ... BE25: =BD25 -> 20
B26: Actual | F26: 0 | G26: 0 | H26: 0 | I26: 0 | J26: 0 | K26: 0 | L26: 0 | M26: 0 | N26: 0 | O26: 0 | P26: 0 | Q26: 0 | R26: 0 | S26: 0 | T26: 0 | U26: 0 | V26: 0 | W26: 0 | X26: 0 | Y26: 0 | Z26: 0 | AA26: 0 | AB26: 0 | AC26: 0 | AD26: 0 | AE26: 0 | AF26: 0 | AG26: 0 | AH26: 0 | AI26: 0 | AJ26: 0 | AK26: 0 | AL26: 0 | AM26: 0 | AN26: 0 | AO26: 0 | AP26: 0 | AQ26: 0 | AR26: 0 | AS26: 0 | AT26: 0 | AU26: 0 | AV26: 0 | AW26: 0 | AX26: 0 | AY26: 0 | AZ26: 0 | BA26: 0 | BB26: 0 | BC26: 0 | BD26: 0 | BE26: 0
B27: Delta | F27: =F26-F25 -> -20 | G27: =G26-G25 -> -20 | H27: =H26-H25 -> -20 | I27: =I26-I25 -> -20 | J27: =J26-J25 -> -20 | K27: =K26-K25 -> -20 | L27: =L26-L25 -> -20 | M27: =M26-M25 -> -20 | ... BE27: =BE26-BE25 -> -20
B28: Notes on this KPI (anything to add this week?)
B30: =P13&" TARGET" -> Customer Satisfaction Scores (CSAT, NPS) TARGET | F30: 20 | G30: =F30 -> 20 | H30: =G30 -> 20 | I30: =H30 -> 20 | J30: =I30 -> 20 | K30: =J30 -> 20 | L30: =K30 -> 20 | M30: =L30 -> 20 | N30: =M30 -> 20 | ... BE30: =BD30 -> 20
B31: Actual | F31: 0 | G31: 0 | H31: 0 | I31: 0 | J31: 0 | K31: 0 | L31: 0 | M31: 0 | N31: 0 | O31: 0 | P31: 0 | Q31: 0 | R31: 0 | S31: 0 | T31: 0 | U31: 0 | V31: 0 | W31: 0 | X31: 0 | Y31: 0 | Z31: 0 | AA31: 0 | AB31: 0 | AC31: 0 | AD31: 0 | AE31: 0 | AF31: 0 | AG31: 0 | AH31: 0 | AI31: 0 | AJ31: 0 | AK31: 0 | AL31: 0 | AM31: 0 | AN31: 0 | AO31: 0 | AP31: 0 | AQ31: 0 | AR31: 0 | AS31: 0 | AT31: 0 | AU31: 0 | AV31: 0 | AW31: 0 | AX31: 0 | AY31: 0 | AZ31: 0 | BA31: 0 | BB31: 0 | BC31: 0 | BD31: 0 | BE31: 0
B32: Delta | F32: =F31-F30 -> -20 | G32: =G31-G30 -> -20 | H32: =H31-H30 -> -20 | I32: =I31-I30 -> -20 | J32: =J31-J30 -> -20 | K32: =K31-K30 -> -20 | L32: =L31-L30 -> -20 | M32: =M31-M30 -> -20 | ... BE32: =BE31-BE30 -> -20
B33: Notes on this KPI (anything to add this week?)
B35: =Y13&" TARGET" -> .... Select the primary KPI (Jonas Library) TARGET | G35: =F35 -> 0 | H35: =G35 -> 0 | I35: =H35 -> 0 | J35: =I35 -> 0 | K35: =J35 -> 0 | L35: =K35 -> 0 | M35: =L35 -> 0 | N35: =M35 -> 0 | ... BE35: =BD35 -> 0
B36: Actual | F36: 0 | G36: 0 | H36: 0 | I36: 0 | J36: 0 | K36: 0 | L36: 0 | M36: 0
B37: Delta | F37: =F36-F35 -> 0 | G37: =G36-G35 -> 0 | H37: =H36-H35 -> 0 | I37: =I36-I35 -> 0 | J37: =J36-J35 -> 0 | K37: =K36-K35 -> 0 | L37: =L36-L35 -> 0 | M37: =M36-M35 -> 0 | ... BE37: =BE36-BE35 -> 0
B38: Notes on this KPI (anything to add this week?)
B41: Revenue Target | F41: =IF($X$12="Revenue Impact",F35,0) -> 0 | G41: =IF($X$12="Revenue Impact",G35,0) -> 0 | H41: =IF($X$12="Revenue Impact",H35,0) -> 0 | I41: =IF($X$12="Revenue Impact",I35,0) -> 0 | J41: =IF($X$12="Revenue Impact",J35,0) -> 0 | K41: =IF($X$12="Revenue Impact",K35,0) -> 0 | L41: =IF($X$12="Revenue Impact",L35,0) -> 0 | M41: =IF($X$12="Revenue Impact",M35,0) -> 0 | ... BE41: =IF($X$12="Revenue Impact",BE35,0) -> 0
B42: Revenue Actual | F42: =IF($X$12="Revenue Impact",F36,0) -> 0 | G42: =IF($X$12="Revenue Impact",G36,0) -> 0 | H42: =IF($X$12="Revenue Impact",H36,0) -> 0 | I42: =IF($X$12="Revenue Impact",I36,0) -> 0 | J42: =IF($X$12="Revenue Impact",J36,0) -> 0 | K42: =IF($X$12="Revenue Impact",K36,0) -> 0 | L42: =IF($X$12="Revenue Impact",L36,0) -> 0 | M42: =IF($X$12="Revenue Impact",M36,0) -> 0 | ... BE42: =IF($X$12="Revenue Impact",BE36,0) -> 0
B44: Cost Target | F44: =IF($X$12="Cost Savings",F35,0) -> 0 | G44: =IF($X$12="Cost Savings",G35,0) -> 0 | H44: =IF($X$12="Cost Savings",H35,0) -> 0 | I44: =IF($X$12="Cost Savings",I35,0) -> 0 | J44: =IF($X$12="Cost Savings",J35,0) -> 0 | K44: =IF($X$12="Cost Savings",K35,0) -> 0 | L44: =IF($X$12="Cost Savings",L35,0) -> 0 | M44: =IF($X$12="Cost Savings",M35,0) -> 0 | ... BE44: =IF($X$12="Cost Savings",BE35,0) -> 0
B45: Cost Actual | F45: =IF($X$12="Cost Savings",F36,0) -> 0 | G45: =IF($X$12="Cost Savings",G36,0) -> 0 | H45: =IF($X$12="Cost Savings",H36,0) -> 0 | I45: =IF($X$12="Cost Savings",I36,0) -> 0 | J45: =IF($X$12="Cost Savings",J36,0) -> 0 | K45: =IF($X$12="Cost Savings",K36,0) -> 0 | L45: =IF($X$12="Cost Savings",L36,0) -> 0 | M45: =IF($X$12="Cost Savings",M36,0) -> 0 | ... BE45: =IF($X$12="Cost Savings",BE36,0) -> 0
B47: Financial Target | F47: =F41+F44 -> 0 | G47: =G41+G44 -> 0 | H47: =H41+H44 -> 0 | I47: =I41+I44 -> 0 | J47: =J41+J44 -> 0 | K47: =K41+K44 -> 0 | L47: =L41+L44 -> 0 | M47: =M41+M44 -> 0 | ... BE47: =BE41+BE44 -> 0
B48: Financial Actual | F48: =F42+F45 -> 0 | G48: =G42+G45 -> 0 | H48: =H42+H45 -> 0 | I48: =I42+I45 -> 0 | J48: =J42+J45 -> 0 | K48: =K42+K45 -> 0 | L48: =L42+L45 -> 0 | M48: =M42+M45 -> 0 | ... BE48: =BE42+BE45 -> 0
E49: To Date
B50: Current Financial Target | E50: =MAX(F50:BE50) -> 0 | F50: =IF($AZ$3>F24,F47,0) -> 0 | G50: =IF($AZ$3>G24,G47,0) -> 0 | H50: =IF($AZ$3>H24,H47,0) -> 0 | I50: =IF($AZ$3>I24,I47,0) -> 0 | J50: =IF($AZ$3>J24,J47,0) -> 0 | K50: =IF($AZ$3>K24,K47,0) -> 0 | L50: =IF($AZ$3>L24,L47,0) -> 0 | M50: =IF($AZ$3>M24,M47,0) -> 0 | ... BE50: =IF($AZ$3>BE24,BE47,0) -> 0
B51: Current Financial Actual | E51: =MAX(F51:BE51) -> 0 | F51: =IF($AZ$3>F25,F48,0) -> 0 | G51: =IF($AZ$3>G25,G48,0) -> 0 | H51: =IF($AZ$3>H25,H48,0) -> 0 | I51: =IF($AZ$3>I25,I48,0) -> 0 | J51: =IF($AZ$3>J25,J48,0) -> 0 | K51: =IF($AZ$3>K25,K48,0) -> 0 | L51: =IF($AZ$3>L25,L48,0) -> 0 | M51: =IF($AZ$3>M25,M48,0) -> 0 | ... BE51: =IF($AZ$3>BE25,BE48,0) -> 0

Sheet P6
B3: PROJECT | F3: Compete AI Project: Phase I - Front Desk Redesign | AG3: Strategic Value | AO3: =F8 -> Customer Feature - Existing | AV3: =IF(F7="",0,VLOOKUP(F7,Lookups!B4:H8,3)) -> 100 | AZ3: =NOW() -> 45961.476
AG4: Stage Multiplier (today) | AO4: =VLOOKUP(COUNTIF(AR10:AT21,"<="&AZ3),Table3357[],2) -> Dev | AV4: =IF(AO4="Not Def",0,VLOOKUP(AO4,Lookups!L4:M8,2)) -> 0.4 | AZ4: Current Qtr | BC4: =VLOOKUP((YEAR(AZ3)&"-"&MONTH(AZ3)),Lookups!S3:U21,2) -> 2025-Q4
B5: Description (Use Case) | F5: Addressing key attrition concern: FD is cubersome, too many clicks to complete functions and not steamlined for FD staff. | AG5: Stage Last Quarter | AO5: =VLOOKUP(COUNTIF(AR10:AT21,"<"&VLOOKUP(BC4,Lookups!W3:Y9,2)),Table3357[],2) -> Dev | AQ5: =IF(AV5=1,"No Change","Progression") -> No Change | AV5: =IF(AO4="Not Def",0,IF(AO5=AO4,1,1.2)) -> 1
AG6: PROJECT SCORE | AV6: =AV3*AV4*AV5 -> 40
B7: Category | F7: L4. Using AI to enhance existing customer-facing products | Y7: Ratio Impacted | AC7: S&M
B8: Strategic Value Level | F8: =IF(F7="","",VLOOKUP(F7,Lookups!B4:H8,2)) -> Customer Feature - Existing
B9: Examples | F9: =IF(F7="","",VLOOKUP(F7,Lookups!B4:H8,4)) -> Smart data analysis in existing dashboards, intelligent recommendations, automated report generation | AG9: Stage | AJ9: Tasks | AO9: Target | AR9: Completed | AU9: Days to Target | AY9: Notes
AG10: Idea | AJ10: Project Defined | AO10: 45658 | AR10: 45658 | AU10: =IF(AO10=$BK$3,"Missing Target",IF(AR10=$BK$3,IF($AZ$3>AO10,INT($AZ$3-AO10)&" Day(s) Overdue","Incomplete"),IF(AR10>AO10,INT(AR10-AO10)&" Day(s) Late",IF(AR10=AO10,"OK",INT(AO10-AR10)&" Day(s) Ahead")))) -> OK
B11: PROJECT RESOURCES | F11: KEY PERFORMANCE INDICATORS / MEASURES OF SUCCESS | AJ11: Business Case approved | AO11: 45658 | AR11: 45658 | AU11: =IF(AO11=$BK$3,"Missing Target",IF(AR11=$BK$3,IF($AZ$3>AO11,INT($AZ$3-AO11)&" Day(s) Overdue","Incomplete"),IF(AR11>AO11,INT(AR11-AO11)&" Day(s) Late",IF(AR11=AO11,"OK",INT(AO11-AR11)&" Day(s) Ahead")))) -> OK
B12: AI Tools & Services | F12: =IF(F7="","",VLOOKUP(F7,Lookups!B4:H8,5)) -> Customer Adoption | O12: =IF(F7="","",VLOOKUP(F7,Lookups!B4:H8,6)) -> Usage Metrics | X12: =IF(F7="","",VLOOKUP(F7,Lookups!B4:H8,7)) -> Revenue Impact | AJ12: Resources Allocated | AO12: 45658 | AR12: 45658 | AU12: =IF(AO12=$BK$3,"Missing Target",IF(AR12=$BK$3,IF($AZ$3>AO12,INT($AZ$3-AO12)&" Day(s) Overdue","Incomplete"),IF(AR12>AO12,INT(AR12-AO12)&" Day(s) Late",IF(AR12=AO12,"OK",INT(AO12-AR12)&" Day(s) Ahead")))) -> OK
B13: Orbit | F13: KPI | G13: # of Customers using the AI | O13: KPI | P13: Customer Satisfaction Scores (CSAT, NPS) | X13: KPI | Y13: .... Select the primary KPI (Jonas Library) | AG13: Develop | AJ13: Technical PoC validated | AO13: 45689 | AR13: 45689 | AU13: =IF(AO13=$BK$3,"Missing Target",IF(AR13=$BK$3,IF($AZ$3>AO13,INT($AZ$3-AO13)&" Day(s) Overdue","Incomplete"),IF(AR13>AO13,INT(AR13-AO13)&" Day(s) Late",IF(AR13=AO13,"OK",INT(AO13-AR13)&" Day(s) Ahead")))) -> OK
F14: How does this Project support this KPI? | O14: How does this Project support this KPI? | X14: How does this Project support this KPI? | AJ14: Dev roadmap documented | AO14: 45689 | AR14: 45689 | AU14: =IF(AO14=$BK$3,"Missing Target",IF(AR14=$BK$3,IF($AZ$3>AO14,INT($AZ$3-AO14)&" Day(s) Overdue","Incomplete"),IF(AR14>AO14,INT(AR14-AO14)&" Day(s) Late",IF(AR14=AO14,"OK",INT(AO14-AR14)&" Day(s) Ahead")))) -> OK
F15: Customers will be able to access the Front Desk in the traditional fashion but have the ability to flip to the traditional UI which will allow them to gradually get used to the new front desk. | O15: Usage of the new AI feature will address feedback from clients that our FD is too cubersome and involved too many clicks. | AJ15: Coding started | AO15: 45689 | AR15: 45689 | AU15: =IF(AO15=$A$1,"Missing Target",IF(AR15=$A$1,IF($AZ$3>AO15,INT($AZ$3-AO15)&" Day(s) Overdue","Incomplete"),IF(AR15>AO15,INT(AR15-AO15)&" Day(s) Late",IF(AR15=AO15,"OK",INT(AO15-AR15)&" Day(s) Ahead")))) -> OK
AG16: Pilot | AJ16: Deployment to beta | AO16: 46022 | AU16: =IF(AO16=$A$1,"Missing Target",IF(AR16=$A$1,IF($AZ$3>AO16,INT($AZ$3-AO16)&" Day(s) Overdue","Incomplete"),IF(AR16>AO16,INT(AR16-AO16)&" Day(s) Late",IF(AR16=AO16,"OK",INT(AO16-AR16)&" Day(s) Ahead")))) -> Incomplete
B17: Contact | C17: James.Peltier@jonasfitness.com | AJ17: Initial metrics/feedback | AO17: 46022 | AU17: =IF(AO17=$A$1,"Missing Target",IF(AR17=$A$1,IF($AZ$3>AO17,INT($AZ$3-AO17)&" Day(s) Overdue","Incomplete"),IF(AR17>AO17,INT(AR17-AO17)&" Day(s) Late",IF(AR17=AO17,"OK",INT(AO17-AR17)&" Day(s) Ahead")))) -> Incomplete
B18: Prod Mgr | C18: Kari Ewersen | F18: How will you measure the KPI? | O18: How will you measure the KPI? | X18: How will you measure the KPI? | AJ18: Feedback affecting code | AO18: 46022 | AU18: =IF(AO18=$A$1,"Missing Target",IF(AR18=$A$1,IF($AZ$3>AO18,INT($AZ$3-AO18)&" Day(s) Overdue","Incomplete"),IF(AR18>AO18,INT(AR18-AO18)&" Day(s) Late",IF(AR18=AO18,"OK",INT(AO18-AR18)&" Day(s) Ahead")))) -> Incomplete
B19: Analyst | C19: Chase Winston | F19: Usage metrics in the front desk of # of users accessing and using the new interface, goal of 20% usage. | O19: Customer feedback in focus groups and NPS surveys with satisfaction score increase of 20%. | AG19: Live | AJ19: General release available | AO19: 46112 | AU19: =IF(AO19=$A$1,"Missing Target",IF(AR19=$A$1,IF($AZ$3>AO19,INT($AZ$3-AO19)&" Day(s) Overdue","Incomplete"),IF(AR19>AO19,INT(AR19-AO19)&" Day(s) Late",IF(AR19=AO19,"OK",INT(AO19-AR19)&" Day(s) Ahead")))) -> Incomplete
B20: Tech Lead | C20: Jim Peltier | AJ20: Success metrics tracking | AO20: 46112 | AU20: =IF(AO20=$A$1,"Missing Target",IF(AR20=$A$1,IF($AZ$3>AO20,INT($AZ$3-AO20)&" Day(s) Overdue","Incomplete"),IF(AR20>AO20,INT(AR20-AO20)&" Day(s) Late",IF(AR20=AO20,"OK",INT(AO20-AR20)&" Day(s) Ahead")))) -> Incomplete
B21: Exec | C21: Sandy Crutcher | AJ21: Feedback loop continuing | AO21: 46112 | AU21: =IF(AO21=$A$1,"Missing Target",IF(AR21=$A$1,IF($AZ$3>AO21,INT($AZ$3-AO21)&" Day(s) Overdue","Incomplete"),IF(AR21>AO21,INT(AR21-AO21)&" Day(s) Late",IF(AR21=AO21,"OK",INT(AO21-AR21)&" Day(s) Ahead")))) -> Incomplete
B23: WEEKLY KPI TRACKER | F23: 1 | G23: =F23+1 -> 2 | H23: =G23+1 -> 3 | I23: =H23+1 -> 4 | J23: =I23+1 -> 5 | K23: =J23+1 -> 6 | L23: =K23+1 -> 7 | M23: =L23+1 -> 8 | N23: =M23+1 -> 9 | ... BE23: =BD23+1 -> 52
B24: Week Ending | F24: 46112 | G24: =F24+7 -> 46119 | H24: =G24+7 -> 46126 | I24: =H24+7 -> 46133 | J24: =I24+7 -> 46140 | K24: =J24+7 -> 46147 | L24: =K24+7 -> 46154 | M24: =L24+7 -> 46161 | N24: =M24+7 -> 46168 | ... BE24: =BD24+7 -> 46469
B25: =G13&" TARGET" -> # of Customers using the AI TARGET | F25: 20 | G25: =F25 -> 20 | H25: =G25 -> 20 | I25: =H25 -> 20 | J25: =I25 -> 20 | K25: =J25 -> 20 | L25: =K25 -> 20 | M25: =L25 -> 20 | N25: =M25 -> 20 | ... BE25: =BD25 -> 20
B26: Actual | F26: 0 | G26: 0 | H26: 0 | I26: 0 | J26: 0 | K26: 0 | L26: 0 | M26: 0 | N26: 0 | O26: 0 | P26: 0 | Q26: 0 | R26: 0 | S26: 0 | T26: 0 | U26: 0 | V26: 0 | W26: 0 | X26: 0 | Y26: 0 | Z26: 0 | AA26: 0 | AB26: 0 | AC26: 0 | AD26: 0 | AE26: 0 | AF26: 0 | AG26: 0 | AH26: 0 | AI26: 0 | AJ26: 0 | AK26: 0 | AL26: 0 | AM26: 0 | AN26: 0 | AO26: 0 | AP26: 0 | AQ26: 0 | AR26: 0 | AS26: 0 | AT26: 0 | AU26: 0 | AV26: 0 | AW26: 0 | AX26: 0 | AY26: 0 | AZ26: 0 | BA26: 0 | BB26: 0 | BC26: 0 | BD26: 0 | BE26: 0
B27: Delta | F27: =F26-F25 -> -20 | G27: =G26-G25 -> -20 | H27: =H26-H25 -> -20 | I27: =I26-I25 -> -20 | J27: =J26-J25 -> -20 | K27: =K26-K25 -> -20 | L27: =L26-L25 -> -20 | M27: =M26-M25 -> -20 | ... BE27: =BE26-BE25 -> -20
B28: Notes on this KPI (anything to add this week?)
B30: =P13&" TARGET" -> Customer Satisfaction Scores (CSAT, NPS) TARGET | F30: 20 | G30: =F30 -> 20 | H30: =G30 -> 20 | I30: =H30 -> 20 | J30: =I30 -> 20 | K30: =J30 -> 20 | L30: =K30 -> 20 | M30: =L30 -> 20 | N30: =M30 -> 20 | ... BE30: =BD30 -> 20
B31: Actual | F31: 0 | G31: 0 | H31: 0 | I31: 0 | J31: 0 | K31: 0 | L31: 0 | M31: 0 | N31: 0 | O31: 0 | P31: 0 | Q31: 0 | R31: 0 | S31: 0 | T31: 0 | U31: 0 | V31: 0 | W31: 0 | X31: 0 | Y31: 0 | Z31: 0 | AA31: 0 | AB31: 0 | AC31: 0 | AD31: 0 | AE31: 0 | AF31: 0 | AG31: 0 | AH31: 0 | AI31: 0 | AJ31: 0 | AK31: 0 | AL31: 0 | AM31: 0 | AN31: 0 | AO31: 0 | AP31: 0 | AQ31: 0 | AR31: 0 | AS31: 0 | AT31: 0 | AU31: 0 | AV31: 0 | AW31: 0 | AX31: 0 | AY31: 0 | AZ31: 0 | BA31: 0 | BB31: 0 | BC31: 0 | BD31: 0 | BE31: 0
B32: Delta | F32: =F31-F30 -> -20 | G32: =G31-G30 -> -20 | H32: =H31-H30 -> -20 | I32: =I31-I30 -> -20 | J32: =J31-J30 -> -20 | K32: =K31-K30 -> -20 | L32: =L31-L30 -> -20 | M32: =M31-M30 -> -20 | ... BE32: =BE31-BE30 -> -20
B33: Notes on this KPI (anything to add this week?)
B35: =Y13&" TARGET" -> .... Select the primary KPI (Jonas Library) TARGET | G35: =F35 -> 0 | H35: =G35 -> 0 | I35: =H35 -> 0 | J35: =I35 -> 0 | K35: =J35 -> 0 | L35: =K35 -> 0 | M35: =L35 -> 0 | N35: =M35 -> 0 | ... BE35: =BD35 -> 0
B36: Actual | F36: 0 | G36: 0 | H36: 0 | I36: 0 | J36: 0 | K36: 0 | L36: 0 | M36: 0
B37: Delta | F37: =F36-F35 -> 0 | G37: =G36-G35 -> 0 | H37: =H36-H35 -> 0 | I37: =I36-I35 -> 0 | J37: =J36-J35 -> 0 | K37: =K36-K35 -> 0 | L37: =L36-L35 -> 0 | M37: =M36-M35 -> 0 | ... BE37: =BE36-BE35 -> 0
B38: Notes on this KPI (anything to add this week?)
B41: Revenue Target | F41: =IF($X$12="Revenue Impact",F35,0) -> 0 | G41: =IF($X$12="Revenue Impact",G35,0) -> 0 | H41: =IF($X$12="Revenue Impact",H35,0) -> 0 | I41: =IF($X$12="Revenue Impact",I35,0) -> 0 | J41: =IF($X$12="Revenue Impact",J35,0) -> 0 | K41: =IF($X$12="Revenue Impact",K35,0) -> 0 | L41: =IF($X$12="Revenue Impact",L35,0) -> 0 | M41: =IF($X$12="Revenue Impact",M35,0) -> 0 | ... BE41: =IF($X$12="Revenue Impact",BE35,0) -> 0
B42: Revenue Actual | F42: =IF($X$12="Revenue Impact",F36,0) -> 0 | G42: =IF($X$12="Revenue Impact",G36,0) -> 0 | H42: =IF($X$12="Revenue Impact",H36,0) -> 0 | I42: =IF($X$12="Revenue Impact",I36,0) -> 0 | J42: =IF($X$12="Revenue Impact",J36,0) -> 0 | K42: =IF($X$12="Revenue Impact",K36,0) -> 0 | L42: =IF($X$12="Revenue Impact",L36,0) -> 0 | M42: =IF($X$12="Revenue Impact",M36,0) -> 0 | ... BE42: =IF($X$12="Revenue Impact",BE36,0) -> 0
B44: Cost Target | F44: =IF($X$12="Cost Savings",F35,0) -> 0 | G44: =IF($X$12="Cost Savings",G35,0) -> 0 | H44: =IF($X$12="Cost Savings",H35,0) -> 0 | I44: =IF($X$12="Cost Savings",I35,0) -> 0 | J44: =IF($X$12="Cost Savings",J35,0) -> 0 | K44: =IF($X$12="Cost Savings",K35,0) -> 0 | L44: =IF($X$12="Cost Savings",L35,0) -> 0 | M44: =IF($X$12="Cost Savings",M35,0) -> 0 | ... BE44: =IF($X$12="Cost Savings",BE35,0) -> 0
B45: Cost Actual | F45: =IF($X$12="Cost Savings",F36,0) -> 0 | G45: =IF($X$12="Cost Savings",G36,0) -> 0 | H45: =IF($X$12="Cost Savings",H36,0) -> 0 | I45: =IF($X$12="Cost Savings",I36,0) -> 0 | J45: =IF($X$12="Cost Savings",J36,0) -> 0 | K45: =IF($X$12="Cost Savings",K36,0) -> 0 | L45: =IF($X$12="Cost Savings",L36,0) -> 0 | M45: =IF($X$12="Cost Savings",M36,0) -> 0 | ... BE45: =IF($X$12="Cost Savings",BE36,0) -> 0
B47: Financial Target | F47: =F41+F44 -> 0 | G47: =G41+G44 -> 0 | H47: =H41+H44 -> 0 | I47: =I41+I44 -> 0 | J47: =J41+J44 -> 0 | K47: =K41+K44 -> 0 | L47: =L41+L44 -> 0 | M47: =M41+M44 -> 0 | ... BE47: =BE41+BE44 -> 0
B48: Financial Actual | F48: =F42+F45 -> 0 | G48: =G42+G45 -> 0 | H48: =H42+H45 -> 0 | I48: =I42+I45 -> 0 | J48: =J42+J45 -> 0 | K48: =K42+K45 -> 0 | L48: =L42+L45 -> 0 | M48: =M42+M45 -> 0 | ... BE48: =BE42+BE45 -> 0
E49: To Date
B50: Current Financial Target | E50: =MAX(F50:BE50) -> 0 | F50: =IF($AZ$3>F24,F47,0) -> 0 | G50: =IF($AZ$3>G24,G47,0) -> 0 | H50: =IF($AZ$3>H24,H47,0) -> 0 | I50: =IF($AZ$3>I24,I47,0) -> 0 | J50: =IF($AZ$3>J24,J47,0) -> 0 | K50: =IF($AZ$3>K24,K47,0) -> 0 | L50: =IF($AZ$3>L24,L47,0) -> 0 | M50: =IF($AZ$3>M24,M47,0) -> 0 | ... BE50: =IF($AZ$3>BE24,BE47,0) -> 0
B51: Current Financial Actual | E51: =MAX(F51:BE51) -> 0 | F51: =IF($AZ$3>F25,F48,0) -> 0 | G51: =IF($AZ$3>G25,G48,0) -> 0 | H51: =IF($AZ$3>H25,H48,0) -> 0 | I51: =IF($AZ$3>I25,I48,0) -> 0 | J51: =IF($AZ$3>J25,J48,0) -> 0 | K51: =IF($AZ$3>K25,K48,0) -> 0 | L51: =IF($AZ$3>L25,L48,0) -> 0 | M51: =IF($AZ$3>M25,M48,0) -> 0 | ... BE51: =IF($AZ$3>BE25,BE48,0) -> 0

Sheet P7
B3: PROJECT | F3: Compete AI Project Phase II: Front Desk Redesign, use of APIs to appear as a web-based product. | AG3: Strategic Value | AO3: =F8 -> Customer Feature - Existing | AV3: =IF(F7="",0,VLOOKUP(F7,Lookups!B4:H8,3)) -> 100 | AZ3: =NOW() -> 45961.476
AG4: Stage Multiplier (today) | AO4: =VLOOKUP(COUNTIF(AR10:AT21,"<="&AZ3),Table3357[],2) -> Dev | AV4: =IF(AO4="Not Def",0,VLOOKUP(AO4,Lookups!L4:M8,2)) -> 0.4 | AZ4: Current Qtr | BC4: =VLOOKUP((YEAR(AZ3)&"-"&MONTH(AZ3)),Lookups!S3:U21,2) -> 2025-Q4
B5: Description (Use Case) | F5: Addressing the key reason given for new logo lost deals: Compete is not a true web-based product. Currently requires a thin client to be installed to function. | AG5: Stage Last Quarter | AO5: =VLOOKUP(COUNTIF(AR10:AT21,"<"&VLOOKUP(BC4,Lookups!W3:Y9,2)),Table3357[],2) -> Dev | AQ5: =IF(AV5=1,"No Change","Progression") -> No Change | AV5: =IF(AO4="Not Def",0,IF(AO5=AO4,1,1.2)) -> 1
AG6: PROJECT SCORE | AV6: =AV3*AV4*AV5 -> 40
B7: Category | F7: L4. Using AI to enhance existing customer-facing products | Y7: Ratio Impacted | AC7: S&M
B8: Strategic Value Level | F8: =IF(F7="","",VLOOKUP(F7,Lookups!B4:H8,2)) -> Customer Feature - Existing
B9: Examples | F9: =IF(F7="","",VLOOKUP(F7,Lookups!B4:H8,4)) -> Smart data analysis in existing dashboards, intelligent recommendations, automated report generation | AG9: Stage | AJ9: Tasks | AO9: Target | AR9: Completed | AU9: Days to Target | AY9: Notes
AG10: Idea | AJ10: Project Defined | AO10: 45658 | AR10: 45658 | AU10: =IF(AO10=$BK$3,"Missing Target",IF(AR10=$BK$3,IF($AZ$3>AO10,INT($AZ$3-AO10)&" Day(s) Overdue","Incomplete"),IF(AR10>AO10,INT(AR10-AO10)&" Day(s) Late",IF(AR10=AO10,"OK",INT(AO10-AR10)&" Day(s) Ahead")))) -> OK
B11: PROJECT RESOURCES | F11: KEY PERFORMANCE INDICATORS / MEASURES OF SUCCESS | AJ11: Business Case approved | AO11: 45658 | AR11: 45658 | AU11: =IF(AO11=$BK$3,"Missing Target",IF(AR11=$BK$3,IF($AZ$3>AO11,INT($AZ$3-AO11)&" Day(s) Overdue","Incomplete"),IF(AR11>AO11,INT(AR11-AO11)&" Day(s) Late",IF(AR11=AO11,"OK",INT(AO11-AR11)&" Day(s) Ahead")))) -> OK
B12: AI Tools & Services | F12: =IF(F7="","",VLOOKUP(F7,Lookups!B4:H8,5)) -> Customer Adoption | O12: =IF(F7="","",VLOOKUP(F7,Lookups!B4:H8,6)) -> Usage Metrics | X12: =IF(F7="","",VLOOKUP(F7,Lookups!B4:H8,7)) -> Revenue Impact | AJ12: Resources Allocated | AO12: 45658 | AR12: 45658 | AU12: =IF(AO12=$BK$3,"Missing Target",IF(AR12=$BK$3,IF($AZ$3>AO12,INT($AZ$3-AO12)&" Day(s) Overdue","Incomplete"),IF(AR12>AO12,INT(AR12-AO12)&" Day(s) Late",IF(AR12=AO12,"OK",INT(AO12-AR12)&" Day(s) Ahead")))) -> OK
B13: Orbit, APIs. | F13: KPI | G13: .... Select the primary KPI (Jonas Library) | O13: KPI | P13: # of Customers using the AI | X13: KPI | Y13: Revenue Growth from AI-enhanced products | AG13: Develop | AJ13: Technical PoC validated | AO13: 45689 | AR13: 45689 | AU13: =IF(AO13=$BK$3,"Missing Target",IF(AR13=$BK$3,IF($AZ$3>AO13,INT($AZ$3-AO13)&" Day(s) Overdue","Incomplete"),IF(AR13>AO13,INT(AR13-AO13)&" Day(s) Late",IF(AR13=AO13,"OK",INT(AO13-AR13)&" Day(s) Ahead")))) -> OK
F14: How does this Project support this KPI? | O14: How does this Project support this KPI? | X14: How does this Project support this KPI? | AJ14: Dev roadmap documented | AO14: 45689 | AR14: 45689 | AU14: =IF(AO14=$BK$3,"Missing Target",IF(AR14=$BK$3,IF($AZ$3>AO14,INT($AZ$3-AO14)&" Day(s) Overdue","Incomplete"),IF(AR14>AO14,INT(AR14-AO14)&" Day(s) Late",IF(AR14=AO14,"OK",INT(AO14-AR14)&" Day(s) Ahead")))) -> OK
O15: Usage of the new AI feature will address feedback from clients that our FD is too cubersome and involved too many clicks. | X15: Increase client satisfaction with our product and in turn, reduce attrition. | AJ15: Coding started | AO15: 46112 | AU15: =IF(AO15=$A$1,"Missing Target",IF(AR15=$A$1,IF($AZ$3>AO15,INT($AZ$3-AO15)&" Day(s) Overdue","Incomplete"),IF(AR15>AO15,INT(AR15-AO15)&" Day(s) Late",IF(AR15=AO15,"OK",INT(AO15-AR15)&" Day(s) Ahead")))) -> Incomplete
AG16: Pilot | AJ16: Deployment to beta | AO16: 46234 | AU16: =IF(AO16=$A$1,"Missing Target",IF(AR16=$A$1,IF($AZ$3>AO16,INT($AZ$3-AO16)&" Day(s) Overdue","Incomplete"),IF(AR16>AO16,INT(AR16-AO16)&" Day(s) Late",IF(AR16=AO16,"OK",INT(AO16-AR16)&" Day(s) Ahead")))) -> Incomplete
B17: Contact | C17: James.Peltier@jonasfitness.com | AJ17: Initial metrics/feedback | AO17: 46234 | AU17: =IF(AO17=$A$1,"Missing Target",IF(AR17=$A$1,IF($AZ$3>AO17,INT($AZ$3-AO17)&" Day(s) Overdue","Incomplete"),IF(AR17>AO17,INT(AR17-AO17)&" Day(s) Late",IF(AR17=AO17,"OK",INT(AO17-AR17)&" Day(s) Ahead")))) -> Incomplete
B18: Prod Mgr | C18: Kari Ewersen | F18: How will you measure the KPI? | O18: How will you measure the KPI? | X18: How will you measure the KPI? | AJ18: Feedback affecting code | AO18: 46234 | AU18: =IF(AO18=$A$1,"Missing Target",IF(AR18=$A$1,IF($AZ$3>AO18,INT($AZ$3-AO18)&" Day(s) Overdue","Incomplete"),IF(AR18>AO18,INT(AR18-AO18)&" Day(s) Late",IF(AR18=AO18,"OK",INT(AO18-AR18)&" Day(s) Ahead")))) -> Incomplete
B19: Analyst | C19: Chase Winston | O19: Usage metrics in the front desk of # of users accessing and using the new interface. Goal of 20%. | X19: Attrition metrics comparision, goal of $100K less attrition. | AG19: Live | AJ19: General release available | AO19: 46264 | AU19: =IF(AO19=$A$1,"Missing Target",IF(AR19=$A$1,IF($AZ$3>AO19,INT($AZ$3-AO19)&" Day(s) Overdue","Incomplete"),IF(AR19>AO19,INT(AR19-AO19)&" Day(s) Late",IF(AR19=AO19,"OK",INT(AO19-AR19)&" Day(s) Ahead")))) -> Incomplete
B20: Tech Lead | C20: Jim Peltier | AJ20: Success metrics tracking | AO20: 46264 | AU20: =IF(AO20=$A$1,"Missing Target",IF(AR20=$A$1,IF($AZ$3>AO20,INT($AZ$3-AO20)&" Day(s) Overdue","Incomplete"),IF(AR20>AO20,INT(AR20-AO20)&" Day(s) Late",IF(AR20=AO20,"OK",INT(AO20-AR20)&" Day(s) Ahead")))) -> Incomplete
B21: Exec | C21: Sandy Crutcher | AJ21: Feedback loop continuing | AO21: 46264 | AU21: =IF(AO21=$A$1,"Missing Target",IF(AR21=$A$1,IF($AZ$3>AO21,INT($AZ$3-AO21)&" Day(s) Overdue","Incomplete"),IF(AR21>AO21,INT(AR21-AO21)&" Day(s) Late",IF(AR21=AO21,"OK",INT(AO21-AR21)&" Day(s) Ahead")))) -> Incomplete
B23: WEEKLY KPI TRACKER | F23: 1 | G23: =F23+1 -> 2 | H23: =G23+1 -> 3 | I23: =H23+1 -> 4 | J23: =I23+1 -> 5 | K23: =J23+1 -> 6 | L23: =K23+1 -> 7 | M23: =L23+1 -> 8 | N23: =M23+1 -> 9 | ... BE23: =BD23+1 -> 52
B24: Week Ending | F24: 46234 | G24: =F24+7 -> 46241 | H24: =G24+7 -> 46248 | I24: =H24+7 -> 46255 | J24: =I24+7 -> 46262 | K24: =J24+7 -> 46269 | L24: =K24+7 -> 46276 | M24: =L24+7 -> 46283 | N24: =M24+7 -> 46290 | ... BE24: =BD24+7 -> 46591
B25: =G13&" TARGET" -> .... Select the primary KPI (Jonas Library) TARGET | F25: 0 | G25: =F25 -> 0 | H25: =G25 -> 0 | I25: =H25 -> 0 | J25: =I25 -> 0 | K25: =J25 -> 0 | L25: =K25 -> 0 | M25: =L25 -> 0 | N25: =M25 -> 0 | ... BE25: =BD25 -> 0
B26: Actual | F26: 0 | G26: 0 | H26: 0 | I26: 0 | J26: 0 | K26: 0 | L26: 0 | M26: 0 | N26: 0 | O26: 0 | P26: 0 | Q26: 0 | R26: 0 | S26: 0 | T26: 0 | U26: 0 | V26: 0 | W26: 0 | X26: 0 | Y26: 0 | Z26: 0 | AA26: 0 | AB26: 0 | AC26: 0 | AD26: 0 | AE26: 0 | AF26: 0 | AG26: 0 | AH26: 0 | AI26: 0 | AJ26: 0 | AK26: 0 | AL26: 0 | AM26: 0 | AN26: 0 | AO26: 0 | AP26: 0 | AQ26: 0 | AR26: 0 | AS26: 0 | AT26: 0 | AU26: 0 | AV26: 0 | AW26: 0 | AX26: 0 | AY26: 0 | AZ26: 0 | BA26: 0 | BB26: 0 | BC26: 0 | BD26: 0 | BE26: 0
B27: Delta | F27: =F26-F25 -> 0 | G27: =G26-G25 -> 0 | H27: =H26-H25 -> 0 | I27: =I26-I25 -> 0 | J27: =J26-J25 -> 0 | K27: =K26-K25 -> 0 | L27: =L26-L25 -> 0 | M27: =M26-M25 -> 0 | ... BE27: =BE26-BE25 -> 0
B28: Notes on this KPI (anything to add this week?)
B30: =P13&" TARGET" -> # of Customers using the AI TARGET | F30: 20 | G30: =F30 -> 20 | H30: =G30 -> 20 | I30: =H30 -> 20 | J30: =I30 -> 20 | K30: =J30 -> 20 | L30: =K30 -> 20 | M30: =L30 -> 20 | N30: =M30 -> 20 | ... BE30: =BD30 -> 20
B31: Actual | F31: 0 | G31: 0 | H31: 0 | I31: 0 | J31: 0 | K31: 0 | L31: 0 | M31: 0 | N31: 0 | O31: 0 | P31: 0 | Q31: 0 | R31: 0 | S31: 0 | T31: 0 | U31: 0 | V31: 0 | W31: 0 | X31: 0 | Y31: 0 | Z31: 0 | AA31: 0 | AB31: 0 | AC31: 0 | AD31: 0 | AE31: 0 | AF31: 0 | AG31: 0 | AH31: 0 | AI31: 0 | AJ31: 0 | AK31: 0 | AL31: 0 | AM31: 0 | AN31: 0 | AO31: 0 | AP31: 0 | AQ31: 0 | AR31: 0 | AS31: 0 | AT31: 0 | AU31: 0 | AV31: 0 | AW31: 0 | AX31: 0 | AY31: 0 | AZ31: 0 | BA31: 0 | BB31: 0 | BC31: 0 | BD31: 0 | BE31: 0
B32: Delta | F32: =F31-F30 -> -20 | G32: =G31-G30 -> -20 | H32: =H31-H30 -> -20 | I32: =I31-I30 -> -20 | J32: =J31-J30 -> -20 | K32: =K31-K30 -> -20 | L32: =L31-L30 -> -20 | M32: =M31-M30 -> -20 | ... BE32: =BE31-BE30 -> -20
B33: Notes on this KPI (anything to add this week?)
B35: =Y13&" TARGET" -> Revenue Growth from AI-enhanced products TARGET | F35: 100 | G35: =F35 -> 100 | H35: =G35 -> 100 | I35: =H35 -> 100 | J35: =I35 -> 100 | K35: =J35 -> 100 | L35: =K35 -> 100 | M35: =L35 -> 100 | N35: =M35 -> 100 | ... BE35: =BD35 -> 100
B36: Actual | F36: 0 | G36: 0 | H36: 0 | I36: 0 | J36: 0 | K36: 0 | L36: 0 | M36: 0
B37: Delta | F37: =F36-F35 -> -100 | G37: =G36-G35 -> -100 | H37: =H36-H35 -> -100 | I37: =I36-I35 -> -100 | J37: =J36-J35 -> -100 | K37: =K36-K35 -> -100 | L37: =L36-L35 -> -100 | M37: =M36-M35 -> -100 | ... BE37: =BE36-BE35 -> -100
B38: Notes on this KPI (anything to add this week?)
B41: Revenue Target | F41: =IF($X$12="Revenue Impact",F35,0) -> 100 | G41: =IF($X$12="Revenue Impact",G35,0) -> 100 | H41: =IF($X$12="Revenue Impact",H35,0) -> 100 | I41: =IF($X$12="Revenue Impact",I35,0) -> 100 | J41: =IF($X$12="Revenue Impact",J35,0) -> 100 | K41: =IF($X$12="Revenue Impact",K35,0) -> 100 | L41: =IF($X$12="Revenue Impact",L35,0) -> 100 | M41: =IF($X$12="Revenue Impact",M35,0) -> 100 | ... BE41: =IF($X$12="Revenue Impact",BE35,0) -> 100
B42: Revenue Actual | F42: =IF($X$12="Revenue Impact",F36,0) -> 0 | G42: =IF($X$12="Revenue Impact",G36,0) -> 0 | H42: =IF($X$12="Revenue Impact",H36,0) -> 0 | I42: =IF($X$12="Revenue Impact",I36,0) -> 0 | J42: =IF($X$12="Revenue Impact",J36,0) -> 0 | K42: =IF($X$12="Revenue Impact",K36,0) -> 0 | L42: =IF($X$12="Revenue Impact",L36,0) -> 0 | M42: =IF($X$12="Revenue Impact",M36,0) -> 0 | ... BE42: =IF($X$12="Revenue Impact",BE36,0) -> 0
B44: Cost Target | F44: =IF($X$12="Cost Savings",F35,0) -> 0 | G44: =IF($X$12="Cost Savings",G35,0) -> 0 | H44: =IF($X$12="Cost Savings",H35,0) -> 0 | I44: =IF($X$12="Cost Savings",I35,0) -> 0 | J44: =IF($X$12="Cost Savings",J35,0) -> 0 | K44: =IF($X$12="Cost Savings",K35,0) -> 0 | L44: =IF($X$12="Cost Savings",L35,0) -> 0 | M44: =IF($X$12="Cost Savings",M35,0) -> 0 | ... BE44: =IF($X$12="Cost Savings",BE35,0) -> 0
B45: Cost Actual | F45: =IF($X$12="Cost Savings",F36,0) -> 0 | G45: =IF($X$12="Cost Savings",G36,0) -> 0 | H45: =IF($X$12="Cost Savings",H36,0) -> 0 | I45: =IF($X$12="Cost Savings",I36,0) -> 0 | J45: =IF($X$12="Cost Savings",J36,0) -> 0 | K45: =IF($X$12="Cost Savings",K36,0) -> 0 | L45: =IF($X$12="Cost Savings",L36,0) -> 0 | M45: =IF($X$12="Cost Savings",M36,0) -> 0 | ... BE45: =IF($X$12="Cost Savings",BE36,0) -> 0
B47: Financial Target | F47: =F41+F44 -> 100 | G47: =G41+G44 -> 100 | H47: =H41+H44 -> 100 | I47: =I41+I44 -> 100 | J47: =J41+J44 -> 100 | K47: =K41+K44 -> 100 | L47: =L41+L44 -> 100 | M47: =M41+M44 -> 100 | ... BE47: =BE41+BE44 -> 100
B48: Financial Actual | F48: =F42+F45 -> 0 | G48: =G42+G45 -> 0 | H48: =H42+H45 -> 0 | I48: =I42+I45 -> 0 | J48: =J42+J45 -> 0 | K48: =K42+K45 -> 0 | L48: =L42+L45 -> 0 | M48: =M42+M45 -> 0 | ... BE48: =BE42+BE45 -> 0
E49: To Date
B50: Current Financial Target | E50: =MAX(F50:BE50) -> 0 | F50: =IF($AZ$3>F24,F47,0) -> 0 | G50: =IF($AZ$3>G24,G47,0) -> 0 | H50: =IF($AZ$3>H24,H47,0) -> 0 | I50: =IF($AZ$3>I24,I47,0) -> 0 | J50: =IF($AZ$3>J24,J47,0) -> 0 | K50: =IF($AZ$3>K24,K47,0) -> 0 | L50: =IF($AZ$3>L24,L47,0) -> 0 | M50: =IF($AZ$3>M24,M47,0) -> 0 | ... BE50: =IF($AZ$3>BE24,BE47,0) -> 0
B51: Current Financial Actual | E51: =MAX(F51:BE51) -> 0 | F51: =IF($AZ$3>F25,F48,0) -> 0 | G51: =IF($AZ$3>G25,G48,0) -> 0 | H51: =IF($AZ$3>H25,H48,0) -> 0 | I51: =IF($AZ$3>I25,I48,0) -> 0 | J51: =IF($AZ$3>J25,J48,0) -> 0 | K51: =IF($AZ$3>K25,K48,0) -> 0 | L51: =IF($AZ$3>L25,L48,0) -> 0 | M51: =IF($AZ$3>M25,M48,0) -> 0 | ... BE51: =IF($AZ$3>BE25,BE48,0) -> 0

Sheet P8
B3: PROJECT | F3: Compete AI Project Phase III: Billing Analytic Tool | AG3: Strategic Value | AO3: =F8 -> Customer Feature - New | AV3: =IF(F7="",0,VLOOKUP(F7,Lookups!B4:H8,3)) -> 200 | AZ3: =NOW() -> 45961.476
AG4: Stage Multiplier (today) | AO4: =VLOOKUP(COUNTIF(AR10:AT21,"<="&AZ3),Table3357[],2) -> Dev | AV4: =IF(AO4="Not Def",0,VLOOKUP(AO4,Lookups!L4:M8,2)) -> 0.4 | AZ4: Current Qtr | BC4: =VLOOKUP((YEAR(AZ3)&"-"&MONTH(AZ3)),Lookups!S3:U21,2) -> 2025-Q4
B5: Description (Use Case) | F5: Identify trends in billing data without manual intervention. This tool can be sold to both MBS and Non MBS clients as replacement for current BI reporting solutions. | AG5: Stage Last Quarter | AO5: =VLOOKUP(COUNTIF(AR10:AT21,"<"&VLOOKUP(BC4,Lookups!W3:Y9,2)),Table3357[],2) -> Idea | AQ5: =IF(AV5=1,"No Change","Progression") -> Progression | AV5: =IF(AO4="Not Def",0,IF(AO5=AO4,1,1.2)) -> 1.2
AG6: PROJECT SCORE | AV6: =AV3*AV4*AV5 -> 96
B7: Category | F7: L5. Entirely new product capabilities powered by AI | Y7: Ratio Impacted | AC7: S&M
B8: Strategic Value Level | F8: =IF(F7="","",VLOOKUP(F7,Lookups!B4:H8,2)) -> Customer Feature - New
B9: Examples | F9: =IF(F7="","",VLOOKUP(F7,Lookups!B4:H8,4)) -> Predictive analytics modules, AI-powered workflow automation, intelligent decision support systems | AG9: Stage | AJ9: Tasks | AO9: Target | AR9: Completed | AU9: Days to Target | AY9: Notes
AG10: Idea | AJ10: Project Defined | AO10: 45658 | AR10: 45658 | AU10: =IF(AO10=$BK$3,"Missing Target",IF(AR10=$BK$3,IF($AZ$3>AO10,INT($AZ$3-AO10)&" Day(s) Overdue","Incomplete"),IF(AR10>AO10,INT(AR10-AO10)&" Day(s) Late",IF(AR10=AO10,"OK",INT(AO10-AR10)&" Day(s) Ahead")))) -> OK
B11: PROJECT RESOURCES | F11: KEY PERFORMANCE INDICATORS / MEASURES OF SUCCESS | AJ11: Business Case approved | AO11: 45658 | AR11: 45658 | AU11: =IF(AO11=$BK$3,"Missing Target",IF(AR11=$BK$3,IF($AZ$3>AO11,INT($AZ$3-AO11)&" Day(s) Overdue","Incomplete"),IF(AR11>AO11,INT(AR11-AO11)&" Day(s) Late",IF(AR11=AO11,"OK",INT(AO11-AR11)&" Day(s) Ahead")))) -> OK
B12: AI Tools & Services | F12: =IF(F7="","",VLOOKUP(F7,Lookups!B4:H8,5)) -> Market Differentiation | O12: =IF(F7="","",VLOOKUP(F7,Lookups!B4:H8,6)) -> Competitive Advantage | X12: =IF(F7="","",VLOOKUP(F7,Lookups!B4:H8,7)) -> Revenue Impact | AJ12: Resources Allocated | AO12: 45658 | AR12: 45658 | AU12: =IF(AO12=$BK$3,"Missing Target",IF(AR12=$BK$3,IF($AZ$3>AO12,INT($AZ$3-AO12)&" Day(s) Overdue","Incomplete"),IF(AR12>AO12,INT(AR12-AO12)&" Day(s) Late",IF(AR12=AO12,"OK",INT(AO12-AR12)&" Day(s) Ahead")))) -> OK
B13: Orbit, API | F13: KPI | G13: # of Customers using the AI | O13: KPI | P13: Customer Satisfaction Scores (CSAT, NPS) | X13: KPI | Y13: Revenue Growth from AI-enhanced products | AG13: Develop | AJ13: Technical PoC validated | AO13: 45931 | AR13: 45931 | AU13: =IF(AO13=$BK$3,"Missing Target",IF(AR13=$BK$3,IF($AZ$3>AO13,INT($AZ$3-AO13)&" Day(s) Overdue","Incomplete"),IF(AR13>AO13,INT(AR13-AO13)&" Day(s) Late",IF(AR13=AO13,"OK",INT(AO13-AR13)&" Day(s) Ahead")))) -> OK
F14: How does this Project support this KPI? | O14: How does this Project support this KPI? | X14: How does this Project support this KPI? | AJ14: Dev roadmap documented | AO14: 45931 | AR14: 45931 | AU14: =IF(AO14=$BK$3,"Missing Target",IF(AR14=$BK$3,IF($AZ$3>AO14,INT($AZ$3-AO14)&" Day(s) Overdue","Incomplete"),IF(AR14>AO14,INT(AR14-AO14)&" Day(s) Late",IF(AR14=AO14,"OK",INT(AO14-AR14)&" Day(s) Ahead")))) -> OK
F15: Our billing intelligence tool will analyze patterns in billing, usage, and customer payment behaviors and will allow our clients to develop unique pricing models (e.g., usage-based, outcome-based, or predictive pricing) and make business decisions based on actual member data. | O15: Our tool will allow our customers to forecast future revenue streams, customer churn risk, and payment delays. Our competitors are reactive, predictive intelligence will position JFI as proactive and data-driven. | X15: The tool will be sold as a seperate module and will be available to both our existing base and new customers. | AJ15: Coding started | AO15: 46112 | AU15: =IF(AO15=$A$1,"Missing Target",IF(AR15=$A$1,IF($AZ$3>AO15,INT($AZ$3-AO15)&" Day(s) Overdue","Incomplete"),IF(AR15>AO15,INT(AR15-AO15)&" Day(s) Late",IF(AR15=AO15,"OK",INT(AO15-AR15)&" Day(s) Ahead")))) -> Incomplete
AG16: Pilot | AJ16: Deployment to beta | AO16: 46233 | AU16: =IF(AO16=$A$1,"Missing Target",IF(AR16=$A$1,IF($AZ$3>AO16,INT($AZ$3-AO16)&" Day(s) Overdue","Incomplete"),IF(AR16>AO16,INT(AR16-AO16)&" Day(s) Late",IF(AR16=AO16,"OK",INT(AO16-AR16)&" Day(s) Ahead")))) -> Incomplete
B17: Contact | C17: James.Peltier@jonasfitness.com | AJ17: Initial metrics/feedback | AO17: 46264 | AU17: =IF(AO17=$A$1,"Missing Target",IF(AR17=$A$1,IF($AZ$3>AO17,INT($AZ$3-AO17)&" Day(s) Overdue","Incomplete"),IF(AR17>AO17,INT(AR17-AO17)&" Day(s) Late",IF(AR17=AO17,"OK",INT(AO17-AR17)&" Day(s) Ahead")))) -> Incomplete
B18: Prod Mgr | C18: Kari Ewersen | F18: How will you measure the KPI? | O18: How will you measure the KPI? | X18: How will you measure the KPI? | AJ18: Feedback affecting code | AO18: 46264 | AU18: =IF(AO18=$A$1,"Missing Target",IF(AR18=$A$1,IF($AZ$3>AO18,INT($AZ$3-AO18)&" Day(s) Overdue","Incomplete"),IF(AR18>AO18,INT(AR18-AO18)&" Day(s) Late",IF(AR18=AO18,"OK",INT(AO18-AR18)&" Day(s) Ahead")))) -> Incomplete
B19: Analyst | C19: Chase Winston | F19: Evaluate performance through an audit of customer adoption rates, including sign-ups and active usage following the tool’s release, goal of 20% adoption. | O19: Feedback cycles with our Product Owner and NPS surveys of our customers of 20% increase in Satification. | X19: Quarterly/Monthly sales figures. Increase of $200K in 2027, $300K in 2028, $500K in 2029. | AG19: Live | AJ19: General release available | AO19: 46295 | AU19: =IF(AO19=$A$1,"Missing Target",IF(AR19=$A$1,IF($AZ$3>AO19,INT($AZ$3-AO19)&" Day(s) Overdue","Incomplete"),IF(AR19>AO19,INT(AR19-AO19)&" Day(s) Late",IF(AR19=AO19,"OK",INT(AO19-AR19)&" Day(s) Ahead")))) -> Incomplete
B20: Tech Lead | C20: Jim Peltier | AJ20: Success metrics tracking | AO20: 46296 | AU20: =IF(AO20=$A$1,"Missing Target",IF(AR20=$A$1,IF($AZ$3>AO20,INT($AZ$3-AO20)&" Day(s) Overdue","Incomplete"),IF(AR20>AO20,INT(AR20-AO20)&" Day(s) Late",IF(AR20=AO20,"OK",INT(AO20-AR20)&" Day(s) Ahead")))) -> Incomplete
B21: Exec | C21: Sandy Crutcher | AJ21: Feedback loop continuing | AO21: 46297 | AU21: =IF(AO21=$A$1,"Missing Target",IF(AR21=$A$1,IF($AZ$3>AO21,INT($AZ$3-AO21)&" Day(s) Overdue","Incomplete"),IF(AR21>AO21,INT(AR21-AO21)&" Day(s) Late",IF(AR21=AO21,"OK",INT(AO21-AR21)&" Day(s) Ahead")))) -> Incomplete
B23: WEEKLY KPI TRACKER | F23: 1 | G23: =F23+1 -> 2 | H23: =G23+1 -> 3 | I23: =H23+1 -> 4 | J23: =I23+1 -> 5 | K23: =J23+1 -> 6 | L23: =K23+1 -> 7 | M23: =L23+1 -> 8 | N23: =M23+1 -> 9 | ... BE23: =BD23+1 -> 52
B24: Week Ending | F24: 46233 | G24: =F24+7 -> 46240 | H24: =G24+7 -> 46247 | I24: =H24+7 -> 46254 | J24: =I24+7 -> 46261 | K24: =J24+7 -> 46268 | L24: =K24+7 -> 46275 | M24: =L24+7 -> 46282 | N24: =M24+7 -> 46289 | ... BE24: =BD24+7 -> 46590
B25: =G13&" TARGET" -> # of Customers using the AI TARGET | F25: 20 | G25: =F25 -> 20 | H25: =G25 -> 20 | I25: =H25 -> 20 | J25: =I25 -> 20 | K25: =J25 -> 20 | L25: =K25 -> 20 | M25: =L25 -> 20 | N25: =M25 -> 20 | ... BE25: =BD25 -> 20
B26: Actual | F26: 0 | G26: 0 | H26: 0 | I26: 0 | J26: 0 | K26: 0 | L26: 0 | M26: 0 | N26: 0 | O26: 0 | P26: 0 | Q26: 0 | R26: 0 | S26: 0 | T26: 0 | U26: 0 | V26: 0 | W26: 0 | X26: 0 | Y26: 0 | Z26: 0 | AA26: 0 | AB26: 0 | AC26: 0 | AD26: 0 | AE26: 0 | AF26: 0 | AG26: 0 | AH26: 0 | AI26: 0 | AJ26: 0 | AK26: 0 | AL26: 0 | AM26: 0 | AN26: 0 | AO26: 0 | AP26: 0 | AQ26: 0 | AR26: 0 | AS26: 0 | AT26: 0 | AU26: 0 | AV26: 0 | AW26: 0 | AX26: 0 | AY26: 0 | AZ26: 0 | BA26: 0 | BB26: 0 | BC26: 0 | BD26: 0 | BE26: 0
B27: Delta | F27: =F26-F25 -> -20 | G27: =G26-G25 -> -20 | H27: =H26-H25 -> -20 | I27: =I26-I25 -> -20 | J27: =J26-J25 -> -20 | K27: =K26-K25 -> -20 | L27: =L26-L25 -> -20 | M27: =M26-M25 -> -20 | ... BE27: =BE26-BE25 -> -20
B28: Notes on this KPI (anything to add this week?)
B30: =P13&" TARGET" -> Customer Satisfaction Scores (CSAT, NPS) TARGET | F30: 20 | G30: =F30 -> 20 | H30: =G30 -> 20 | I30: =H30 -> 20 | J30: =I30 -> 20 | K30: =J30 -> 20 | L30: =K30 -> 20 | M30: =L30 -> 20 | N30: =M30 -> 20 | ... BE30: =BD30 -> 20
B31: Actual | F31: 0 | G31: 0 | H31: 0 | I31: 0 | J31: 0 | K31: 0 | L31: 0 | M31: 0 | N31: 0 | O31: 0 | P31: 0 | Q31: 0 | R31: 0 | S31: 0 | T31: 0 | U31: 0 | V31: 0 | W31: 0 | X31: 0 | Y31: 0 | Z31: 0 | AA31: 0 | AB31: 0 | AC31: 0 | AD31: 0 | AE31: 0 | AF31: 0 | AG31: 0 | AH31: 0 | AI31: 0 | AJ31: 0 | AK31: 0 | AL31: 0 | AM31: 0 | AN31: 0 | AO31: 0 | AP31: 0 | AQ31: 0 | AR31: 0 | AS31: 0 | AT31: 0 | AU31: 0 | AV31: 0 | AW31: 0 | AX31: 0 | AY31: 0 | AZ31: 0 | BA31: 0 | BB31: 0 | BC31: 0 | BD31: 0 | BE31: 0
B32: Delta | F32: =F31-F30 -> -20 | G32: =G31-G30 -> -20 | H32: =H31-H30 -> -20 | I32: =I31-I30 -> -20 | J32: =J31-J30 -> -20 | K32: =K31-K30 -> -20 | L32: =L31-L30 -> -20 | M32: =M31-M30 -> -20 | ... BE32: =BE31-BE30 -> -20
B33: Notes on this KPI (anything to add this week?)
B35: =Y13&" TARGET" -> Revenue Growth from AI-enhanced products TARGET | F35: 0 | G35: =F35 -> 0 | H35: =G35 -> 0 | I35: =H35 -> 0 | J35: =I35 -> 0 | K35: =J35 -> 0 | L35: =K35 -> 0 | M35: =L35 -> 0 | N35: =M35 -> 0 | ... AB35: =AA35 -> 0 | AC35: 200 | AD35: =AC35 -> 200 | AE35: =AD35 -> 200 | AF35: =AE35 -> 200 | AG35: =AF35 -> 200 | AH35: =AG35 -> 200 | AI35: =AH35 -> 200 | AJ35: =AI35 -> 200 | AK35: =AJ35 -> 200 | ... BE35: =BD35 -> 200
B36: Actual | F36: 0 | G36: 0 | H36: 0 | I36: 0 | J36: 0 | K36: 0 | L36: 0 | M36: 0 | N36: 0 | O36: 0 | P36: 0 | Q36: 0 | R36: 0 | S36: 0 | T36: 0 | U36: 0 | V36: 0 | W36: 0 | X36: 0 | Y36: 0 | Z36: 0 | AA36: 0 | AB36: 0 | AC36: 0 | AD36: 0 | AE36: 0 | AF36: 0 | AG36: 0 | AH36: 0 | AI36: 0 | AJ36: 0 | AK36: 0 | AL36: 0 | AM36: 0 | AN36: 0 | AO36: 0 | AP36: 0 | AQ36: 0 | AR36: 0 | AS36: 0 | AT36: 0 | AU36: 0 | AV36: 0 | AW36: 0 | AX36: 0 | AY36: 0 | AZ36: 0 | BA36: 0 | BB36: 0 | BC36: 0 | BD36: 0 | BE36: 0
B37: Delta | F37: =F36-F35 -> 0 | G37: =G36-G35 -> 0 | H37: =H36-H35 -> 0 | I37: =I36-I35 -> 0 | J37: =J36-J35 -> 0 | K37: =K36-K35 -> 0 | L37: =L36-L35 -> 0 | M37: =M36-M35 -> 0 | ... BE37: =BE36-BE35 -> -200
B38: Notes on this KPI (anything to add this week?)
B41: Revenue Target | F41: =IF($X$12="Revenue Impact",F35,0) -> 0 | G41: =IF($X$12="Revenue Impact",G35,0) -> 0 | H41: =IF($X$12="Revenue Impact",H35,0) -> 0 | I41: =IF($X$12="Revenue Impact",I35,0) -> 0 | J41: =IF($X$12="Revenue Impact",J35,0) -> 0 | K41: =IF($X$12="Revenue Impact",K35,0) -> 0 | L41: =IF($X$12="Revenue Impact",L35,0) -> 0 | M41: =IF($X$12="Revenue Impact",M35,0) -> 0 | ... BE41: =IF($X$12="Revenue Impact",BE35,0) -> 200
B42: Revenue Actual | F42: =IF($X$12="Revenue Impact",F36,0) -> 0 | G42: =IF($X$12="Revenue Impact",G36,0) -> 0 | H42: =IF($X$12="Revenue Impact",H36,0) -> 0 | I42: =IF($X$12="Revenue Impact",I36,0) -> 0 | J42: =IF($X$12="Revenue Impact",J36,0) -> 0 | K42: =IF($X$12="Revenue Impact",K36,0) -> 0 | L42: =IF($X$12="Revenue Impact",L36,0) -> 0 | M42: =IF($X$12="Revenue Impact",M36,0) -> 0 | ... BE42: =IF($X$12="Revenue Impact",BE36,0) -> 0
B44: Cost Target | F44: =IF($X$12="Cost Savings",F35,0) -> 0 | G44: =IF($X$12="Cost Savings",G35,0) -> 0 | H44: =IF($X$12="Cost Savings",H35,0) -> 0 | I44: =IF($X$12="Cost Savings",I35,0) -> 0 | J44: =IF($X$12="Cost Savings",J35,0) -> 0 | K44: =IF($X$12="Cost Savings",K35,0) -> 0 | L44: =IF($X$12="Cost Savings",L35,0) -> 0 | M44: =IF($X$12="Cost Savings",M35,0) -> 0 | ... BE44: =IF($X$12="Cost Savings",BE35,0) -> 0
B45: Cost Actual | F45: =IF($X$12="Cost Savings",F36,0) -> 0 | G45: =IF($X$12="Cost Savings",G36,0) -> 0 | H45: =IF($X$12="Cost Savings",H36,0) -> 0 | I45: =IF($X$12="Cost Savings",I36,0) -> 0 | J45: =IF($X$12="Cost Savings",J36,0) -> 0 | K45: =IF($X$12="Cost Savings",K36,0) -> 0 | L45: =IF($X$12="Cost Savings",L36,0) -> 0 | M45: =IF($X$12="Cost Savings",M36,0) -> 0 | ... BE45: =IF($X$12="Cost Savings",BE36,0) -> 0
B47: Financial Target | F47: =F41+F44 -> 0 | G47: =G41+G44 -> 0 | H47: =H41+H44 -> 0 | I47: =I41+I44 -> 0 | J47: =J41+J44 -> 0 | K47: =K41+K44 -> 0 | L47: =L41+L44 -> 0 | M47: =M41+M44 -> 0 | ... BE47: =BE41+BE44 -> 200
B48: Financial Actual | F48: =F42+F45 -> 0 | G48: =G42+G45 -> 0 | H48: =H42+H45 -> 0 | I48: =I42+I45 -> 0 | J48: =J42+J45 -> 0 | K48: =K42+K45 -> 0 | L48: =L42+L45 -> 0 | M48: =M42+M45 -> 0 | ... BE48: =BE42+BE45 -> 0
E49: To Date
B50: Current Financial Target | E50: =MAX(F50:BE50) -> 0 | F50: =IF($AZ$3>F24,F47,0) -> 0 | G50: =IF($AZ$3>G24,G47,0) -> 0 | H50: =IF($AZ$3>H24,H47,0) -> 0 | I50: =IF($AZ$3>I24,I47,0) -> 0 | J50: =IF($AZ$3>J24,J47,0) -> 0 | K50: =IF($AZ$3>K24,K47,0) -> 0 | L50: =IF($AZ$3>L24,L47,0) -> 0 | M50: =IF($AZ$3>M24,M47,0) -> 0 | ... BE50: =IF($AZ$3>BE24,BE47,0) -> 0
B51: Current Financial Actual | E51: =MAX(F51:BE51) -> 0 | F51: =IF($AZ$3>F25,F48,0) -> 0 | G51: =IF($AZ$3>G25,G48,0) -> 0 | H51: =IF($AZ$3>H25,H48,0) -> 0 | I51: =IF($AZ$3>I25,I48,0) -> 0 | J51: =IF($AZ$3>J25,J48,0) -> 0 | K51: =IF($AZ$3>K25,K48,0) -> 0 | L51: =IF($AZ$3>L25,L48,0) -> 0 | M51: =IF($AZ$3>M25,M48,0) -> 0 | ... BE51: =IF($AZ$3>BE25,BE48,0) -> 0

Sheet P9
B3: PROJECT | F3: AI Client/Marketing Communication Tool | AG3: Strategic Value | AO3: =F8 -> Simple Tool | AV3: =IF(F7="",0,VLOOKUP(F7,Lookups!B4:H8,3)) -> 10 | AZ3: =NOW() -> 45961.476
AG4: Stage Multiplier (today) | AO4: =VLOOKUP(COUNTIF(AR10:AT21,"<="&AZ3),Table3357[],2) -> Idea | AV4: =IF(AO4="Not Def",0,VLOOKUP(AO4,Lookups!L4:M8,2)) -> 0.1 | AZ4: Current Qtr | BC4: =VLOOKUP((YEAR(AZ3)&"-"&MONTH(AZ3)),Lookups!S3:U21,2) -> 2025-Q4
B5: Description (Use Case) | F5: A tool that will help us automate the process of posting, texting, emailing of information for marketing and or customer update information. | AG5: Stage Last Quarter | AO5: =VLOOKUP(COUNTIF(AR10:AT21,"<"&VLOOKUP(BC4,Lookups!W3:Y9,2)),Table3357[],2) -> Not Def | AQ5: =IF(AV5=1,"No Change","Progression") -> Progression | AV5: =IF(AO4="Not Def",0,IF(AO5=AO4,1,1.2)) -> 1.2
AG6: PROJECT SCORE | AV6: =AV3*AV4*AV5 -> 1.2
B7: Category | F7: L1. Using external AI tools for basic internal productivity | Y7: Ratio Impacted | AC7: S&M
B8: Strategic Value Level | F8: =IF(F7="","",VLOOKUP(F7,Lookups!B4:H8,2)) -> Simple Tool
B9: Examples | F9: =IF(F7="","",VLOOKUP(F7,Lookups!B4:H8,4)) -> ChatGPT for content, Co-Pilot for drafting emails, AI meeting summaries | AG9: Stage | AJ9: Tasks | AO9: Target | AR9: Completed | AU9: Days to Target | AY9: Notes
AG10: Idea | AJ10: Project Defined | AO10: 45931 | AR10: 45931 | AU10: =IF(AO10=$BK$3,"Missing Target",IF(AR10=$BK$3,IF($AZ$3>AO10,INT($AZ$3-AO10)&" Day(s) Overdue","Incomplete"),IF(AR10>AO10,INT(AR10-AO10)&" Day(s) Late",IF(AR10=AO10,"OK",INT(AO10-AR10)&" Day(s) Ahead")))) -> OK
B11: PROJECT RESOURCES | F11: KEY PERFORMANCE INDICATORS / MEASURES OF SUCCESS | AJ11: Business Case approved | AO11: 45931 | AR11: 45931 | AU11: =IF(AO11=$BK$3,"Missing Target",IF(AR11=$BK$3,IF($AZ$3>AO11,INT($AZ$3-AO11)&" Day(s) Overdue","Incomplete"),IF(AR11>AO11,INT(AR11-AO11)&" Day(s) Late",IF(AR11=AO11,"OK",INT(AO11-AR11)&" Day(s) Ahead")))) -> OK
B12: AI Tools & Services | F12: =IF(F7="","",VLOOKUP(F7,Lookups!B4:H8,5)) -> Adoption Rate | O12: =IF(F7="","",VLOOKUP(F7,Lookups!B4:H8,6)) -> Productivity Gains | X12: =IF(F7="","",VLOOKUP(F7,Lookups!B4:H8,7)) -> Cost Savings | AJ12: Resources Allocated | AO12: 45962 | AR12: 45962 | AU12: =IF(AO12=$BK$3,"Missing Target",IF(AR12=$BK$3,IF($AZ$3>AO12,INT($AZ$3-AO12)&" Day(s) Overdue","Incomplete"),IF(AR12>AO12,INT(AR12-AO12)&" Day(s) Late",IF(AR12=AO12,"OK",INT(AO12-AR12)&" Day(s) Ahead")))) -> OK
B13: TBD | F13: KPI | G13: Employee AI Tool Adoption Rate | O13: KPI | P13: Employee Productivity Gains | X13: KPI | Y13: Conversion Rates from AI-powered features | AG13: Develop | AJ13: Technical PoC validated | AO13: 45963 | AR13: 45963 | AU13: =IF(AO13=$BK$3,"Missing Target",IF(AR13=$BK$3,IF($AZ$3>AO13,INT($AZ$3-AO13)&" Day(s) Overdue","Incomplete"),IF(AR13>AO13,INT(AR13-AO13)&" Day(s) Late",IF(AR13=AO13,"OK",INT(AO13-AR13)&" Day(s) Ahead")))) -> OK
F14: How does this Project support this KPI? | O14: How does this Project support this KPI? | X14: How does this Project support this KPI? | AJ14: Dev roadmap documented | AO14: 45964 | AR14: 45964 | AU14: =IF(AO14=$BK$3,"Missing Target",IF(AR14=$BK$3,IF($AZ$3>AO14,INT($AZ$3-AO14)&" Day(s) Overdue","Incomplete"),IF(AR14>AO14,INT(AR14-AO14)&" Day(s) Late",IF(AR14=AO14,"OK",INT(AO14-AR14)&" Day(s) Ahead")))) -> OK
F15: 1 marketing resource to have access and use the tool. | O15: Automation Reduces Manual Labor, employee currently spends significant time: Writing and scheduling social posts, formatting and sending emails and updating or maintaining blog content. By automating these repetitive tasks, the AI tool allows employees to focus on strategic, creative, and revenue-generating activities, rather than administrative or time-consuming posting duties. This directly translates into measurable productivity gains—more output with fewer hours. | X15: If successful, the amount of leads and or impressions from our posts, emails and texts will increase. | AJ15: Coding started | AO15: 45965 | AR15: 45965 | AU15: =IF(AO15=$A$1,"Missing Target",IF(AR15=$A$1,IF($AZ$3>AO15,INT($AZ$3-AO15)&" Day(s) Overdue","Incomplete"),IF(AR15>AO15,INT(AR15-AO15)&" Day(s) Late",IF(AR15=AO15,"OK",INT(AO15-AR15)&" Day(s) Ahead")))) -> OK
AG16: Pilot | AJ16: Deployment to beta | AO16: 46022 | AU16: =IF(AO16=$A$1,"Missing Target",IF(AR16=$A$1,IF($AZ$3>AO16,INT($AZ$3-AO16)&" Day(s) Overdue","Incomplete"),IF(AR16>AO16,INT(AR16-AO16)&" Day(s) Late",IF(AR16=AO16,"OK",INT(AO16-AR16)&" Day(s) Ahead")))) -> Incomplete
B17: Contact | C17: Kim.Forster@jonasfitness.com | AJ17: Initial metrics/feedback | AO17: 46037 | AU17: =IF(AO17=$A$1,"Missing Target",IF(AR17=$A$1,IF($AZ$3>AO17,INT($AZ$3-AO17)&" Day(s) Overdue","Incomplete"),IF(AR17>AO17,INT(AR17-AO17)&" Day(s) Late",IF(AR17=AO17,"OK",INT(AO17-AR17)&" Day(s) Ahead")))) -> Incomplete
B18: Prod Mgr | C18: Kim Forster | F18: How will you measure the KPI? | O18: How will you measure the KPI? | X18: How will you measure the KPI? | AJ18: Feedback affecting code | AO18: 46037 | AU18: =IF(AO18=$A$1,"Missing Target",IF(AR18=$A$1,IF($AZ$3>AO18,INT($AZ$3-AO18)&" Day(s) Overdue","Incomplete"),IF(AR18>AO18,INT(AR18-AO18)&" Day(s) Late",IF(AR18=AO18,"OK",INT(AO18-AR18)&" Day(s) Ahead")))) -> Incomplete
B19: Analyst | C19: Chase Winston | F19: Ensure resource has the tool, has been trained and then tracking progress on usage. | O19: Conduct time audits to log time spent on marketing activities before and after the adoption of the tool. | X19: Meaure number of impressions, clicks and or responses to our campaigns. | AG19: Live | AJ19: General release available | AO19: 46054 | AU19: =IF(AO19=$A$1,"Missing Target",IF(AR19=$A$1,IF($AZ$3>AO19,INT($AZ$3-AO19)&" Day(s) Overdue","Incomplete"),IF(AR19>AO19,INT(AR19-AO19)&" Day(s) Late",IF(AR19=AO19,"OK",INT(AO19-AR19)&" Day(s) Ahead")))) -> Incomplete
B20: Tech Lead | C20: Jim Peltier | AJ20: Success metrics tracking | AO20: 46055 | AU20: =IF(AO20=$A$1,"Missing Target",IF(AR20=$A$1,IF($AZ$3>AO20,INT($AZ$3-AO20)&" Day(s) Overdue","Incomplete"),IF(AR20>AO20,INT(AR20-AO20)&" Day(s) Late",IF(AR20=AO20,"OK",INT(AO20-AR20)&" Day(s) Ahead")))) -> Incomplete
B21: Exec | C21: Sandy Crutcher | AJ21: Feedback loop continuing | AO21: 46056 | AU21: =IF(AO21=$A$1,"Missing Target",IF(AR21=$A$1,IF($AZ$3>AO21,INT($AZ$3-AO21)&" Day(s) Overdue","Incomplete"),IF(AR21>AO21,INT(AR21-AO21)&" Day(s) Late",IF(AR21=AO21,"OK",INT(AO21-AR21)&" Day(s) Ahead")))) -> Incomplete
B23: WEEKLY KPI TRACKER | F23: 1 | G23: =F23+1 -> 2 | H23: =G23+1 -> 3 | I23: =H23+1 -> 4 | J23: =I23+1 -> 5 | K23: =J23+1 -> 6 | L23: =K23+1 -> 7 | M23: =L23+1 -> 8 | N23: =M23+1 -> 9 | ... BE23: =BD23+1 -> 52
B24: Week Ending | F24: 46022 | G24: =F24+7 -> 46029 | H24: =G24+7 -> 46036 | I24: =H24+7 -> 46043 | J24: =I24+7 -> 46050 | K24: =J24+7 -> 46057 | L24: =K24+7 -> 46064 | M24: =L24+7 -> 46071 | N24: =M24+7 -> 46078 | ... BE24: =BD24+7 -> 46379
B25: =G13&" TARGET" -> Employee AI Tool Adoption Rate TARGET | F25: 0 | G25: =F25 -> 0 | H25: =G25 -> 0 | I25: =H25 -> 0 | J25: =I25 -> 0 | K25: =J25 -> 0 | L25: =K25 -> 0 | M25: =L25 -> 0 | N25: =M25 -> 0 | ... BE25: =BD25 -> 0
B26: Actual | F26: 0 | G26: 0 | H26: 0 | I26: 0 | J26: 0 | K26: 0 | L26: 0 | M26: 0 | N26: 0 | O26: 0 | P26: 0 | Q26: 0 | R26: 0 | S26: 0 | T26: 0 | U26: 0 | V26: 0 | W26: 0 | X26: 0 | Y26: 0 | Z26: 0 | AA26: 0 | AB26: 0 | AC26: 0 | AD26: 0 | AE26: 0 | AF26: 0 | AG26: 0 | AH26: 0 | AI26: 0 | AJ26: 0 | AK26: 0 | AL26: 0 | AM26: 0 | AN26: 0 | AO26: 0 | AP26: 0 | AQ26: 0 | AR26: 0 | AS26: 0 | AT26: 0 | AU26: 0 | AV26: 0 | AW26: 0 | AX26: 0 | AY26: 0 | AZ26: 0 | BA26: 0 | BB26: 0 | BC26: 0 | BD26: 0 | BE26: 0
B27: Delta | F27: =F26-F25 -> 0 | G27: =G26-G25 -> 0 | H27: =H26-H25 -> 0 | I27: =I26-I25 -> 0 | J27: =J26-J25 -> 0 | K27: =K26-K25 -> 0 | L27: =L26-L25 -> 0 | M27: =M26-M25 -> 0 | ... BE27: =BE26-BE25 -> 0
B28: Notes on this KPI (anything to add this week?)
B30: =P13&" TARGET" -> Employee Productivity Gains TARGET | F30: 0 | G30: =F30 -> 0 | H30: =G30 -> 0 | I30: =H30 -> 0 | J30: =I30 -> 0 | K30: =J30 -> 0 | L30: =K30 -> 0 | M30: =L30 -> 0 | N30: =M30 -> 0 | ... BE30: =BD30 -> 0
B31: Actual | F31: 0 | G31: 0 | H31: 0 | I31: 0 | J31: 0 | K31: 0 | L31: 0 | M31: 0 | N31: 0 | O31: 0 | P31: 0 | Q31: 0 | R31: 0 | S31: 0 | T31: 0 | U31: 0 | V31: 0 | W31: 0 | X31: 0 | Y31: 0 | Z31: 0 | AA31: 0 | AB31: 0 | AC31: 0 | AD31: 0 | AE31: 0 | AF31: 0 | AG31: 0 | AH31: 0 | AI31: 0 | AJ31: 0 | AK31: 0 | AL31: 0 | AM31: 0 | AN31: 0 | AO31: 0 | AP31: 0 | AQ31: 0 | AR31: 0 | AS31: 0 | AT31: 0 | AU31: 0 | AV31: 0 | AW31: 0 | AX31: 0 | AY31: 0 | AZ31: 0 | BA31: 0 | BB31: 0 | BC31: 0 | BD31: 0 | BE31: 0
B32: Delta | F32: =F31-F30 -> 0 | G32: =G31-G30 -> 0 | H32: =H31-H30 -> 0 | I32: =I31-I30 -> 0 | J32: =J31-J30 -> 0 | K32: =K31-K30 -> 0 | L32: =L31-L30 -> 0 | M32: =M31-M30 -> 0 | ... BE32: =BE31-BE30 -> 0
B33: Notes on this KPI (anything to add this week?)
B35: =Y13&" TARGET" -> Conversion Rates from AI-powered features TARGET | F35: 0 | G35: =F35 -> 0 | H35: =G35 -> 0 | I35: =H35 -> 0 | J35: =I35 -> 0 | K35: =J35 -> 0 | L35: =K35 -> 0 | M35: =L35 -> 0 | N35: =M35 -> 0 | ... BE35: =BD35 -> 0
B36: Actual | F36: 0 | G36: 0 | H36: 0 | I36: 0 | J36: 0 | K36: 0 | L36: 0 | M36: 0 | N36: 0 | O36: 0 | P36: 0 | Q36: 0 | R36: 0 | S36: 0 | T36: 0 | U36: 0 | V36: 0 | W36: 0 | X36: 0 | Y36: 0 | Z36: 0 | AA36: 0 | AB36: 0 | AC36: 0 | AD36: 0 | AE36: 0 | AF36: 0 | AG36: 0 | AH36: 0 | AI36: 0 | AJ36: 0 | AK36: 0 | AL36: 0 | AM36: 0 | AN36: 0 | AO36: 0 | AP36: 0 | AQ36: 0 | AR36: 0 | AS36: 0 | AT36: 0 | AU36: 0 | AV36: 0 | AW36: 0 | AX36: 0 | AY36: 0 | AZ36: 0 | BA36: 0 | BB36: 0 | BC36: 0 | BD36: 0 | BE36: 0
B37: Delta | F37: =F36-F35 -> 0 | G37: =G36-G35 -> 0 | H37: =H36-H35 -> 0 | I37: =I36-I35 -> 0 | J37: =J36-J35 -> 0 | K37: =K36-K35 -> 0 | L37: =L36-L35 -> 0 | M37: =M36-M35 -> 0 | ... BE37: =BE36-BE35 -> 0
B38: Notes on this KPI (anything to add this week?)
B41: Revenue Target | F41: =IF($X$12="Revenue Impact",F35,0) -> 0 | G41: =IF($X$12="Revenue Impact",G35,0) -> 0 | H41: =IF($X$12="Revenue Impact",H35,0) -> 0 | I41: =IF($X$12="Revenue Impact",I35,0) -> 0 | J41: =IF($X$12="Revenue Impact",J35,0) -> 0 | K41: =IF($X$12="Revenue Impact",K35,0) -> 0 | L41: =IF($X$12="Revenue Impact",L35,0) -> 0 | M41: =IF($X$12="Revenue Impact",M35,0) -> 0 | ... BE41: =IF($X$12="Revenue Impact",BE35,0) -> 0
B42: Revenue Actual | F42: =IF($X$12="Revenue Impact",F36,0) -> 0 | G42: =IF($X$12="Revenue Impact",G36,0) -> 0 | H42: =IF($X$12="Revenue Impact",H36,0) -> 0 | I42: =IF($X$12="Revenue Impact",I36,0) -> 0 | J42: =IF($X$12="Revenue Impact",J36,0) -> 0 | K42: =IF($X$12="Revenue Impact",K36,0) -> 0 | L42: =IF($X$12="Revenue Impact",L36,0) -> 0 | M42: =IF($X$12="Revenue Impact",M36,0) -> 0 | ... BE42: =IF($X$12="Revenue Impact",BE36,0) -> 0
B44: Cost Target | F44: =IF($X$12="Cost Savings",F35,0) -> 0 | G44: =IF($X$12="Cost Savings",G35,0) -> 0 | H44: =IF($X$12="Cost Savings",H35,0) -> 0 | I44: =IF($X$12="Cost Savings",I35,0) -> 0 | J44: =IF($X$12="Cost Savings",J35,0) -> 0 | K44: =IF($X$12="Cost Savings",K35,0) -> 0 | L44: =IF($X$12="Cost Savings",L35,0) -> 0 | M44: =IF($X$12="Cost Savings",M35,0) -> 0 | ... BE44: =IF($X$12="Cost Savings",BE35,0) -> 0
B45: Cost Actual | F45: =IF($X$12="Cost Savings",F36,0) -> 0 | G45: =IF($X$12="Cost Savings",G36,0) -> 0 | H45: =IF($X$12="Cost Savings",H36,0) -> 0 | I45: =IF($X$12="Cost Savings",I36,0) -> 0 | J45: =IF($X$12="Cost Savings",J36,0) -> 0 | K45: =IF($X$12="Cost Savings",K36,0) -> 0 | L45: =IF($X$12="Cost Savings",L36,0) -> 0 | M45: =IF($X$12="Cost Savings",M36,0) -> 0 | ... BE45: =IF($X$12="Cost Savings",BE36,0) -> 0
B47: Financial Target | F47: =F41+F44 -> 0 | G47: =G41+G44 -> 0 | H47: =H41+H44 -> 0 | I47: =I41+I44 -> 0 | J47: =J41+J44 -> 0 | K47: =K41+K44 -> 0 | L47: =L41+L44 -> 0 | M47: =M41+M44 -> 0 | ... BE47: =BE41+BE44 -> 0
B48: Financial Actual | F48: =F42+F45 -> 0 | G48: =G42+G45 -> 0 | H48: =H42+H45 -> 0 | I48: =I42+I45 -> 0 | J48: =J42+J45 -> 0 | K48: =K42+K45 -> 0 | L48: =L42+L45 -> 0 | M48: =M42+M45 -> 0 | ... BE48: =BE42+BE45 -> 0
E49: To Date
B50: Current Financial Target | E50: =MAX(F50:BE50) -> 0 | F50: =IF($AZ$3>F24,F47,0) -> 0 | G50: =IF($AZ$3>G24,G47,0) -> 0 | H50: =IF($AZ$3>H24,H47,0) -> 0 | I50: =IF($AZ$3>I24,I47,0) -> 0 | J50: =IF($AZ$3>J24,J47,0) -> 0 | K50: =IF($AZ$3>K24,K47,0) -> 0 | L50: =IF($AZ$3>L24,L47,0) -> 0 | M50: =IF($AZ$3>M24,M47,0) -> 0 | ... BE50: =IF($AZ$3>BE24,BE47,0) -> 0
B51: Current Financial Actual | E51: =MAX(F51:BE51) -> 0 | F51: =IF($AZ$3>F25,F48,0) -> 0 | G51: =IF($AZ$3>G25,G48,0) -> 0 | H51: =IF($AZ$3>H25,H48,0) -> 0 | I51: =IF($AZ$3>I25,I48,0) -> 0 | J51: =IF($AZ$3>J25,J48,0) -> 0 | K51: =IF($AZ$3>K25,K48,0) -> 0 | L51: =IF($AZ$3>L25,L48,0) -> 0 | M51: =IF($AZ$3>M25,M48,0) -> 0 | ... BE51: =IF($AZ$3>BE25,BE48,0) -> 0

Sheet P10
B3: PROJECT | F3: AI Tool for Lead Generation and Qualification | AG3: Strategic Value | AO3: =F8 -> Simple Tool | AV3: =IF(F7="",0,VLOOKUP(F7,Lookups!B4:H8,3)) -> 10 | AZ3: =NOW() -> 45961.476
AG4: Stage Multiplier (today) | AO4: =VLOOKUP(COUNTIF(AR10:AT21,"<="&AZ3),Table3357[],2) -> Idea | AV4: =IF(AO4="Not Def",0,VLOOKUP(AO4,Lookups!L4:M8,2)) -> 0.1 | AZ4: Current Qtr | BC4: =VLOOKUP((YEAR(AZ3)&"-"&MONTH(AZ3)),Lookups!S3:U21,2) -> 2025-Q4
B5: Description (Use Case) | F5: Need a tool that can create leads and qualify them, routing them to our sales team. | AG5: Stage Last Quarter | AO5: =VLOOKUP(COUNTIF(AR10:AT21,"<"&VLOOKUP(BC4,Lookups!W3:Y9,2)),Table3357[],2) -> Not Def | AQ5: =IF(AV5=1,"No Change","Progression") -> Progression | AV5: =IF(AO4="Not Def",0,IF(AO5=AO4,1,1.2)) -> 1.2
AG6: PROJECT SCORE | AV6: =AV3*AV4*AV5 -> 1.2
B7: Category | F7: L1. Using external AI tools for basic internal productivity | Y7: Ratio Impacted | AC7: S&M
B8: Strategic Value Level | F8: =IF(F7="","",VLOOKUP(F7,Lookups!B4:H8,2)) -> Simple Tool
B9: Examples | F9: =IF(F7="","",VLOOKUP(F7,Lookups!B4:H8,4)) -> ChatGPT for content, Co-Pilot for drafting emails, AI meeting summaries | AG9: Stage | AJ9: Tasks | AO9: Target | AR9: Completed | AU9: Days to Target | AY9: Notes
AG10: Idea | AJ10: Project Defined | AO10: 45931 | AR10: 45931 | AU10: =IF(AO10=$BK$3,"Missing Target",IF(AR10=$BK$3,IF($AZ$3>AO10,INT($AZ$3-AO10)&" Day(s) Overdue","Incomplete"),IF(AR10>AO10,INT(AR10-AO10)&" Day(s) Late",IF(AR10=AO10,"OK",INT(AO10-AR10)&" Day(s) Ahead")))) -> OK
B11: PROJECT RESOURCES | F11: KEY PERFORMANCE INDICATORS / MEASURES OF SUCCESS | AJ11: Business Case approved | AO11: 45931 | AR11: 45931 | AU11: =IF(AO11=$BK$3,"Missing Target",IF(AR11=$BK$3,IF($AZ$3>AO11,INT($AZ$3-AO11)&" Day(s) Overdue","Incomplete"),IF(AR11>AO11,INT(AR11-AO11)&" Day(s) Late",IF(AR11=AO11,"OK",INT(AO11-AR11)&" Day(s) Ahead")))) -> OK
B12: AI Tools & Services | F12: =IF(F7="","",VLOOKUP(F7,Lookups!B4:H8,5)) -> Adoption Rate | O12: =IF(F7="","",VLOOKUP(F7,Lookups!B4:H8,6)) -> Productivity Gains | X12: =IF(F7="","",VLOOKUP(F7,Lookups!B4:H8,7)) -> Cost Savings | AJ12: Resources Allocated | AO12: 45962 | AR12: 45962 | AU12: =IF(AO12=$BK$3,"Missing Target",IF(AR12=$BK$3,IF($AZ$3>AO12,INT($AZ$3-AO12)&" Day(s) Overdue","Incomplete"),IF(AR12>AO12,INT(AR12-AO12)&" Day(s) Late",IF(AR12=AO12,"OK",INT(AO12-AR12)&" Day(s) Ahead")))) -> OK
F13: KPI | G13: Data Quality Score (Valid-data ratio) | O13: KPI | P13: Conversion Rates from AI-powered features | X13: KPI | Y13: Cost Savings | AG13: Develop | AJ13: Technical PoC validated | AO13: 45963 | AR13: 45963 | AU13: =IF(AO13=$BK$3,"Missing Target",IF(AR13=$BK$3,IF($AZ$3>AO13,INT($AZ$3-AO13)&" Day(s) Overdue","Incomplete"),IF(AR13>AO13,INT(AR13-AO13)&" Day(s) Late",IF(AR13=AO13,"OK",INT(AO13-AR13)&" Day(s) Ahead")))) -> OK
F14: How does this Project support this KPI? | O14: How does this Project support this KPI? | X14: How does this Project support this KPI? | AJ14: Dev roadmap documented | AO14: 45964 | AR14: 45964 | AU14: =IF(AO14=$BK$3,"Missing Target",IF(AR14=$BK$3,IF($AZ$3>AO14,INT($AZ$3-AO14)&" Day(s) Overdue","Incomplete"),IF(AR14>AO14,INT(AR14-AO14)&" Day(s) Late",IF(AR14=AO14,"OK",INT(AO14-AR14)&" Day(s) Ahead")))) -> OK
F15: Leads will be passed to our sales team and be qualifed as valid based on the type of product we sell. | O15: More qualified leads will lead to more sales and higher conversion rates. | X15: Saves time for our sales team to focus on more sales activities vs. lead generation activities. | AJ15: Coding started | AO15: 45965 | AR15: 45965 | AU15: =IF(AO15=$A$1,"Missing Target",IF(AR15=$A$1,IF($AZ$3>AO15,INT($AZ$3-AO15)&" Day(s) Overdue","Incomplete"),IF(AR15>AO15,INT(AR15-AO15)&" Day(s) Late",IF(AR15=AO15,"OK",INT(AO15-AR15)&" Day(s) Ahead")))) -> OK
AG16: Pilot | AJ16: Deployment to beta | AO16: 46022 | AU16: =IF(AO16=$A$1,"Missing Target",IF(AR16=$A$1,IF($AZ$3>AO16,INT($AZ$3-AO16)&" Day(s) Overdue","Incomplete"),IF(AR16>AO16,INT(AR16-AO16)&" Day(s) Late",IF(AR16=AO16,"OK",INT(AO16-AR16)&" Day(s) Ahead")))) -> Incomplete
B17: Contact | C17: Sandra.Crutcher@jonasfitness.com | AJ17: Initial metrics/feedback | AO17: 46037 | AU17: =IF(AO17=$A$1,"Missing Target",IF(AR17=$A$1,IF($AZ$3>AO17,INT($AZ$3-AO17)&" Day(s) Overdue","Incomplete"),IF(AR17>AO17,INT(AR17-AO17)&" Day(s) Late",IF(AR17=AO17,"OK",INT(AO17-AR17)&" Day(s) Ahead")))) -> Incomplete
B18: Prod Mgr | C18: Christian Menard | F18: How will you measure the KPI? | O18: How will you measure the KPI? | X18: How will you measure the KPI? | AJ18: Feedback affecting code | AO18: 46037 | AU18: =IF(AO18=$A$1,"Missing Target",IF(AR18=$A$1,IF($AZ$3>AO18,INT($AZ$3-AO18)&" Day(s) Overdue","Incomplete"),IF(AR18>AO18,INT(AR18-AO18)&" Day(s) Late",IF(AR18=AO18,"OK",INT(AO18-AR18)&" Day(s) Ahead")))) -> Incomplete
B19: Analyst | C19: Chase Winston | F19: Measure the amount of leads received compared to how many are valid, qualified leads. | O19: Compare our converstion rate from before the use of the tool to after the use of the tool. Conversion rate of number of demos completed to number of sales completed. | X19: Number of sales compared to number of leads generated and our conversion rate. | AG19: Live | AJ19: General release available | AO19: 46054 | AU19: =IF(AO19=$A$1,"Missing Target",IF(AR19=$A$1,IF($AZ$3>AO19,INT($AZ$3-AO19)&" Day(s) Overdue","Incomplete"),IF(AR19>AO19,INT(AR19-AO19)&" Day(s) Late",IF(AR19=AO19,"OK",INT(AO19-AR19)&" Day(s) Ahead")))) -> Incomplete
B20: Tech Lead | C20: Jim Peltier | AJ20: Success metrics tracking | AO20: 46055 | AU20: =IF(AO20=$A$1,"Missing Target",IF(AR20=$A$1,IF($AZ$3>AO20,INT($AZ$3-AO20)&" Day(s) Overdue","Incomplete"),IF(AR20>AO20,INT(AR20-AO20)&" Day(s) Late",IF(AR20=AO20,"OK",INT(AO20-AR20)&" Day(s) Ahead")))) -> Incomplete
B21: Exec | C21: Sandy Crutcher | AJ21: Feedback loop continuing | AO21: 46056 | AU21: =IF(AO21=$A$1,"Missing Target",IF(AR21=$A$1,IF($AZ$3>AO21,INT($AZ$3-AO21)&" Day(s) Overdue","Incomplete"),IF(AR21>AO21,INT(AR21-AO21)&" Day(s) Late",IF(AR21=AO21,"OK",INT(AO21-AR21)&" Day(s) Ahead")))) -> Incomplete
B23: WEEKLY KPI TRACKER | F23: 1 | G23: =F23+1 -> 2 | H23: =G23+1 -> 3 | I23: =H23+1 -> 4 | J23: =I23+1 -> 5 | K23: =J23+1 -> 6 | L23: =K23+1 -> 7 | M23: =L23+1 -> 8 | N23: =M23+1 -> 9 | ... BE23: =BD23+1 -> 52
B24: Week Ending | F24: 46022 | G24: =F24+7 -> 46029 | H24: =G24+7 -> 46036 | I24: =H24+7 -> 46043 | J24: =I24+7 -> 46050 | K24: =J24+7 -> 46057 | L24: =K24+7 -> 46064 | M24: =L24+7 -> 46071 | N24: =M24+7 -> 46078 | ... BE24: =BD24+7 -> 46379
B25: =G13&" TARGET" -> Data Quality Score (Valid-data ratio) TARGET | F25: =E25 -> 0 | G25: =F25 -> 0 | H25: =G25 -> 0 | I25: =H25 -> 0 | J25: =I25 -> 0 | K25: =J25 -> 0 | L25: =K25 -> 0 | M25: =L25 -> 0 | ... BE25: =BD25 -> 0
B26: Actual | F26: =E26 -> 0 | G26: 0 | H26: 0 | I26: 0 | J26: 0 | K26: 0 | L26: 0 | M26: 0 | N26: 0 | O26: 0 | P26: 0 | Q26: 0 | R26: 0 | S26: 0 | T26: 0 | U26: 0 | V26: 0 | W26: 0 | X26: 0 | Y26: 0 | Z26: 0 | AA26: 0 | AB26: 0 | AC26: 0 | AD26: 0 | AE26: 0 | AF26: 0 | AG26: 0 | AH26: 0 | AI26: 0 | AJ26: 0 | AK26: 0 | AL26: 0 | AM26: 0 | AN26: 0 | AO26: 0 | AP26: 0 | AQ26: 0 | AR26: 0 | AS26: 0 | AT26: 0 | AU26: 0 | AV26: 0 | AW26: 0 | AX26: 0 | AY26: 0 | AZ26: 0 | BA26: 0 | BB26: 0 | BC26: 0 | BD26: 0 | BE26: 0
B27: Delta | F27: =F26-F25 -> 0 | G27: =G26-G25 -> 0 | H27: =H26-H25 -> 0 | I27: =I26-I25 -> 0 | J27: =J26-J25 -> 0 | K27: =K26-K25 -> 0 | L27: =L26-L25 -> 0 | M27: =M26-M25 -> 0 | ... BE27: =BE26-BE25 -> 0
B28: Notes on this KPI (anything to add this week?)
B30: =P13&" TARGET" -> Conversion Rates from AI-powered features TARGET | F30: =E30 -> 0 | G30: =F30 -> 0 | H30: =G30 -> 0 | I30: =H30 -> 0 | J30: =I30 -> 0 | K30: =J30 -> 0 | L30: =K30 -> 0 | M30: =L30 -> 0 | ... BE30: =BD30 -> 0
B31: Actual | F31: =E31 -> 0 | G31: 0 | H31: 0 | I31: 0 | J31: 0 | K31: 0 | L31: 0 | M31: 0 | N31: 0 | O31: 0 | P31: 0 | Q31: 0 | R31: 0 | S31: 0 | T31: 0 | U31: 0 | V31: 0 | W31: 0 | X31: 0 | Y31: 0 | Z31: 0 | AA31: 0 | AB31: 0 | AC31: 0 | AD31: 0 | AE31: 0 | AF31: 0 | AG31: 0 | AH31: 0 | AI31: 0 | AJ31: 0 | AK31: 0 | AL31: 0 | AM31: 0 | AN31: 0 | AO31: 0 | AP31: 0 | AQ31: 0 | AR31: 0 | AS31: 0 | AT31: 0 | AU31: 0 | AV31: 0 | AW31: 0 | AX31: 0 | AY31: 0 | AZ31: 0 | BA31: 0 | BB31: 0 | BC31: 0 | BD31: 0 | BE31: 0
B32: Delta | F32: =F31-F30 -> 0 | G32: =G31-G30 -> 0 | H32: =H31-H30 -> 0 | I32: =I31-I30 -> 0 | J32: =J31-J30 -> 0 | K32: =K31-K30 -> 0 | L32: =L31-L30 -> 0 | M32: =M31-M30 -> 0 | ... BE32: =BE31-BE30 -> 0
B33: Notes on this KPI (anything to add this week?)
B35: =Y13&" TARGET" -> Cost Savings TARGET | F35: =E35 -> 0 | G35: =F35 -> 0 | H35: =G35 -> 0 | I35: =H35 -> 0 | J35: =I35 -> 0 | K35: =J35 -> 0 | L35: =K35 -> 0 | M35: =L35 -> 0 | ... BE35: =BD35 -> 0
B36: Actual | F36: 0 | G36: 0 | H36: 0 | I36: 0 | J36: 0 | K36: 0 | L36: 0 | M36: 0 | N36: 0 | O36: 0 | P36: 0 | Q36: 0 | R36: 0 | S36: 0 | T36: 0 | U36: 0 | V36: 0 | W36: 0 | X36: 0 | Y36: 0 | Z36: 0 | AA36: 0 | AB36: 0 | AC36: 0 | AD36: 0 | AE36: 0 | AF36: 0 | AG36: 0 | AH36: 0 | AI36: 0 | AJ36: 0 | AK36: 0 | AL36: 0 | AM36: 0 | AN36: 0 | AO36: 0 | AP36: 0 | AQ36: 0 | AR36: 0 | AS36: 0 | AT36: 0 | AU36: 0 | AV36: 0 | AW36: 0 | AX36: 0 | AY36: 0 | AZ36: 0 | BA36: 0 | BB36: 0 | BC36: 0 | BD36: 0 | BE36: 0
B37: Delta | F37: =F36-F35 -> 0 | G37: =G36-G35 -> 0 | H37: =H36-H35 -> 0 | I37: =I36-I35 -> 0 | J37: =J36-J35 -> 0 | K37: =K36-K35 -> 0 | L37: =L36-L35 -> 0 | M37: =M36-M35 -> 0 | ... BE37: =BE36-BE35 -> 0
B38: Notes on this KPI (anything to add this week?)
B41: Revenue Target | F41: =IF($X$12="Revenue Impact",F35,0) -> 0 | G41: =IF($X$12="Revenue Impact",G35,0) -> 0 | H41: =IF($X$12="Revenue Impact",H35,0) -> 0 | I41: =IF($X$12="Revenue Impact",I35,0) -> 0 | J41: =IF($X$12="Revenue Impact",J35,0) -> 0 | K41: =IF($X$12="Revenue Impact",K35,0) -> 0 | L41: =IF($X$12="Revenue Impact",L35,0) -> 0 | M41: =IF($X$12="Revenue Impact",M35,0) -> 0 | ... BE41: =IF($X$12="Revenue Impact",BE35,0) -> 0
B42: Revenue Actual | F42: =IF($X$12="Revenue Impact",F36,0) -> 0 | G42: =IF($X$12="Revenue Impact",G36,0) -> 0 | H42: =IF($X$12="Revenue Impact",H36,0) -> 0 | I42: =IF($X$12="Revenue Impact",I36,0) -> 0 | J42: =IF($X$12="Revenue Impact",J36,0) -> 0 | K42: =IF($X$12="Revenue Impact",K36,0) -> 0 | L42: =IF($X$12="Revenue Impact",L36,0) -> 0 | M42: =IF($X$12="Revenue Impact",M36,0) -> 0 | ... BE42: =IF($X$12="Revenue Impact",BE36,0) -> 0
B44: Cost Target | F44: =IF($X$12="Cost Savings",F35,0) -> 0 | G44: =IF($X$12="Cost Savings",G35,0) -> 0 | H44: =IF($X$12="Cost Savings",H35,0) -> 0 | I44: =IF($X$12="Cost Savings",I35,0) -> 0 | J44: =IF($X$12="Cost Savings",J35,0) -> 0 | K44: =IF($X$12="Cost Savings",K35,0) -> 0 | L44: =IF($X$12="Cost Savings",L35,0) -> 0 | M44: =IF($X$12="Cost Savings",M35,0) -> 0 | ... BE44: =IF($X$12="Cost Savings",BE35,0) -> 0
B45: Cost Actual | F45: =IF($X$12="Cost Savings",F36,0) -> 0 | G45: =IF($X$12="Cost Savings",G36,0) -> 0 | H45: =IF($X$12="Cost Savings",H36,0) -> 0 | I45: =IF($X$12="Cost Savings",I36,0) -> 0 | J45: =IF($X$12="Cost Savings",J36,0) -> 0 | K45: =IF($X$12="Cost Savings",K36,0) -> 0 | L45: =IF($X$12="Cost Savings",L36,0) -> 0 | M45: =IF($X$12="Cost Savings",M36,0) -> 0 | ... BE45: =IF($X$12="Cost Savings",BE36,0) -> 0
B47: Financial Target | F47: =F41+F44 -> 0 | G47: =G41+G44 -> 0 | H47: =H41+H44 -> 0 | I47: =I41+I44 -> 0 | J47: =J41+J44 -> 0 | K47: =K41+K44 -> 0 | L47: =L41+L44 -> 0 | M47: =M41+M44 -> 0 | ... BE47: =BE41+BE44 -> 0
B48: Financial Actual | F48: =F42+F45 -> 0 | G48: =G42+G45 -> 0 | H48: =H42+H45 -> 0 | I48: =I42+I45 -> 0 | J48: =J42+J45 -> 0 | K48: =K42+K45 -> 0 | L48: =L42+L45 -> 0 | M48: =M42+M45 -> 0 | ... BE48: =BE42+BE45 -> 0
E49: To Date
B50: Current Financial Target | E50: =MAX(F50:BE50) -> 0 | F50: =IF($AZ$3>F24,F47,0) -> 0 | G50: =IF($AZ$3>G24,G47,0) -> 0 | H50: =IF($AZ$3>H24,H47,0) -> 0 | I50: =IF($AZ$3>I24,I47,0) -> 0 | J50: =IF($AZ$3>J24,J47,0) -> 0 | K50: =IF($AZ$3>K24,K47,0) -> 0 | L50: =IF($AZ$3>L24,L47,0) -> 0 | M50: =IF($AZ$3>M24,M47,0) -> 0 | ... BE50: =IF($AZ$3>BE24,BE47,0) -> 0
B51: Current Financial Actual | E51: =MAX(F51:BE51) -> 0 | F51: =IF($AZ$3>F25,F48,0) -> 0 | G51: =IF($AZ$3>G25,G48,0) -> 0 | H51: =IF($AZ$3>H25,H48,0) -> 0 | I51: =IF($AZ$3>I25,I48,0) -> 0 | J51: =IF($AZ$3>J25,J48,0) -> 0 | K51: =IF($AZ$3>K25,K48,0) -> 0 | L51: =IF($AZ$3>L25,L48,0) -> 0 | M51: =IF($AZ$3>M25,M48,0) -> 0 | ... BE51: =IF($AZ$3>BE25,BE48,0) -> 0

Sheet Lookups
B3: Definition | C3: Value | D3: Definition2 | E3: Examples | F3: Assessment Criteria 2 | G3: Assessment Criteria 3 | H3: Assessment Criteria 4 | J3: KPI LISt | L3: Status Progress | M3: Weight | O3: Tasks | P3: Score | Q3: Multiplier | S3: Month | T3: Qtr | U3: Previous Quarter | W3: Qtr | X3: Start | Y3: End | AA3: KPI Categories | AC3: Ratio Impacted
B4: L1. Using external AI tools for basic internal productivity | C4: Simple Tool | D4: 10 | E4: ChatGPT for content, Co-Pilot for drafting emails, AI meeting summaries | F4: Adoption Rate | G4: Productivity Gains | H4: Cost Savings | J4: .... Select the primary KPI (Jonas Library) | L4: Dev | M4: 0.4 | O4: 0 | P4: Not Def | Q4: 0 | S4: 2025-7 | T4: 2025-Q3 | W4: 2025-Q3 | X4: 45839 | Y4: 45930 | AA4: Business Impact | AC4: R&D
B5: L2. Sophisticated AI tooling for development/operations but generally limited to a single department or workflow | C5: Complex Tool | D5: 25 | E5: AI-powered code review, automated testing, advanced development environments | F5: Integration Depth | G5: Process Improvement | H5: Skills Development | J5: # of Customers using the AI | L5: Idea | M5: 0.1 | O5: 1 | P5: Idea | Q5: 0.1 | S5: 2025-8 | T5: 2025-Q3 | W5: 2025-Q4 | X5: 45931 | Y5: 0 | AA5: Data Readiness & Governance | AC5: Maintenance
B6: L3. AI-powered internal business process improvements | C6: Internal Process | D6: 50 | E6: Automated customer support triage, intelligent lead scoring, predictive maintenance, churn analysis, scheduling | F6: Employee Satisfaction | G6: Productivity Gains | H6: Cost Savings | J6: % of Customers using the AI | L6: Live | M6: 1 | O6: 2 | P6: Idea | Q6: 0.1 | S6: 2025-9 | T6: 2025-Q3 | W6: 2026-Q1 | X6: 46023 | Y6: 46112 | AA6: Innovation & Scalability | AC6: S&M
B7: L4. Using AI to enhance existing customer-facing products | C7: Customer Feature - Existing | D7: 100 | E7: Smart data analysis in existing dashboards, intelligent recommendations, automated report generation | F7: Customer Adoption | G7: Usage Metrics | H7: Revenue Impact | J7: AI Literacy Initiatives Completion Rate | L7: Not Defined | M7: 0 | O7: 3 | P7: Idea | Q7: 0.1 | S7: 2025-10 | T7: 2025-Q4 | U7: 2025-Q3 | W7: 2026-Q2 | X7: 46113 | Y7: 46203 | AA7: Operational Efficiency | AC7: PS
B8: L5. Entirely new product capabilities powered by AI | C8: Customer Feature - New | D8: 200 | E8: Predictive analytics modules, AI-powered workflow automation, intelligent decision support systems | F8: Market Differentiation | G8: Competitive Advantage | H8: Revenue Impact | J8: Audit Frequency and Results | L8: Pilot | M8: 0.7 | O8: 4 | P8: Dev | Q8: 0.4 | S8: 2025-11 | T8: 2025-Q4 | U8: 2025-Q3 | W8: 2026-Q3 | X8: 46204 | Y8: 46295 | AA8: Risk & Governance | AC8: G&A
J9: Automation Rate | O9: 5 | P9: Dev | Q9: 0.4 | S9: 2025-12 | T9: 2025-Q4 | U9: 2025-Q3 | W9: 2026-Q4 | X9: 46296 | Y9: 46387 | AA9: Talent & Culture Readiness | AC9: M&A
J10: Consistency Scores | O10: 6 | P10: Dev | Q10: 0.4 | S10: 2026-1 | T10: 2026-Q1 | U10: 2025-Q4
J11: Conversion Rates from AI-powered features | O11: 7 | P11: Pilot | Q11: 0.7 | S11: 2026-2 | T11: 2026-Q1 | U11: 2025-Q4
J12: Cost Savings | O12: 8 | P12: Pilot | Q12: 0.7 | S12: 2026-3 | T12: 2026-Q1 | U12: 2025-Q4
J13: Customer Satisfaction Scores (CSAT, NPS) | O13: 9 | P13: Pilot | Q13: 0.7 | S13: 2026-4 | T13: 2026-Q2 | U13: 2026-Q1
J14: Data Accessibility (Time to Data Access) | O14: 10 | P14: Live | Q14: 1 | S14: 2026-5 | T14: 2026-Q2 | U14: 2026-Q1
J15: Data Quality Score (Valid-data ratio) | O15: 11 | P15: Live | Q15: 1 | S15: 2026-6 | T15: 2026-Q2 | U15: 2026-Q1
J16: Employee AI Tool Adoption Rate | O16: 12 | P16: Live | Q16: 1 | S16: 2026-7 | T16: 2026-Q3 | U16: 2026-Q2
J17: Employee Productivity Gains | S17: 2026-8 | T17: 2026-Q3 | U17: 2026-Q2
J18: Error Rate Reduction | S18: 2026-9 | T18: 2026-Q3 | U18: 2026-Q2
J19: Ethical Standards Adherence | S19: 2026-10 | T19: 2026-Q4 | U19: 2026-Q3
J20: Hallucination Detection Rate | S20: 2026-11 | T20: 2026-Q4 | U20: 2026-Q3
J21: Improvement in Decision-Making Speed | S21: 2026-12 | T21: 2026-Q4 | U21: 2026-Q3
J22: Market Share Expansion / New Market Entry
J23: Metadata Management Maturity
J24: New AI-enabled Products/Features
J25: Performance under Increased Load
J26: Process Cycle Time Reduction
J27: Regulatory Compliance Rate (Data Privacy)
J28: Revenue Growth from AI-enhanced products
J29: Successful Adaptation to New Use Cases
J30: Throughput
J31: Time Savings / Resolution Time Reduction
J32: Time-to-Market Reduction

Sheet KPI Library
A1: KPI Category | B1: KPI Name | C1: Definition/Explanation | D1: Example Metric/Calculation | E1: Relevance
A2: Business Impact | B2: Revenue Growth from AI-enhanced products | C2: Isolates the impact of AI-enabled strategies on revenue. | D2: % increase in revenue from AI-powered features | E2: Long-term, Strategic
B3: Cost Savings | C3: Quantifies financial benefits from AI-driven reductions in labor, resources, and time. | D3: "45 hours per week returned to team" 5, $X reduction in operational costs | E3: Short-term, Operational, Financial
B4: Customer Satisfaction Scores (CSAT, NPS) | C4: Measures AI's positive impact on user needs and product offerings. | D4: Comparison of before/after CSAT/NPS scores | E4: Short-term, Long-term, Customer Experience
B5: Time Savings / Resolution Time Reduction | C5: Time needed to complete tasks or resolve issues after AI implementation vs. before. | D5: "Customer issues resolved 40% faster month-over-month" 5 | E5: Short-term, Operational
B6: Market Share Expansion / New Market Entry | C6: Measures AI's facilitation of market growth or entry into new segments. | D6: Market penetration rates in new segments (%) 5 | E6: Long-term, Strategic
B7: Conversion Rates from AI-powered features | C7: Percentage of users completing a desired action via AI features. | D7: % increase in conversion rates | E7: Short-term, Strategic
A8: Operational Efficiency | B8: Process Cycle Time Reduction | C8: Measures improvement in process performance and cycle times due to AI. | D8: % reduction in cycle time for key processes | E8: Short-term, Operational
B9: Automation Rate | C9: Degree to which manual tasks are automated using AI-powered systems. | D9: "200 customer inquiries handled by AI per day" 5 | E9: Short-term, Operational
B10: Throughput | C10: Number of requests or tasks an AI system processes within a given timeframe. | D10: X requests per minute/hour | E10: Short-term, Operational
B11: Error Rate Reduction | C11: Percentage decrease in incorrect or invalid model outputs. | D11: % reduction in errors (e.g., defect detection rate) 3 | E11: Short-term, Operational, Quality
B12: Improvement in Decision-Making Speed | C12: How quickly a team can make decisions with AI assistance. | D12: % faster decision speed | E12: Short-term, Operational
A13: Talent & Culture Readiness | B13: Employee AI Tool Adoption Rate | C13: Percentage of eligible employees actively using AI tools. | D13: "75% of eligible employees actively using AI tools weekly" 5 | E13: Short-term, Cultural, Operational
B14: AI Literacy Initiatives Completion Rate | C14: Percentage of workforce completing AI training programs. | D14: % of workforce trained in AI fundamentals | E14: Long-term, Cultural
B15: Employee Productivity Gains | C15: Output per employee before and after AI implementation. | D15: % increase in output per employee | E15: Short-term, Operational, Human Impact
A16: Data Readiness & Governance | B16: Data Quality Score (Valid-data ratio) | C16: Percentage of data points meeting defined quality criteria. | D16: % of data points meeting quality standards | E16: Foundational, Ongoing
B17: Data Accessibility (Time to Data Access) | C17: Duration required to locate and access needed information. | D17: Hours/minutes to access specific datasets | E17: Foundational, Operational
B18: Regulatory Compliance Rate (Data Privacy) | C18: Percentage of AI processes/outputs adhering to legal/ethical data standards. | D18: % adherence to GDPR, CCPA, AI Act | E18: Foundational, Risk, Governance
B19: Metadata Management Maturity | C19: Effectiveness of practices for data discovery, understanding, and utilization. | D19: Score on a 1-5 scale for metadata completeness/accuracy | E19: Foundational, Governance
A20: Innovation & Scalability | B20: New AI-enabled Products/Features | C20: Count of new products or features directly attributed to AI. | D20: Number of new AI-driven features launched | E20: Long-term, Strategic, Innovation
B21: Time-to-Market Reduction | C21: Acceleration of product development cycles with AI. | D21: % reduction in time-to-market for new offerings | E21: Long-term, Strategic, Innovation
B22: Performance under Increased Load | C22: AI solution's performance (e.g., response time) under higher usage volumes. | D22: Response time at 2x, 5x, 10x normal usage 5 | E22: Long-term, Operational, Scalability
B23: Successful Adaptation to New Use Cases | C23: Percentage of attempted AI adaptations to new use cases that succeed. | D23: % of successful new use case adaptations 5 | E23: Long-term, Strategic, Scalability
A24: Risk & Governance | B24: Ethical Standards Adherence | C24: Measures AI model's fairness, transparency, accountability, and responsible use. | D24: Score based on ethical guideline compliance (e.g., bias detection, demographic parity) 3 | E24: Ongoing, Risk, Governance
B25: Audit Frequency and Results | C25: How often AI audits are conducted and thoroughness of system examinations. | D25: Number of audits per quarter, audit findings resolution rate | E25: Ongoing, Risk, Governance
B26: Hallucination Detection Rate | C26: For generative AI, measures the frequency of AI creating incorrect information. | D26: % of detected hallucinations 19 | E26: Ongoing, Risk, Quality
B27: Consistency Scores | C27: Measures consistent responses to similar inputs for AI models. | D27: Statistical variance in responses to varied queries 19 | E27: Ongoing, Quality, Reliability
